Workbook

Sheet Comece Aqui
B2: MESA ÁGIL · PLANEJAMENTO FINANCEIRO · GUIA RÁPIDO | D2: ▦ DASHBOARD →
B4: 01 | C4: PREMISSAS — preços dos planos (já vêm do escopo), cenários de venda, custos variáveis, marketing e custos fixos. Os campos AMARELO-CLAROS você edita. | D4: ABRIR →
B5: 02 | C5: PREMISSAS › Cenário em uso — escolha Pessimista, Realista ou Otimista. Projeção, Fluxo de Caixa, Unit Economics e Dashboard passam a usar esse cenário. | D5: ABRIR →
B6: 03 | C6: PROJEÇÃO 24 MESES — clientes (novos, cancelados, ativos por plano), MRR, ARR, ticket médio, custos, margem bruta e lucro líquido mês a mês. | D6: ABRIR →
B7: 04 | C7: FLUXO DE CAIXA — separa o dinheiro das mensalidades do dinheiro do plano anual (que entra de uma vez) e mostra a receita anual ainda a reconhecer. | D7: ABRIR →
B8: 05 | C8: UNIT ECONOMICS — LTV, CAC, LTV/CAC e payback por plano e na média, mais o ponto de equilíbrio em número de clientes. | D8: ABRIR →
B9: 06 | C9: CENÁRIOS — os três cenários lado a lado, sempre calculados ao mesmo tempo, com gráficos comparativos. | D9: ABRIR →
B10: 07 | C10: DASHBOARD — resumo do cenário em uso: indicadores-chave e gráficos. Tudo automático. | D10: ABRIR →
B11: 08 | C11: MOTOR CENÁRIOS — cálculo automático que alimenta a aba Cenários. Não precisa mexer. | D11: ABRIR →
B13: IMPORTANTE | C13: Só os PREÇOS dos planos vieram do escopo. Todos os outros campos amarelo-claros (clientes, churn, mix, custos, marketing) são EXEMPLOS estimados para a planilha já sair funcionando — troque pelos seus dados reais.
B15: CORES | C15: Campos AMARELO-CLAROS com borda mostarda = você preenche (clique neles para ver uma dica). Células brancas = cálculo automático, não digite por cima. Vermelho = resultado negativo. Verde = resultado positivo.
B17: COMO LER | C17: Receita (MRR, lucro) é por COMPETÊNCIA: o plano anual é distribuído em 12 meses. Caixa é quando o dinheiro ENTRA: o plano anual entra inteiro no mês da venda/renovação. Clientes aparecem com casas decimais porque são médias estatísticas.
C19: Mesa Ágil (Powered by AIA) · comanda digital SaaS para barracas, food trucks, lanchonetes e restaurantes pequenos · mesaagil.pages.dev

Sheet Dashboard
B1: ⌂ Início
B2: ="DASHBOARD · "&UPPER(Premissas!$C$6)&" · CENÁRIO "&UPPER(Premissas!$C$9) -> DASHBOARD · MESA ÁGIL · CENÁRIO REALISTA
B3: Tudo automático, sempre no cenário em uso. Para trocar o cenário ou os números, vá em Premissas. | Q3: Premissas →
B5: PRINCIPAIS NÚMEROS · MÊS 24
B6: CLIENTES ATIVOS | E6: MRR | H6: ARR | K6: LUCRO LÍQUIDO | N6: LTV / CAC | Q6: PAYBACK DO CAC
B7: ='Projeção 24 meses'!$G$29 -> 338.01863 | E7: ='Projeção 24 meses'!$L$29 -> 21200.282 | H7: ='Projeção 24 meses'!$M$29 -> 254403.38 | K7: ='Projeção 24 meses'!$X$29 -> 12304.604 | N7: ='Unit Economics'!$K$18 -> 10.505223 | Q7: ='Unit Economics'!$L$18 -> 2.0768889
B8: no mês 24 | E8: ='Projeção 24 meses'!$L$17 -> 7530.4908 | H8: MRR × 12 | K8: no mês 24 | N8: ideal ≥ 3x | Q8: ideal ≤ 12 meses
B10: TICKET MÉDIO | E10: MARGEM BRUTA | H10: EQUILÍBRIO | K10: 1º MÊS COM LUCRO | N10: LUCRO ACUMULADO | Q10: MENOR SALDO DE CAIXA
B11: ='Projeção 24 meses'!$N$29 -> 62.719269 | E11: ='Projeção 24 meses'!$S$29 -> 0.89090935 | H11: ='Unit Economics'!$C$33 -> 61 | K11: ='Unit Economics'!$C$36 -> 46600 | N11: ='Projeção 24 meses'!$Y$29 -> 62578.916 | Q11: ='Fluxo de Caixa'!$G$34 -> -9905.4545
B12: ARPU | E12: após impostos, gateway, infra | H12: cobrem os custos fixos | K12: lucro líquido > 0 | N12: soma dos 24 meses | Q12: capital necessário
B14: RUMO AO EQUILÍBRIO
B15: Clientes ativos no mês 24 × clientes que cobrem os custos fixos | H15: =REPT("█",ROUND(MIN(1,MAX(0,N(O15)))*30,0))&REPT("░",30-ROUND(MIN(1,MAX(0,N(O15)))*30,0)) -> ██████████████████████████████ | O15: =IFERROR('Unit Economics'!$C$35/'Unit Economics'!$C$33,0) -> 5.541289 | P15: ='Unit Economics'!$C$33 -> 61
B17: EVOLUÇÃO EM 24 MESES
B52: ALERTAS
B53: =IF(V53,"✖ LTV/CAC abaixo de 3x — o cliente devolve pouco do que custa","✔ LTV/CAC saudável (3x ou mais)") -> ✔ LTV/CAC saudável (3x ou mais) | V53: ='Unit Economics'!$K$18<3 -> FALSE
B54: =IF(V54,"✖ Payback do CAC acima de 12 meses","✔ Payback do CAC em até 12 meses") -> ✔ Payback do CAC em até 12 meses | V54: ='Unit Economics'!$L$18>12 -> FALSE
B55: =IF(V55,"✖ O caixa fica negativo em algum mês — é preciso capital inicial","✔ O caixa nunca fica negativo") -> ✖ O caixa fica negativo em algum mês — é preciso capital inicial | V55: ='Fluxo de Caixa'!$G$34<0 -> TRUE
B56: =IF(V56,"✖ Ainda dá prejuízo no mês 24","✔ Operação lucrativa no mês 24") -> ✔ Operação lucrativa no mês 24 | V56: ='Projeção 24 meses'!$X$29<0 -> FALSE

Sheet Premissas
B1: ⌂ Início | C1: ▦ Dashboard
B2: PREMISSAS · TODOS OS CAMPOS EDITÁVEIS
B3: Campos AMARELO-CLAROS = você preenche. Preços dos planos vieram do escopo; o restante são exemplos para substituir pelos seus números.
B5: GERAL
B6: Nome do produto | C6: Mesa Ágil
B7: Mês de início da projeção | C7: 46296 | D7: Primeiro mês de vendas (mês 1 da projeção)
B8: Caixa inicial (R$) | C8: 0 | D8: Dinheiro já disponível no mês 1
B9: Cenário em uso | C9: Realista | D9: Pessimista, Realista ou Otimista — muda Projeção, Fluxo, Unit Economics e Dashboard
B11: PREÇOS DOS PLANOS (definidos no escopo)
B12: PLANO | C12: MENSAL | D12: DESCONTO ANUAL | E12: ANUAL (POR MÊS) | F12: ANUAL (COBRADO DE UMA VEZ) | G12: O QUE INCLUI
B13: Essencial | C13: 57.9 | D13: 0.15 | E13: =C13*(1-D13) -> 49.215 | F13: =ROUND(E13*12,2) -> 590.58 | G13: 1 barraca, lançar pedido, cozinha, chamada de senha, relatório do dia, histórico de 7 dias
B14: Pro | C14: 87.9 | D14: 0.2 | E14: =C14*(1-D14) -> 70.32 | F14: =ROUND(E14*12,2) -> 843.84 | G14: Tudo do Essencial + várias barracas, histórico completo, exportar, custo/lucro/taxas, suporte prioritário no WhatsApp
B15: No plano anual a RECEITA é reconhecida em 12 parcelas iguais (cobrado ÷ 12), mas o CAIXA entra inteiro no mês da venda.
B17: PREMISSAS DE VENDA POR CENÁRIO
B18: PREMISSA | C18: PESSIMISTA | D18: REALISTA | E18: OTIMISTA | F18: EM USO | G18: COMO PREENCHER
B19: Novos clientes pagantes no mês 1 | C19: 4 | D19: 8 | E19: 15 | F19: =INDEX(C19:E19,MATCH($C$9,$C$18:$E$18,0)) -> 8 | G19: Quantas assinaturas novas no primeiro mês de vendas
B20: Crescimento mensal dos novos clientes | C20: 0.03 | D20: 0.07 | E20: 0.12 | F20: =INDEX(C20:E20,MATCH($C$9,$C$18:$E$18,0)) -> 0.07 | G20: Quanto o nº de novos clientes cresce a cada mês. Ex.: 7% → 8; 8,6; 9,2...
B21: Churn mensal (plano mensal) | C21: 0.08 | D21: 0.05 | E21: 0.03 | F21: =INDEX(C21:E21,MATCH($C$9,$C$18:$E$18,0)) -> 0.05 | G21: % dos clientes do plano MENSAL que cancelam por mês
B22: Renovação do plano anual | C22: 0.5 | D22: 0.65 | E22: 0.8 | F22: =INDEX(C22:E22,MATCH($C$9,$C$18:$E$18,0)) -> 0.65 | G22: % dos clientes anuais que renovam ao fim dos 12 meses
B23: % dos novos clientes no plano Pro | C23: 0.15 | D23: 0.25 | E23: 0.35 | F23: =INDEX(C23:E23,MATCH($C$9,$C$18:$E$18,0)) -> 0.25 | G23: Mix de planos: o restante vai para o Essencial
B24: % dos novos clientes no plano anual | C24: 0.1 | D24: 0.2 | E24: 0.3 | F24: =INDEX(C24:E24,MATCH($C$9,$C$18:$E$18,0)) -> 0.2 | G24: Mix de cobrança: o restante paga mensal
B25: Conversão do teste grátis | C25: 0.1 | D25: 0.2 | E25: 0.3 | F25: =INDEX(C25:E25,MATCH($C$9,$C$18:$E$18,0)) -> 0.2 | G25: % dos testes grátis que viram pagantes. Sem teste grátis? Coloque 100%
B27: CUSTOS VARIÁVEIS POR CLIENTE
B28: Taxa do gateway de pagamento (%) | C28: 0.035 | D28: % cobrado pelo gateway (cartão/Pix/boleto) sobre cada cobrança. Média ponderada.
B29: Tarifa fixa por cobrança (R$) | C29: 0.49 | D29: Valor fixo por cobrança gerada (se houver). Mensal = 1 cobrança/mês; anual = 1 por ano.
B30: Imposto sobre faturamento (%) | C30: 0.06 | D30: Alíquota do Simples Nacional (SaaS costuma ser Anexo III, a partir de 6%). Confirme com o contador.
B31: Infraestrutura por cliente ativo (R$/mês) | C31: 0.5 | D31: Custo extra de servidor/banco/tempo real para cada cliente ativo.
B33: AQUISIÇÃO (MARKETING)
B34: Investimento em anúncios no mês 1 (R$) | C34: 1500 | D34: Meta/Google/Instagram pago no primeiro mês
B35: Crescimento mensal do investimento em anúncios | C35: 0.03 | D35: Quanto o orçamento de anúncios sobe por mês. 0% = fixo
B36: % dos novos clientes vindos de indicação/revenda | C36: 0.2 | D36: Parte dos novos clientes que gera comissão
B37: Comissão por cliente indicado (R$, paga uma vez) | C37: 30 | D37: Valor pago ao indicador/revendedor por cliente novo. 0 se não houver
B38: O CAC não é digitado: ele é calculado (anúncios + comissões ÷ novos clientes) na Projeção e no Unit Economics.
B40: CUSTOS FIXOS MENSAIS
B41: DESCRIÇÃO | C41: VALOR MENSAL | D41: A PARTIR DO MÊS | G41: OBSERVAÇÃO
B42: Hospedagem — Cloudflare Pages | C42: 0 | D42: 1 | G42: Plano gratuito atende no início
B43: Backend, banco de dados e tempo real | C43: 150 | D43: 1 | G43: Ex.: Supabase/Firebase pago (~US$ 25)
B44: Domínio | C44: 10 | D44: 1 | G44: Valor anual ÷ 12
B45: E-mail profissional | C45: 30 | D45: 1 | G45: Google Workspace, Zoho etc.
B46: Ferramentas de IA | C46: 110 | D46: 1 | G46: Assinaturas de IA usadas no desenvolvimento/atendimento
B47: Design (Canva etc.) | C47: 35 | D47: 1
B48: Site WordPress/Elementor + hospedagem | C48: 60 | D48: 1 | G48: Site institucional / página de vendas
B49: WhatsApp de atendimento (número/API) | C49: 50 | D49: 1 | G49: Suporte prioritário do plano Pro
B50: Pró-labore | C50: 1500 | D50: 1 | G50: Sua retirada mensal
B51: Suporte e atendimento (pessoa) | C51: 1200 | D51: 7 | G51: Exemplo: contratar a partir do mês 7
B52: Contador | C52: 250 | D52: 1
B53: Impostos/taxas fixas (DAS MEI, anuidades) | C53: 0 | D53: 1 | G53: No Simples o imposto é % (linha 30); aqui só o que é fixo
B62: TOTAL (todos os custos já ativos) | C62: =SUM(C42:C61) -> 3395

Sheet Projeção 24 meses
B1: ⌂ Início | C1: ▦ Dashboard
B2: ="PROJEÇÃO 24 MESES · CENÁRIO "&UPPER(Premissas!$C$9) -> PROJEÇÃO 24 MESES · CENÁRIO REALISTA
B3: Clientes, MRR, custos e lucro por COMPETÊNCIA (o plano anual é distribuído em 12 meses). Tudo automático — edite só a aba Premissas.
B4: CLIENTES | L4: RECEITA E RESULTADO | AC4: CÁLCULOS AUXILIARES
B5: Nº | C5: MÊS | D5: NOVOS CLIENTES | E5: TESTES GRÁTIS NECESSÁRIOS | F5: CANCELADOS | G5: CLIENTES ATIVOS | H5: ESSENCIAL MENSAL | I5: ESSENCIAL ANUAL | J5: PRO MENSAL | K5: PRO ANUAL | L5: MRR (RECEITA RECORRENTE) | M5: ARR (MRR × 12) | N5: TICKET MÉDIO (ARPU) | O5: IMPOSTOS | P5: GATEWAY | Q5: INFRA POR CLIENTE | R5: MARGEM BRUTA | S5: MARGEM BRUTA % | T5: CUSTOS FIXOS | U5: ANÚNCIOS | V5: COMISSÕES DE INDICAÇÃO | W5: CUSTOS TOTAIS | X5: LUCRO LÍQUIDO | Y5: LUCRO ACUMULADO | Z5: CAC DO MÊS | AA5: CLIENTES P/ EQUILÍBRIO | AC5: NOVOS ESS. MENSAL | AD5: NOVOS ESS. ANUAL | AE5: NOVOS PRO MENSAL | AF5: NOVOS PRO ANUAL | AG5: COBRANÇAS ANUAIS ESS. (NOVOS + RENOV.) | AH5: COBRANÇAS ANUAIS PRO (NOVOS + RENOV.) | AI5: ANUAIS QUE NÃO RENOVARAM | AJ5: Nº DE COBRANÇAS NO MÊS | AK5: MÊS COM LUCRO?
B6: =1 -> 1 | C6: =EDATE(Premissas!$C$7,B6-1) -> 46296 | D6: =Premissas!$F$19*(1+Premissas!$F$20)^(B6-1) -> 8 | E6: =IFERROR(D6/Premissas!$F$25,0) -> 40 | F6: =(N(H5)+N(J5))*Premissas!$F$21+AI6 -> 0 | G6: =H6+I6+J6+K6 -> 8 | H6: =N(H5)*(1-Premissas!$F$21)+AC6 -> 4.8 | I6: =SUM(INDEX($AG$6:$AG$29,MAX(1,B6-11)):INDEX($AG$6:$AG$29,B6)) -> 1.2 | J6: =N(J5)*(1-Premissas!$F$21)+AE6 -> 1.6 | K6: =SUM(INDEX($AH$6:$AH$29,MAX(1,B6-11)):INDEX($AH$6:$AH$29,B6)) -> 0.4 | L6: =H6*Premissas!$C$13+I6*Premissas!$F$13/12+J6*Premissas!$C$14+K6*Premissas!$F$14/12 -> 505.746 | M6: =L6*12 -> 6068.952 | N6: =IFERROR(L6/G6,0) -> 63.21825 | O6: =L6*Premissas!$C$30 -> 30.34476 | P6: =L6*Premissas!$C$28+AJ6*Premissas!$C$29 -> 21.62111 | Q6: =G6*Premissas!$C$31 -> 4 | R6: =L6-O6-P6-Q6 -> 449.78013 | S6: =IFERROR(R6/L6,0) -> 0.88933997 | T6: =SUMPRODUCT(Premissas!$C$42:$C$61,--(Premissas!$D$42:$D$61<=B6)) -> 2195 | U6: =Premissas!$C$34*(1+Premissas!$C$35)^(B6-1) -> 1500 | V6: =D6*Premissas!$C$36*Premissas!$C$37 -> 48 | W6: =O6+P6+Q6+T6+U6+V6 -> 3798.9659 | X6: =L6-W6 -> -3293.2199 | Y6: =N(Y5)+X6 -> -3293.2199 | Z6: =IFERROR((U6+V6)/D6,0) -> 193.5 | AA6: =IFERROR(T6/(R6/G6),0) -> 39.041298 | AC6: =D6*(1-Premissas!$F$23)*(1-Premissas!$F$24) -> 4.8 | AD6: =D6*(1-Premissas!$F$23)*Premissas!$F$24 -> 1.2 | AE6: =D6*Premissas!$F$23*(1-Premissas!$F$24) -> 1.6 | AF6: =D6*Premissas!$F$23*Premissas!$F$24 -> 0.4 | AG6: =AD6+IF(B6>12,INDEX($AD$6:$AD$29,B6-12)*Premissas!$F$22,0) -> 1.2 | AH6: =AF6+IF(B6>12,INDEX($AF$6:$AF$29,B6-12)*Premissas!$F$22,0) -> 0.4 | AI6: =IF(B6>12,(INDEX($AD$6:$AD$29,B6-12)+INDEX($AF$6:$AF$29,B6-12))*(1-Premissas!$F$22),0) -> 0 | AJ6: =H6+J6+AG6+AH6 -> 8 | AK6: =IF(X6>0,B6,"")
B7: =B6+1 -> 2 | C7: =EDATE(Premissas!$C$7,B7-1) -> 46327 | D7: =Premissas!$F$19*(1+Premissas!$F$20)^(B7-1) -> 8.56 | E7: =IFERROR(D7/Premissas!$F$25,0) -> 42.8 | F7: =(N(H6)+N(J6))*Premissas!$F$21+AI7 -> 0.32 | G7: =H7+I7+J7+K7 -> 16.24 | H7: =N(H6)*(1-Premissas!$F$21)+AC7 -> 9.696 | I7: =SUM(INDEX($AG$6:$AG$29,MAX(1,B7-11)):INDEX($AG$6:$AG$29,B7)) -> 2.484 | J7: =N(J6)*(1-Premissas!$F$21)+AE7 -> 3.232 | K7: =SUM(INDEX($AH$6:$AH$29,MAX(1,B7-11)):INDEX($AH$6:$AH$29,B7)) -> 0.828 | L7: =H7*Premissas!$C$13+I7*Premissas!$F$13/12+J7*Premissas!$C$14+K7*Premissas!$F$14/12 -> 1025.9662 | M7: =L7*12 -> 12311.595 | N7: =IFERROR(L7/G7,0) -> 63.17526 | O7: =L7*Premissas!$C$30 -> 61.557973 | P7: =L7*Premissas!$C$28+AJ7*Premissas!$C$29 -> 43.082418 | Q7: =G7*Premissas!$C$31 -> 8.12 | R7: =L7-O7-P7-Q7 -> 913.20583 | S7: =IFERROR(R7/L7,0) -> 0.89009347 | T7: =SUMPRODUCT(Premissas!$C$42:$C$61,--(Premissas!$D$42:$D$61<=B7)) -> 2195 | U7: =Premissas!$C$34*(1+Premissas!$C$35)^(B7-1) -> 1545 | V7: =D7*Premissas!$C$36*Premissas!$C$37 -> 51.36 | W7: =O7+P7+Q7+T7+U7+V7 -> 3904.1204 | X7: =L7-W7 -> -2878.1542 | Y7: =N(Y6)+X7 -> -6171.374 | Z7: =IFERROR((U7+V7)/D7,0) -> 186.49065 | AA7: =IFERROR(T7/(R7/G7),0) -> 39.034792 | AC7: =D7*(1-Premissas!$F$23)*(1-Premissas!$F$24) -> 5.136 | AD7: =D7*(1-Premissas!$F$23)*Premissas!$F$24 -> 1.284 | AE7: =D7*Premissas!$F$23*(1-Premissas!$F$24) -> 1.712 | AF7: =D7*Premissas!$F$23*Premissas!$F$24 -> 0.428 | AG7: =AD7+IF(B7>12,INDEX($AD$6:$AD$29,B7-12)*Premissas!$F$22,0) -> 1.284 | AH7: =AF7+IF(B7>12,INDEX($AF$6:$AF$29,B7-12)*Premissas!$F$22,0) -> 0.428 | AI7: =IF(B7>12,(INDEX($AD$6:$AD$29,B7-12)+INDEX($AF$6:$AF$29,B7-12))*(1-Premissas!$F$22),0) -> 0 | AJ7: =H7+J7+AG7+AH7 -> 14.64 | AK7: =IF(X7>0,B7,"")
B8: =B7+1 -> 3 | C8: =EDATE(Premissas!$C$7,B8-1) -> 46357 | D8: =Premissas!$F$19*(1+Premissas!$F$20)^(B8-1) -> 9.1592 | E8: =IFERROR(D8/Premissas!$F$25,0) -> 45.796 | F8: =(N(H7)+N(J7))*Premissas!$F$21+AI8 -> 0.6464 | G8: =H8+I8+J8+K8 -> 24.7528 | H8: =N(H7)*(1-Premissas!$F$21)+AC8 -> 14.70672 | I8: =SUM(INDEX($AG$6:$AG$29,MAX(1,B8-11)):INDEX($AG$6:$AG$29,B8)) -> 3.85788 | J8: =N(J7)*(1-Premissas!$F$21)+AE8 -> 4.90224 | K8: =SUM(INDEX($AH$6:$AH$29,MAX(1,B8-11)):INDEX($AH$6:$AH$29,B8)) -> 1.28596 | L8: =H8*Premissas!$C$13+I8*Premissas!$F$13/12+J8*Premissas!$C$14+K8*Premissas!$F$14/12 -> 1562.7203 | M8: =L8*12 -> 18752.643 | N8: =IFERROR(L8/G8,0) -> 63.13307 | O8: =L8*Premissas!$C$30 -> 93.763215 | P8: =L8*Premissas!$C$28+AJ8*Premissas!$C$29 -> 65.201201 | Q8: =G8*Premissas!$C$31 -> 12.3764 | R8: =L8-O8-P8-Q8 -> 1391.3794 | S8: =IFERROR(R8/L8,0) -> 0.89035733 | T8: =SUMPRODUCT(Premissas!$C$42:$C$61,--(Premissas!$D$42:$D$61<=B8)) -> 2195 | U8: =Premissas!$C$34*(1+Premissas!$C$35)^(B8-1) -> 1591.35 | V8: =D8*Premissas!$C$36*Premissas!$C$37 -> 54.9552 | W8: =O8+P8+Q8+T8+U8+V8 -> 4012.646 | X8: =L8-W8 -> -2449.9258 | Y8: =N(Y7)+X8 -> -8621.2998 | Z8: =IFERROR((U8+V8)/D8,0) -> 179.74334 | AA8: =IFERROR(T8/(R8/G8),0) -> 39.049302 | AC8: =D8*(1-Premissas!$F$23)*(1-Premissas!$F$24) -> 5.49552 | AD8: =D8*(1-Premissas!$F$23)*Premissas!$F$24 -> 1.37388 | AE8: =D8*Premissas!$F$23*(1-Premissas!$F$24) -> 1.83184 | AF8: =D8*Premissas!$F$23*Premissas!$F$24 -> 0.45796 | AG8: =AD8+IF(B8>12,INDEX($AD$6:$AD$29,B8-12)*Premissas!$F$22,0) -> 1.37388 | AH8: =AF8+IF(B8>12,INDEX($AF$6:$AF$29,B8-12)*Premissas!$F$22,0) -> 0.45796 | AI8: =IF(B8>12,(INDEX($AD$6:$AD$29,B8-12)+INDEX($AF$6:$AF$29,B8-12))*(1-Premissas!$F$22),0) -> 0 | AJ8: =H8+J8+AG8+AH8 -> 21.4408 | AK8: =IF(X8>0,B8,"")
B9: =B8+1 -> 4 | C9: =EDATE(Premissas!$C$7,B9-1) -> 46388 | D9: =Premissas!$F$19*(1+Premissas!$F$20)^(B9-1) -> 9.800344 | E9: =IFERROR(D9/Premissas!$F$25,0) -> 49.00172 | F9: =(N(H8)+N(J8))*Premissas!$F$21+AI9 -> 0.980448 | G9: =H9+I9+J9+K9 -> 33.572696 | H9: =N(H8)*(1-Premissas!$F$21)+AC9 -> 19.85159 | I9: =SUM(INDEX($AG$6:$AG$29,MAX(1,B9-11)):INDEX($AG$6:$AG$29,B9)) -> 5.3279316 | J9: =N(J8)*(1-Premissas!$F$21)+AE9 -> 6.6171968 | K9: =SUM(INDEX($AH$6:$AH$29,MAX(1,B9-11)):INDEX($AH$6:$AH$29,B9)) -> 1.7759772 | L9: =H9*Premissas!$C$13+I9*Premissas!$F$13/12+J9*Premissas!$C$14+K9*Premissas!$F$14/12 -> 2118.1596 | M9: =L9*12 -> 25417.915 | N9: =IFERROR(L9/G9,0) -> 63.091732 | O9: =L9*Premissas!$C$30 -> 127.08957 | P9: =L9*Premissas!$C$28+AJ9*Premissas!$C$29 -> 88.065724 | Q9: =G9*Premissas!$C$31 -> 16.786348 | R9: =L9-O9-P9-Q9 -> 1886.2179 | S9: =IFERROR(R9/L9,0) -> 0.8904985 | T9: =SUMPRODUCT(Premissas!$C$42:$C$61,--(Premissas!$D$42:$D$61<=B9)) -> 2195 | U9: =Premissas!$C$34*(1+Premissas!$C$35)^(B9-1) -> 1639.0905 | V9: =D9*Premissas!$C$36*Premissas!$C$37 -> 58.802064 | W9: =O9+P9+Q9+T9+U9+V9 -> 4124.8342 | X9: =L9-W9 -> -2006.6747 | Y9: =N(Y8)+X9 -> -10627.974 | Z9: =IFERROR((U9+V9)/D9,0) -> 173.24826 | AA9: =IFERROR(T9/(R9/G9),0) -> 39.068693 | AC9: =D9*(1-Premissas!$F$23)*(1-Premissas!$F$24) -> 5.8802064 | AD9: =D9*(1-Premissas!$F$23)*Premissas!$F$24 -> 1.4700516 | AE9: =D9*Premissas!$F$23*(1-Premissas!$F$24) -> 1.9600688 | AF9: =D9*Premissas!$F$23*Premissas!$F$24 -> 0.4900172 | AG9: =AD9+IF(B9>12,INDEX($AD$6:$AD$29,B9-12)*Premissas!$F$22,0) -> 1.4700516 | AH9: =AF9+IF(B9>12,INDEX($AF$6:$AF$29,B9-12)*Premissas!$F$22,0) -> 0.4900172 | AI9: =IF(B9>12,(INDEX($AD$6:$AD$29,B9-12)+INDEX($AF$6:$AF$29,B9-12))*(1-Premissas!$F$22),0) -> 0 | AJ9: =H9+J9+AG9+AH9 -> 28.428856 | AK9: =IF(X9>0,B9,"")
B10: =B9+1 -> 5 | C10: =EDATE(Premissas!$C$7,B10-1) -> 46419 | D10: =Premissas!$F$19*(1+Premissas!$F$20)^(B10-1) -> 10.486368 | E10: =IFERROR(D10/Premissas!$F$25,0) -> 52.43184 | F10: =(N(H9)+N(J9))*Premissas!$F$21+AI10 -> 1.3234394 | G10: =H10+I10+J10+K10 -> 42.735625 | H10: =N(H9)*(1-Premissas!$F$21)+AC10 -> 25.150832 | I10: =SUM(INDEX($AG$6:$AG$29,MAX(1,B10-11)):INDEX($AG$6:$AG$29,B10)) -> 6.9008868 | J10: =N(J9)*(1-Premissas!$F$21)+AE10 -> 8.3836106 | K10: =SUM(INDEX($AH$6:$AH$29,MAX(1,B10-11)):INDEX($AH$6:$AH$29,B10)) -> 2.3002956 | L10: =H10*Premissas!$C$13+I10*Premissas!$F$13/12+J10*Premissas!$C$14+K10*Premissas!$F$14/12 -> 2694.5365 | M10: =L10*12 -> 32334.437 | N10: =IFERROR(L10/G10,0) -> 63.051294 | O10: =L10*Premissas!$C$30 -> 161.67219 | P10: =L10*Premissas!$C$28+AJ10*Premissas!$C$29 -> 111.76832 | Q10: =G10*Premissas!$C$31 -> 21.367812 | R10: =L10-O10-P10-Q10 -> 2399.7281 | S10: =IFERROR(R10/L10,0) -> 0.89059034 | T10: =SUMPRODUCT(Premissas!$C$42:$C$61,--(Premissas!$D$42:$D$61<=B10)) -> 2195 | U10: =Premissas!$C$34*(1+Premissas!$C$35)^(B10-1) -> 1688.2632 | V10: =D10*Premissas!$C$36*Premissas!$C$37 -> 62.918208 | W10: =O10+P10+Q10+T10+U10+V10 -> 4240.9897 | X10: =L10-W10 -> -1546.4533 | Y10: =N(Y9)+X10 -> -12174.428 | Z10: =IFERROR((U10+V10)/D10,0) -> 166.99599 | AA10: =IFERROR(T10/(R10/G10),0) -> 39.089718 | AC10: =D10*(1-Premissas!$F$23)*(1-Premissas!$F$24) -> 6.2918208 | AD10: =D10*(1-Premissas!$F$23)*Premissas!$F$24 -> 1.5729552 | AE10: =D10*Premissas!$F$23*(1-Premissas!$F$24) -> 2.0972736 | AF10: =D10*Premissas!$F$23*Premissas!$F$24 -> 0.5243184 | AG10: =AD10+IF(B10>12,INDEX($AD$6:$AD$29,B10-12)*Premissas!$F$22,0) -> 1.5729552 | AH10: =AF10+IF(B10>12,INDEX($AF$6:$AF$29,B10-12)*Premissas!$F$22,0) -> 0.5243184 | AI10: =IF(B10>12,(INDEX($AD$6:$AD$29,B10-12)+INDEX($AF$6:$AF$29,B10-12))*(1-Premissas!$F$22),0) -> 0 | AJ10: =H10+J10+AG10+AH10 -> 35.631716 | AK10: =IF(X10>0,B10,"")
B11: =B10+1 -> 6 | C11: =EDATE(Premissas!$C$7,B11-1) -> 46447 | D11: =Premissas!$F$19*(1+Premissas!$F$20)^(B11-1) -> 11.220414 | E11: =IFERROR(D11/Premissas!$F$25,0) -> 56.102069 | F11: =(N(H10)+N(J10))*Premissas!$F$21+AI11 -> 1.6767221 | G11: =H11+I11+J11+K11 -> 52.279316 | H11: =N(H10)*(1-Premissas!$F$21)+AC11 -> 30.625538 | I11: =SUM(INDEX($AG$6:$AG$29,MAX(1,B11-11)):INDEX($AG$6:$AG$29,B11)) -> 8.5839489 | J11: =N(J10)*(1-Premissas!$F$21)+AE11 -> 10.208513 | K11: =SUM(INDEX($AH$6:$AH$29,MAX(1,B11-11)):INDEX($AH$6:$AH$29,B11)) -> 2.8613163 | L11: =H11*Premissas!$C$13+I11*Premissas!$F$13/12+J11*Premissas!$C$14+K11*Premissas!$F$14/12 -> 3294.2138 | M11: =L11*12 -> 39530.565 | N11: =IFERROR(L11/G11,0) -> 63.011799 | O11: =L11*Premissas!$C$30 -> 197.65283 | P11: =L11*Premissas!$C$28+AJ11*Premissas!$C$29 -> 136.40577 | Q11: =G11*Premissas!$C$31 -> 26.139658 | R11: =L11-O11-P11-Q11 -> 2934.0155 | S11: =IFERROR(R11/L11,0) -> 0.89065729 | T11: =SUMPRODUCT(Premissas!$C$42:$C$61,--(Premissas!$D$42:$D$61<=B11)) -> 2195 | U11: =Premissas!$C$34*(1+Premissas!$C$35)^(B11-1) -> 1738.9111 | V11: =D11*Premissas!$C$36*Premissas!$C$37 -> 67.322483 | W11: =O11+P11+Q11+T11+U11+V11 -> 4361.4318 | X11: =L11-W11 -> -1067.2181 | Y11: =N(Y10)+X11 -> -13241.646 | Z11: =IFERROR((U11+V11)/D11,0) -> 160.97745 | AA11: =IFERROR(T11/(R11/G11),0) -> 39.111279 | AC11: =D11*(1-Premissas!$F$23)*(1-Premissas!$F$24) -> 6.7322483 | AD11: =D11*(1-Premissas!$F$23)*Premissas!$F$24 -> 1.6830621 | AE11: =D11*Premissas!$F$23*(1-Premissas!$F$24) -> 2.2440828 | AF11: =D11*Premissas!$F$23*Premissas!$F$24 -> 0.56102069 | AG11: =AD11+IF(B11>12,INDEX($AD$6:$AD$29,B11-12)*Premissas!$F$22,0) -> 1.6830621 | AH11: =AF11+IF(B11>12,INDEX($AF$6:$AF$29,B11-12)*Premissas!$F$22,0) -> 0.56102069 | AI11: =IF(B11>12,(INDEX($AD$6:$AD$29,B11-12)+INDEX($AF$6:$AF$29,B11-12))*(1-Premissas!$F$22),0) -> 0 | AJ11: =H11+J11+AG11+AH11 -> 43.078134 | AK11: =IF(X11>0,B11,"")
B12: =B11+1 -> 7 | C12: =EDATE(Premissas!$C$7,B12-1) -> 46478 | D12: =Premissas!$F$19*(1+Premissas!$F$20)^(B12-1) -> 12.005843 | E12: =IFERROR(D12/Premissas!$F$25,0) -> 60.029214 | F12: =(N(H11)+N(J11))*Premissas!$F$21+AI12 -> 2.0417026 | G12: =H12+I12+J12+K12 -> 62.243457 | H12: =N(H11)*(1-Premissas!$F$21)+AC12 -> 36.297767 | I12: =SUM(INDEX($AG$6:$AG$29,MAX(1,B12-11)):INDEX($AG$6:$AG$29,B12)) -> 10.384825 | J12: =N(J11)*(1-Premissas!$F$21)+AE12 -> 12.099256 | K12: =SUM(INDEX($AH$6:$AH$29,MAX(1,B12-11)):INDEX($AH$6:$AH$29,B12)) -> 3.4616084 | L12: =H12*Premissas!$C$13+I12*Premissas!$F$13/12+J12*Premissas!$C$14+K12*Premissas!$F$14/12 -> 3919.6748 | M12: =L12*12 -> 47036.097 | N12: =IFERROR(L12/G12,0) -> 62.973283 | O12: =L12*Premissas!$C$30 -> 235.18049 | P12: =L12*Premissas!$C$28+AJ12*Premissas!$C$29 -> 162.07973 | Q12: =G12*Premissas!$C$31 -> 31.121728 | R12: =L12-O12-P12-Q12 -> 3491.2928 | S12: =IFERROR(R12/L12,0) -> 0.89070982 | T12: =SUMPRODUCT(Premissas!$C$42:$C$61,--(Premissas!$D$42:$D$61<=B12)) -> 3395 | U12: =Premissas!$C$34*(1+Premissas!$C$35)^(B12-1) -> 1791.0784 | V12: =D12*Premissas!$C$36*Premissas!$C$37 -> 72.035057 | W12: =O12+P12+Q12+T12+U12+V12 -> 5686.4954 | X12: =L12-W12 -> -1766.8207 | Y12: =N(Y11)+X12 -> -15008.466 | Z12: =IFERROR((U12+V12)/D12,0) -> 155.1839 | AA12: =IFERROR(T12/(R12/G12),0) -> 60.526729 | AC12: =D12*(1-Premissas!$F$23)*(1-Premissas!$F$24) -> 7.2035057 | AD12: =D12*(1-Premissas!$F$23)*Premissas!$F$24 -> 1.8008764 | AE12: =D12*Premissas!$F$23*(1-Premissas!$F$24) -> 2.4011686 | AF12: =D12*Premissas!$F$23*Premissas!$F$24 -> 0.60029214 | AG12: =AD12+IF(B12>12,INDEX($AD$6:$AD$29,B12-12)*Premissas!$F$22,0) -> 1.8008764 | AH12: =AF12+IF(B12>12,INDEX($AF$6:$AF$29,B12-12)*Premissas!$F$22,0) -> 0.60029214 | AI12: =IF(B12>12,(INDEX($AD$6:$AD$29,B12-12)+INDEX($AF$6:$AF$29,B12-12))*(1-Premissas!$F$22),0) -> 0 | AJ12: =H12+J12+AG12+AH12 -> 50.798192 | AK12: =IF(X12>0,B12,"")
B13: =B12+1 -> 8 | C13: =EDATE(Premissas!$C$7,B13-1) -> 46508 | D13: =Premissas!$F$19*(1+Premissas!$F$20)^(B13-1) -> 12.846252 | E13: =IFERROR(D13/Premissas!$F$25,0) -> 64.231259 | F13: =(N(H12)+N(J12))*Premissas!$F$21+AI13 -> 2.4198511 | G13: =H13+I13+J13+K13 -> 72.669857 | H13: =N(H12)*(1-Premissas!$F$21)+AC13 -> 42.19063 | I13: =SUM(INDEX($AG$6:$AG$29,MAX(1,B13-11)):INDEX($AG$6:$AG$29,B13)) -> 12.311763 | J13: =N(J12)*(1-Premissas!$F$21)+AE13 -> 14.063543 | K13: =SUM(INDEX($AH$6:$AH$29,MAX(1,B13-11)):INDEX($AH$6:$AH$29,B13)) -> 4.103921 | L13: =H13*Premissas!$C$13+I13*Premissas!$F$13/12+J13*Premissas!$C$14+K13*Premissas!$F$14/12 -> 4573.5341 | M13: =L13*12 -> 54882.409 | N13: =IFERROR(L13/G13,0) -> 62.935779 | O13: =L13*Premissas!$C$30 -> 274.41204 | P13: =L13*Premissas!$C$28+AJ13*Premissas!$C$29 -> 188.89717 | Q13: =G13*Premissas!$C$31 -> 36.334929 | R13: =L13-O13-P13-Q13 -> 4073.8899 | S13: =IFERROR(R13/L13,0) -> 0.89075316 | T13: =SUMPRODUCT(Premissas!$C$42:$C$61,--(Premissas!$D$42:$D$61<=B13)) -> 3395 | U13: =Premissas!$C$34*(1+Premissas!$C$35)^(B13-1) -> 1844.8108 | V13: =D13*Premissas!$C$36*Premissas!$C$37 -> 77.077511 | W13: =O13+P13+Q13+T13+U13+V13 -> 5816.5325 | X13: =L13-W13 -> -1242.9984 | Y13: =N(Y12)+X13 -> -16251.465 | Z13: =IFERROR((U13+V13)/D13,0) -> 149.60693 | AA13: =IFERROR(T13/(R13/G13),0) -> 60.559851 | AC13: =D13*(1-Premissas!$F$23)*(1-Premissas!$F$24) -> 7.7077511 | AD13: =D13*(1-Premissas!$F$23)*Premissas!$F$24 -> 1.9269378 | AE13: =D13*Premissas!$F$23*(1-Premissas!$F$24) -> 2.5692504 | AF13: =D13*Premissas!$F$23*Premissas!$F$24 -> 0.64231259 | AG13: =AD13+IF(B13>12,INDEX($AD$6:$AD$29,B13-12)*Premissas!$F$22,0) -> 1.9269378 | AH13: =AF13+IF(B13>12,INDEX($AF$6:$AF$29,B13-12)*Premissas!$F$22,0) -> 0.64231259 | AI13: =IF(B13>12,(INDEX($AD$6:$AD$29,B13-12)+INDEX($AF$6:$AF$29,B13-12))*(1-Premissas!$F$22),0) -> 0 | AJ13: =H13+J13+AG13+AH13 -> 58.823424 | AK13: =IF(X13>0,B13,"")
B14: =B13+1 -> 9 | C14: =EDATE(Premissas!$C$7,B14-1) -> 46539 | D14: =Premissas!$F$19*(1+Premissas!$F$20)^(B14-1) -> 13.745489 | E14: =IFERROR(D14/Premissas!$F$25,0) -> 68.727447 | F14: =(N(H13)+N(J13))*Premissas!$F$21+AI14 -> 2.8127087 | G14: =H14+I14+J14+K14 -> 83.602638 | H14: =N(H13)*(1-Premissas!$F$21)+AC14 -> 48.328392 | I14: =SUM(INDEX($AG$6:$AG$29,MAX(1,B14-11)):INDEX($AG$6:$AG$29,B14)) -> 14.373586 | J14: =N(J13)*(1-Premissas!$F$21)+AE14 -> 16.109464 | K14: =SUM(INDEX($AH$6:$AH$29,MAX(1,B14-11)):INDEX($AH$6:$AH$29,B14)) -> 4.7911955 | L14: =H14*Premissas!$C$13+I14*Premissas!$F$13/12+J14*Premissas!$C$14+K14*Premissas!$F$14/12 -> 5258.5487 | M14: =L14*12 -> 63102.585 | N14: =IFERROR(L14/G14,0) -> 62.899316 | O14: =L14*Premissas!$C$30 -> 315.51292 | P14: =L14*Premissas!$C$28+AJ14*Premissas!$C$29 -> 216.97081 | Q14: =G14*Premissas!$C$31 -> 41.801319 | R14: =L14-O14-P14-Q14 -> 4684.2637 | S14: =IFERROR(R14/L14,0) -> 0.8907902 | T14: =SUMPRODUCT(Premissas!$C$42:$C$61,--(Premissas!$D$42:$D$61<=B14)) -> 3395 | U14: =Premissas!$C$34*(1+Premissas!$C$35)^(B14-1) -> 1900.1551 | V14: =D14*Premissas!$C$36*Premissas!$C$37 -> 82.472937 | W14: =O14+P14+Q14+T14+U14+V14 -> 5951.9131 | X14: =L14-W14 -> -693.36439 | Y14: =N(Y13)+X14 -> -16944.829 | Z14: =IFERROR((U14+V14)/D14,0) -> 144.23845 | AA14: =IFERROR(T14/(R14/G14),0) -> 60.592438 | AC14: =D14*(1-Premissas!$F$23)*(1-Premissas!$F$24) -> 8.2472937 | AD14: =D14*(1-Premissas!$F$23)*Premissas!$F$24 -> 2.0618234 | AE14: =D14*Premissas!$F$23*(1-Premissas!$F$24) -> 2.7490979 | AF14: =D14*Premissas!$F$23*Premissas!$F$24 -> 0.68727447 | AG14: =AD14+IF(B14>12,INDEX($AD$6:$AD$29,B14-12)*Premissas!$F$22,0) -> 2.0618234 | AH14: =AF14+IF(B14>12,INDEX($AF$6:$AF$29,B14-12)*Premissas!$F$22,0) -> 0.68727447 | AI14: =IF(B14>12,(INDEX($AD$6:$AD$29,B14-12)+INDEX($AF$6:$AF$29,B14-12))*(1-Premissas!$F$22),0) -> 0 | AJ14: =H14+J14+AG14+AH14 -> 67.186954 | AK14: =IF(X14>0,B14,"")
B15: =B14+1 -> 10 | C15: =EDATE(Premissas!$C$7,B15-1) -> 46569 | D15: =Premissas!$F$19*(1+Premissas!$F$20)^(B15-1) -> 14.707674 | E15: =IFERROR(D15/Premissas!$F$25,0) -> 73.538368 | F15: =(N(H14)+N(J14))*Premissas!$F$21+AI15 -> 3.2218928 | G15: =H15+I15+J15+K15 -> 95.088419 | H15: =N(H14)*(1-Premissas!$F$21)+AC15 -> 54.736577 | I15: =SUM(INDEX($AG$6:$AG$29,MAX(1,B15-11)):INDEX($AG$6:$AG$29,B15)) -> 16.579738 | J15: =N(J14)*(1-Premissas!$F$21)+AE15 -> 18.245526 | K15: =SUM(INDEX($AH$6:$AH$29,MAX(1,B15-11)):INDEX($AH$6:$AH$29,B15)) -> 5.5265792 | L15: =H15*Premissas!$C$13+I15*Premissas!$F$13/12+J15*Premissas!$C$14+K15*Premissas!$F$14/12 -> 5977.6303 | M15: =L15*12 -> 71731.564 | N15: =IFERROR(L15/G15,0) -> 62.863915 | O15: =L15*Premissas!$C$30 -> 358.65782 | P15: =L15*Premissas!$C$28+AJ15*Premissas!$C$29 -> 246.41964 | Q15: =G15*Premissas!$C$31 -> 47.54421 | R15: =L15-O15-P15-Q15 -> 5325.0086 | S15: =IFERROR(R15/L15,0) -> 0.89082268 | T15: =SUMPRODUCT(Premissas!$C$42:$C$61,--(Premissas!$D$42:$D$61<=B15)) -> 3395 | U15: =Premissas!$C$34*(1+Premissas!$C$35)^(B15-1) -> 1957.1598 | V15: =D15*Premissas!$C$36*Premissas!$C$37 -> 88.246042 | W15: =O15+P15+Q15+T15+U15+V15 -> 6093.0275 | X15: =L15-W15 -> -115.39717 | Y15: =N(Y14)+X15 -> -17060.226 | Z15: =IFERROR((U15+V15)/D15,0) -> 139.07066 | AA15: =IFERROR(T15/(R15/G15),0) -> 60.624349 | AC15: =D15*(1-Premissas!$F$23)*(1-Premissas!$F$24) -> 8.8246042 | AD15: =D15*(1-Premissas!$F$23)*Premissas!$F$24 -> 2.2061511 | AE15: =D15*Premissas!$F$23*(1-Premissas!$F$24) -> 2.9415347 | AF15: =D15*Premissas!$F$23*Premissas!$F$24 -> 0.73538368 | AG15: =AD15+IF(B15>12,INDEX($AD$6:$AD$29,B15-12)*Premissas!$F$22,0) -> 2.2061511 | AH15: =AF15+IF(B15>12,INDEX($AF$6:$AF$29,B15-12)*Premissas!$F$22,0) -> 0.73538368 | AI15: =IF(B15>12,(INDEX($AD$6:$AD$29,B15-12)+INDEX($AF$6:$AF$29,B15-12))*(1-Premissas!$F$22),0) -> 0 | AJ15: =H15+J15+AG15+AH15 -> 75.923637 | AK15: =IF(X15>0,B15,"")
B16: =B15+1 -> 11 | C16: =EDATE(Premissas!$C$7,B16-1) -> 46600 | D16: =Premissas!$F$19*(1+Premissas!$F$20)^(B16-1) -> 15.737211 | E16: =IFERROR(D16/Premissas!$F$25,0) -> 78.686054 | F16: =(N(H15)+N(J15))*Premissas!$F$21+AI16 -> 3.6491051 | G16: =H16+I16+J16+K16 -> 107.17652 | H16: =N(H15)*(1-Premissas!$F$21)+AC16 -> 61.442074 | I16: =SUM(INDEX($AG$6:$AG$29,MAX(1,B16-11)):INDEX($AG$6:$AG$29,B16)) -> 18.940319 | J16: =N(J15)*(1-Premissas!$F$21)+AE16 -> 20.480691 | K16: =SUM(INDEX($AH$6:$AH$29,MAX(1,B16-11)):INDEX($AH$6:$AH$29,B16)) -> 6.3134397 | L16: =H16*Premissas!$C$13+I16*Premissas!$F$13/12+J16*Premissas!$C$14+K16*Premissas!$F$14/12 -> 6733.8578 | M16: =L16*12 -> 80806.293 | N16: =IFERROR(L16/G16,0) -> 62.829596 | O16: =L16*Premissas!$C$30 -> 404.03147 | P16: =L16*Premissas!$C$28+AJ16*Premissas!$C$29 -> 277.36942 | Q16: =G16*Premissas!$C$31 -> 53.588262 | R16: =L16-O16-P16-Q16 -> 5998.8686 | S16: =IFERROR(R16/L16,0) -> 0.8908517 | T16: =SUMPRODUCT(Premissas!$C$42:$C$61,--(Premissas!$D$42:$D$61<=B16)) -> 3395 | U16: =Premissas!$C$34*(1+Premissas!$C$35)^(B16-1) -> 2015.8746 | V16: =D16*Premissas!$C$36*Premissas!$C$37 -> 94.423265 | W16: =O16+P16+Q16+T16+U16+V16 -> 6240.287 | X16: =L16-W16 -> 493.57079 | Y16: =N(Y15)+X16 -> -16566.656 | Z16: =IFERROR((U16+V16)/D16,0) -> 134.09605 | AA16: =IFERROR(T16/(R16/G16),0) -> 60.655488 | AC16: =D16*(1-Premissas!$F$23)*(1-Premissas!$F$24) -> 9.4423265 | AD16: =D16*(1-Premissas!$F$23)*Premissas!$F$24 -> 2.3605816 | AE16: =D16*Premissas!$F$23*(1-Premissas!$F$24) -> 3.1474422 | AF16: =D16*Premissas!$F$23*Premissas!$F$24 -> 0.78686054 | AG16: =AD16+IF(B16>12,INDEX($AD$6:$AD$29,B16-12)*Premissas!$F$22,0) -> 2.3605816 | AH16: =AF16+IF(B16>12,INDEX($AF$6:$AF$29,B16-12)*Premissas!$F$22,0) -> 0.78686054 | AI16: =IF(B16>12,(INDEX($AD$6:$AD$29,B16-12)+INDEX($AF$6:$AF$29,B16-12))*(1-Premissas!$F$22),0) -> 0 | AJ16: =H16+J16+AG16+AH16 -> 85.070208 | AK16: =IF(X16>0,B16,"") -> 11
B17: =B16+1 -> 12 | C17: =EDATE(Premissas!$C$7,B17-1) -> 46631 | D17: =Premissas!$F$19*(1+Premissas!$F$20)^(B17-1) -> 16.838816 | E17: =IFERROR(D17/Premissas!$F$25,0) -> 84.194078 | F17: =(N(H16)+N(J16))*Premissas!$F$21+AI17 -> 4.0961383 | G17: =H17+I17+J17+K17 -> 119.9192 | H17: =N(H16)*(1-Premissas!$F$21)+AC17 -> 68.47326 | I17: =SUM(INDEX($AG$6:$AG$29,MAX(1,B17-11)):INDEX($AG$6:$AG$29,B17)) -> 21.466142 | J17: =N(J16)*(1-Premissas!$F$21)+AE17 -> 22.82442 | K17: =SUM(INDEX($AH$6:$AH$29,MAX(1,B17-11)):INDEX($AH$6:$AH$29,B17)) -> 7.1553805 | L17: =H17*Premissas!$C$13+I17*Premissas!$F$13/12+J17*Premissas!$C$14+K17*Premissas!$F$14/12 -> 7530.4908 | M17: =L17*12 -> 90365.889 | N17: =IFERROR(L17/G17,0) -> 62.796372 | O17: =L17*Premissas!$C$30 -> 451.82945 | P17: =L17*Premissas!$C$28+AJ17*Premissas!$C$29 -> 309.95324 | Q17: =G17*Premissas!$C$31 -> 59.959601 | R17: =L17-O17-P17-Q17 -> 6708.7485 | S17: =IFERROR(R17/L17,0) -> 0.89087799 | T17: =SUMPRODUCT(Premissas!$C$42:$C$61,--(Premissas!$D$42:$D$61<=B17)) -> 3395 | U17: =Premissas!$C$34*(1+Premissas!$C$35)^(B17-1) -> 2076.3508 | V17: =D17*Premissas!$C$36*Premissas!$C$37 -> 101.03289 | W17: =O17+P17+Q17+T17+U17+V17 -> 6394.126 | X17: =L17-W17 -> 1136.3648 | Y17: =N(Y16)+X17 -> -15430.291 | Z17: =IFERROR((U17+V17)/D17,0) -> 129.30741 | AA17: =IFERROR(T17/(R17/G17),0) -> 60.685788 | AC17: =D17*(1-Premissas!$F$23)*(1-Premissas!$F$24) -> 10.103289 | AD17: =D17*(1-Premissas!$F$23)*Premissas!$F$24 -> 2.5258223 | AE17: =D17*Premissas!$F$23*(1-Premissas!$F$24) -> 3.3677631 | AF17: =D17*Premissas!$F$23*Premissas!$F$24 -> 0.84194078 | AG17: =AD17+IF(B17>12,INDEX($AD$6:$AD$29,B17-12)*Premissas!$F$22,0) -> 2.5258223 | AH17: =AF17+IF(B17>12,INDEX($AF$6:$AF$29,B17-12)*Premissas!$F$22,0) -> 0.84194078 | AI17: =IF(B17>12,(INDEX($AD$6:$AD$29,B17-12)+INDEX($AF$6:$AF$29,B17-12))*(1-Premissas!$F$22),0) -> 0 | AJ17: =H17+J17+AG17+AH17 -> 94.665443 | AK17: =IF(X17>0,B17,"") -> 12
B18: =B17+1 -> 13 | C18: =EDATE(Premissas!$C$7,B18-1) -> 46661 | D18: =Premissas!$F$19*(1+Premissas!$F$20)^(B18-1) -> 18.017533 | E18: =IFERROR(D18/Premissas!$F$25,0) -> 90.087664 | F18: =(N(H17)+N(J17))*Premissas!$F$21+AI18 -> 5.124884 | G18: =H18+I18+J18+K18 -> 132.81185 | H18: =N(H17)*(1-Premissas!$F$21)+AC18 -> 75.860117 | I18: =SUM(INDEX($AG$6:$AG$29,MAX(1,B18-11)):INDEX($AG$6:$AG$29,B18)) -> 23.748771 | J18: =N(J17)*(1-Premissas!$F$21)+AE18 -> 25.286706 | K18: =SUM(INDEX($AH$6:$AH$29,MAX(1,B18-11)):INDEX($AH$6:$AH$29,B18)) -> 7.9162571 | L18: =H18*Premissas!$C$13+I18*Premissas!$F$13/12+J18*Premissas!$C$14+K18*Premissas!$F$14/12 -> 8340.4692 | M18: =L18*12 -> 100085.63 | N18: =IFERROR(L18/G18,0) -> 62.799134 | O18: =L18*Premissas!$C$30 -> 500.42815 | P18: =L18*Premissas!$C$28+AJ18*Premissas!$C$29 -> 343.75368 | Q18: =G18*Premissas!$C$31 -> 66.405925 | R18: =L18-O18-P18-Q18 -> 7429.8814 | S18: =IFERROR(R18/L18,0) -> 0.89082296 | T18: =SUMPRODUCT(Premissas!$C$42:$C$61,--(Premissas!$D$42:$D$61<=B18)) -> 3395 | U18: =Premissas!$C$34*(1+Premissas!$C$35)^(B18-1) -> 2138.6413 | V18: =D18*Premissas!$C$36*Premissas!$C$37 -> 108.1052 | W18: =O18+P18+Q18+T18+U18+V18 -> 6552.3343 | X18: =L18-W18 -> 1788.1349 | Y18: =N(Y17)+X18 -> -13642.156 | Z18: =IFERROR((U18+V18)/D18,0) -> 124.69779 | AA18: =IFERROR(T18/(R18/G18),0) -> 60.686868 | AC18: =D18*(1-Premissas!$F$23)*(1-Premissas!$F$24) -> 10.81052 | AD18: =D18*(1-Premissas!$F$23)*Premissas!$F$24 -> 2.7026299 | AE18: =D18*Premissas!$F$23*(1-Premissas!$F$24) -> 3.6035065 | AF18: =D18*Premissas!$F$23*Premissas!$F$24 -> 0.90087664 | AG18: =AD18+IF(B18>12,INDEX($AD$6:$AD$29,B18-12)*Premissas!$F$22,0) -> 3.4826299 | AH18: =AF18+IF(B18>12,INDEX($AF$6:$AF$29,B18-12)*Premissas!$F$22,0) -> 1.1608766 | AI18: =IF(B18>12,(INDEX($AD$6:$AD$29,B18-12)+INDEX($AF$6:$AF$29,B18-12))*(1-Premissas!$F$22),0) -> 0.56 | AJ18: =H18+J18+AG18+AH18 -> 105.79033 | AK18: =IF(X18>0,B18,"") -> 13
... B29: =B28+1 -> 24 | C29: =EDATE(Premissas!$C$7,B29-1) -> 46997 | D29: =Premissas!$F$19*(1+Premissas!$F$20)^(B29-1) -> 37.924239 | E29: =IFERROR(D29/Premissas!$F$25,0) -> 189.62119 | F29: =(N(H28)+N(J28))*Premissas!$F$21+AI29 -> 13.000512 | G29: =H29+I29+J29+K29 -> 338.01863 | H29: =N(H28)*(1-Premissas!$F$21)+AC29 -> 191.21512 | I29: =SUM(INDEX($AG$6:$AG$29,MAX(1,B29-11)):INDEX($AG$6:$AG$29,B29)) -> 62.298855 | J29: =N(J28)*(1-Premissas!$F$21)+AE29 -> 63.738372 | K29: =SUM(INDEX($AH$6:$AH$29,MAX(1,B29-11)):INDEX($AH$6:$AH$29,B29)) -> 20.766285 | L29: =H29*Premissas!$C$13+I29*Premissas!$F$13/12+J29*Premissas!$C$14+K29*Premissas!$F$14/12 -> 21200.282 | M29: =L29*12 -> 254403.38 | N29: =IFERROR(L29/G29,0) -> 62.719269 | O29: =L29*Premissas!$C$30 -> 1272.0169 | P29: =L29*Premissas!$C$28+AJ29*Premissas!$C$29 -> 871.72627 | Q29: =G29*Premissas!$C$31 -> 169.00932 | R29: =L29-O29-P29-Q29 -> 18887.529 | S29: =IFERROR(R29/L29,0) -> 0.89090935 | T29: =SUMPRODUCT(Premissas!$C$42:$C$61,--(Premissas!$D$42:$D$61<=B29)) -> 3395 | U29: =Premissas!$C$34*(1+Premissas!$C$35)^(B29-1) -> 2960.3798 | V29: =D29*Premissas!$C$36*Premissas!$C$37 -> 227.54543 | W29: =O29+P29+Q29+T29+U29+V29 -> 8895.6777 | X29: =L29-W29 -> 12304.604 | Y29: =N(Y28)+X29 -> 62578.916 | Z29: =IFERROR((U29+V29)/D29,0) -> 84.060361 | AA29: =IFERROR(T29/(R29/G29),0) -> 60.758252 | AC29: =D29*(1-Premissas!$F$23)*(1-Premissas!$F$24) -> 22.754543 | AD29: =D29*(1-Premissas!$F$23)*Premissas!$F$24 -> 5.6886358 | AE29: =D29*Premissas!$F$23*(1-Premissas!$F$24) -> 7.5848478 | AF29: =D29*Premissas!$F$23*Premissas!$F$24 -> 1.8962119 | AG29: =AD29+IF(B29>12,INDEX($AD$6:$AD$29,B29-12)*Premissas!$F$22,0) -> 7.3304204 | AH29: =AF29+IF(B29>12,INDEX($AF$6:$AF$29,B29-12)*Premissas!$F$22,0) -> 2.4434735 | AI29: =IF(B29>12,(INDEX($AD$6:$AD$29,B29-12)+INDEX($AF$6:$AF$29,B29-12))*(1-Premissas!$F$22),0) -> 1.1787171 | AJ29: =H29+J29+AG29+AH29 -> 264.72738 | AK29: =IF(X29>0,B29,"") -> 24
B30: TOTAL | D30: =SUM(D6:D29) -> 465.41337 | E30: =SUM(E6:E29) -> 2327.0668 | F30: =SUM(F6:F29) -> 127.39474 | L30: =SUM(L6:L29) -> 214730.24 | O30: =SUM(O6:O29) -> 12883.815 | P30: =SUM(P6:P29) -> 8845.5088 | Q30: =SUM(Q6:Q29) -> 1709.8181 | R30: =SUM(R6:R29) -> 191291.1 | T30: =SUM(T6:T29) -> 74280 | U30: =SUM(U6:U29) -> 51639.705 | V30: =SUM(V6:V29) -> 2792.4802 | W30: =SUM(W6:W29) -> 152151.33 | X30: =SUM(X6:X29) -> 62578.916 | AC30: =SUM(AC6:AC29) -> 279.24802 | AD30: =SUM(AD6:AD29) -> 69.812005 | AE30: =SUM(AE6:AE29) -> 93.082673 | AF30: =SUM(AF6:AF29) -> 23.270668 | AG30: =SUM(AG6:AG29) -> 83.764997 | AH30: =SUM(AH6:AH29) -> 27.921666 | AI30: =SUM(AI6:AI29) -> 10.017533 | AJ30: =SUM(AJ6:AJ29) -> 2714.1842

Sheet Fluxo de Caixa
B1: ⌂ Início | C1: ▦ Dashboard
B2: ="FLUXO DE CAIXA · CENÁRIO "&UPPER(Premissas!$C$9) -> FLUXO DE CAIXA · CENÁRIO REALISTA
B3: Quando o dinheiro ENTRA e SAI. O plano anual entra inteiro no mês da venda ou da renovação; a última coluna mostra quanto desse dinheiro ainda é receita dos meses seguintes (não gaste como se fosse lucro).
D4: ENTRADAS | G4: SAÍDAS | M4: SALDO | O4: PLANO ANUAL (COMPETÊNCIA)
B5: Nº | C5: MÊS | D5: ENTRADA MENSALIDADES | E5: ENTRADA PLANO ANUAL (À VISTA) | F5: TOTAL DE ENTRADAS | G5: (−) IMPOSTOS | H5: (−) GATEWAY | I5: (−) INFRA | J5: (−) CUSTOS FIXOS | K5: (−) MARKETING | L5: TOTAL DE SAÍDAS | M5: SALDO DO MÊS | N5: SALDO ACUMULADO EM CAIXA | O5: RECEITA ANUAL RECONHECIDA NO MÊS | P5: RECEITA ANUAL A RECONHECER (JÁ RECEBIDA)
B6: ='Projeção 24 meses'!B6 -> 1 | C6: ='Projeção 24 meses'!C6 -> 46296 | D6: ='Projeção 24 meses'!H6*Premissas!$C$13+'Projeção 24 meses'!J6*Premissas!$C$14 -> 418.56 | E6: ='Projeção 24 meses'!AG6*Premissas!$F$13+'Projeção 24 meses'!AH6*Premissas!$F$14 -> 1046.232 | F6: =D6+E6 -> 1464.792 | G6: =F6*Premissas!$C$30 -> 87.88752 | H6: =F6*Premissas!$C$28+'Projeção 24 meses'!AJ6*Premissas!$C$29 -> 55.18772 | I6: ='Projeção 24 meses'!Q6 -> 4 | J6: ='Projeção 24 meses'!T6 -> 2195 | K6: ='Projeção 24 meses'!U6+'Projeção 24 meses'!V6 -> 1548 | L6: =G6+H6+I6+J6+K6 -> 3890.0752 | M6: =F6-L6 -> -2425.2832 | N6: =IF('Projeção 24 meses'!B6=1,Premissas!$C$8,N(N5))+M6 -> -2425.2832 | O6: ='Projeção 24 meses'!I6*Premissas!$F$13/12+'Projeção 24 meses'!K6*Premissas!$F$14/12 -> 87.186 | P6: =N(P5)+E6-O6 -> 959.046
B7: ='Projeção 24 meses'!B7 -> 2 | C7: ='Projeção 24 meses'!C7 -> 46327 | D7: ='Projeção 24 meses'!H7*Premissas!$C$13+'Projeção 24 meses'!J7*Premissas!$C$14 -> 845.4912 | E7: ='Projeção 24 meses'!AG7*Premissas!$F$13+'Projeção 24 meses'!AH7*Premissas!$F$14 -> 1119.4682 | F7: =D7+E7 -> 1964.9594 | G7: =F7*Premissas!$C$30 -> 117.89757 | H7: =F7*Premissas!$C$28+'Projeção 24 meses'!AJ7*Premissas!$C$29 -> 75.94718 | I7: ='Projeção 24 meses'!Q7 -> 8.12 | J7: ='Projeção 24 meses'!T7 -> 2195 | K7: ='Projeção 24 meses'!U7+'Projeção 24 meses'!V7 -> 1596.36 | L7: =G7+H7+I7+J7+K7 -> 3993.3247 | M7: =F7-L7 -> -2028.3653 | N7: =IF('Projeção 24 meses'!B7=1,Premissas!$C$8,N(N6))+M7 -> -4453.6485 | O7: ='Projeção 24 meses'!I7*Premissas!$F$13/12+'Projeção 24 meses'!K7*Premissas!$F$14/12 -> 180.47502 | P7: =N(P6)+E7-O7 -> 1898.0392
B8: ='Projeção 24 meses'!B8 -> 3 | C8: ='Projeção 24 meses'!C8 -> 46357 | D8: ='Projeção 24 meses'!H8*Premissas!$C$13+'Projeção 24 meses'!J8*Premissas!$C$14 -> 1282.426 | E8: ='Projeção 24 meses'!AG8*Premissas!$F$13+'Projeção 24 meses'!AH8*Premissas!$F$14 -> 1197.831 | F8: =D8+E8 -> 2480.257 | G8: =F8*Premissas!$C$30 -> 148.81542 | H8: =F8*Premissas!$C$28+'Projeção 24 meses'!AJ8*Premissas!$C$29 -> 97.314987 | I8: ='Projeção 24 meses'!Q8 -> 12.3764 | J8: ='Projeção 24 meses'!T8 -> 2195 | K8: ='Projeção 24 meses'!U8+'Projeção 24 meses'!V8 -> 1646.3052 | L8: =G8+H8+I8+J8+K8 -> 4099.812 | M8: =F8-L8 -> -1619.555 | N8: =IF('Projeção 24 meses'!B8=1,Premissas!$C$8,N(N7))+M8 -> -6073.2036 | O8: ='Projeção 24 meses'!I8*Premissas!$F$13/12+'Projeção 24 meses'!K8*Premissas!$F$14/12 -> 280.29427 | P8: =N(P7)+E8-O8 -> 2815.576
B9: ='Projeção 24 meses'!B9 -> 4 | C9: ='Projeção 24 meses'!C9 -> 46388 | D9: ='Projeção 24 meses'!H9*Premissas!$C$13+'Projeção 24 meses'!J9*Premissas!$C$14 -> 1731.0587 | E9: ='Projeção 24 meses'!AG9*Premissas!$F$13+'Projeção 24 meses'!AH9*Premissas!$F$14 -> 1281.6792 | F9: =D9+E9 -> 3012.7379 | G9: =F9*Premissas!$C$30 -> 180.76427 | H9: =F9*Premissas!$C$28+'Projeção 24 meses'!AJ9*Premissas!$C$29 -> 119.37596 | I9: ='Projeção 24 meses'!Q9 -> 16.786348 | J9: ='Projeção 24 meses'!T9 -> 2195 | K9: ='Projeção 24 meses'!U9+'Projeção 24 meses'!V9 -> 1697.8926 | L9: =G9+H9+I9+J9+K9 -> 4209.8191 | M9: =F9-L9 -> -1197.0813 | N9: =IF('Projeção 24 meses'!B9=1,Premissas!$C$8,N(N8))+M9 -> -7270.2848 | O9: ='Projeção 24 meses'!I9*Premissas!$F$13/12+'Projeção 24 meses'!K9*Premissas!$F$14/12 -> 387.10087 | P9: =N(P8)+E9-O9 -> 3710.1543
B10: ='Projeção 24 meses'!B10 -> 5 | C10: ='Projeção 24 meses'!C10 -> 46419 | D10: ='Projeção 24 meses'!H10*Premissas!$C$13+'Projeção 24 meses'!J10*Premissas!$C$14 -> 2193.1525 | E10: ='Projeção 24 meses'!AG10*Premissas!$F$13+'Projeção 24 meses'!AH10*Premissas!$F$14 -> 1371.3967 | F10: =D10+E10 -> 3564.5493 | G10: =F10*Premissas!$C$30 -> 213.87296 | H10: =F10*Premissas!$C$28+'Projeção 24 meses'!AJ10*Premissas!$C$29 -> 142.21876 | I10: ='Projeção 24 meses'!Q10 -> 21.367812 | J10: ='Projeção 24 meses'!T10 -> 2195 | K10: ='Projeção 24 meses'!U10+'Projeção 24 meses'!V10 -> 1751.1814 | L10: =G10+H10+I10+J10+K10 -> 4323.641 | M10: =F10-L10 -> -759.0917 | N10: =IF('Projeção 24 meses'!B10=1,Premissas!$C$8,N(N9))+M10 -> -8029.3765 | O10: ='Projeção 24 meses'!I10*Premissas!$F$13/12+'Projeção 24 meses'!K10*Premissas!$F$14/12 -> 501.38393 | P10: =N(P9)+E10-O10 -> 4580.1671
B11: ='Projeção 24 meses'!B11 -> 6 | C11: ='Projeção 24 meses'!C11 -> 46447 | D11: ='Projeção 24 meses'!H11*Premissas!$C$13+'Projeção 24 meses'!J11*Premissas!$C$14 -> 2670.547 | E11: ='Projeção 24 meses'!AG11*Premissas!$F$13+'Projeção 24 meses'!AH11*Premissas!$F$14 -> 1467.3945 | F11: =D11+E11 -> 4137.9415 | G11: =F11*Premissas!$C$30 -> 248.27649 | H11: =F11*Premissas!$C$28+'Projeção 24 meses'!AJ11*Premissas!$C$29 -> 165.93624 | I11: ='Projeção 24 meses'!Q11 -> 26.139658 | J11: ='Projeção 24 meses'!T11 -> 2195 | K11: ='Projeção 24 meses'!U11+'Projeção 24 meses'!V11 -> 1806.2336 | L11: =G11+H11+I11+J11+K11 -> 4441.586 | M11: =F11-L11 -> -303.64452 | N11: =IF('Projeção 24 meses'!B11=1,Premissas!$C$8,N(N10))+M11 -> -8333.0211 | O11: ='Projeção 24 meses'!I11*Premissas!$F$13/12+'Projeção 24 meses'!K11*Premissas!$F$14/12 -> 623.66681 | P11: =N(P10)+E11-O11 -> 5423.8948
B12: ='Projeção 24 meses'!B12 -> 7 | C12: ='Projeção 24 meses'!C12 -> 46478 | D12: ='Projeção 24 meses'!H12*Premissas!$C$13+'Projeção 24 meses'!J12*Premissas!$C$14 -> 3165.1653 | E12: ='Projeção 24 meses'!AG12*Premissas!$F$13+'Projeção 24 meses'!AH12*Premissas!$F$14 -> 1570.1121 | F12: =D12+E12 -> 4735.2774 | G12: =F12*Premissas!$C$30 -> 284.11665 | H12: =F12*Premissas!$C$28+'Projeção 24 meses'!AJ12*Premissas!$C$29 -> 190.62582 | I12: ='Projeção 24 meses'!Q12 -> 31.121728 | J12: ='Projeção 24 meses'!T12 -> 3395 | K12: ='Projeção 24 meses'!U12+'Projeção 24 meses'!V12 -> 1863.1135 | L12: =G12+H12+I12+J12+K12 -> 5763.9777 | M12: =F12-L12 -> -1028.7003 | N12: =IF('Projeção 24 meses'!B12=1,Premissas!$C$8,N(N11))+M12 -> -9361.7213 | O12: ='Projeção 24 meses'!I12*Premissas!$F$13/12+'Projeção 24 meses'!K12*Premissas!$F$14/12 -> 754.50948 | P12: =N(P11)+E12-O12 -> 6239.4974
B13: ='Projeção 24 meses'!B13 -> 8 | C13: ='Projeção 24 meses'!C13 -> 46508 | D13: ='Projeção 24 meses'!H13*Premissas!$C$13+'Projeção 24 meses'!J13*Premissas!$C$14 -> 3679.0229 | E13: ='Projeção 24 meses'!AG13*Premissas!$F$13+'Projeção 24 meses'!AH13*Premissas!$F$14 -> 1680.02 | F13: =D13+E13 -> 5359.0429 | G13: =F13*Premissas!$C$30 -> 321.54257 | H13: =F13*Premissas!$C$28+'Projeção 24 meses'!AJ13*Premissas!$C$29 -> 216.38998 | I13: ='Projeção 24 meses'!Q13 -> 36.334929 | J13: ='Projeção 24 meses'!T13 -> 3395 | K13: ='Projeção 24 meses'!U13+'Projeção 24 meses'!V13 -> 1921.8883 | L13: =G13+H13+I13+J13+K13 -> 5891.1558 | M13: =F13-L13 -> -532.11289 | N13: =IF('Projeção 24 meses'!B13=1,Premissas!$C$8,N(N12))+M13 -> -9893.8342 | O13: ='Projeção 24 meses'!I13*Premissas!$F$13/12+'Projeção 24 meses'!K13*Premissas!$F$14/12 -> 894.51115 | P13: =N(P12)+E13-O13 -> 7025.0062
B14: ='Projeção 24 meses'!B14 -> 9 | C14: ='Projeção 24 meses'!C14 -> 46539 | D14: ='Projeção 24 meses'!H14*Premissas!$C$13+'Projeção 24 meses'!J14*Premissas!$C$14 -> 4214.2358 | E14: ='Projeção 24 meses'!AG14*Premissas!$F$13+'Projeção 24 meses'!AH14*Premissas!$F$14 -> 1797.6214 | F14: =D14+E14 -> 6011.8572 | G14: =F14*Premissas!$C$30 -> 360.71143 | H14: =F14*Premissas!$C$28+'Projeção 24 meses'!AJ14*Premissas!$C$29 -> 243.33661 | I14: ='Projeção 24 meses'!Q14 -> 41.801319 | J14: ='Projeção 24 meses'!T14 -> 3395 | K14: ='Projeção 24 meses'!U14+'Projeção 24 meses'!V14 -> 1982.6281 | L14: =G14+H14+I14+J14+K14 -> 6023.4774 | M14: =F14-L14 -> -11.62026 | N14: =IF('Projeção 24 meses'!B14=1,Premissas!$C$8,N(N13))+M14 -> -9905.4545 | O14: ='Projeção 24 meses'!I14*Premissas!$F$13/12+'Projeção 24 meses'!K14*Premissas!$F$14/12 -> 1044.3129 | P14: =N(P13)+E14-O14 -> 7778.3147
B15: ='Projeção 24 meses'!B15 -> 10 | C15: ='Projeção 24 meses'!C15 -> 46569 | D15: ='Projeção 24 meses'!H15*Premissas!$C$13+'Projeção 24 meses'!J15*Premissas!$C$14 -> 4773.0295 | E15: ='Projeção 24 meses'!AG15*Premissas!$F$13+'Projeção 24 meses'!AH15*Premissas!$F$14 -> 1923.4549 | F15: =D15+E15 -> 6696.4843 | G15: =F15*Premissas!$C$30 -> 401.78906 | H15: =F15*Premissas!$C$28+'Projeção 24 meses'!AJ15*Premissas!$C$29 -> 271.57953 | I15: ='Projeção 24 meses'!Q15 -> 47.54421 | J15: ='Projeção 24 meses'!T15 -> 3395 | K15: ='Projeção 24 meses'!U15+'Projeção 24 meses'!V15 -> 2045.4058 | L15: =G15+H15+I15+J15+K15 -> 6161.3186 | M15: =F15-L15 -> 535.16573 | N15: =IF('Projeção 24 meses'!B15=1,Premissas!$C$8,N(N14))+M15 -> -9370.2888 | O15: ='Projeção 24 meses'!I15*Premissas!$F$13/12+'Projeção 24 meses'!K15*Premissas!$F$14/12 -> 1204.6008 | P15: =N(P14)+E15-O15 -> 8497.1687
B16: ='Projeção 24 meses'!B16 -> 11 | C16: ='Projeção 24 meses'!C16 -> 46600 | D16: ='Projeção 24 meses'!H16*Premissas!$C$13+'Projeção 24 meses'!J16*Premissas!$C$14 -> 5357.7489 | E16: ='Projeção 24 meses'!AG16*Premissas!$F$13+'Projeção 24 meses'!AH16*Premissas!$F$14 -> 2058.0967 | F16: =D16+E16 -> 7415.8456 | G16: =F16*Premissas!$C$30 -> 444.95074 | H16: =F16*Premissas!$C$28+'Projeção 24 meses'!AJ16*Premissas!$C$29 -> 301.239 | I16: ='Projeção 24 meses'!Q16 -> 53.588262 | J16: ='Projeção 24 meses'!T16 -> 3395 | K16: ='Projeção 24 meses'!U16+'Projeção 24 meses'!V16 -> 2110.2978 | L16: =G16+H16+I16+J16+K16 -> 6305.0758 | M16: =F16-L16 -> 1110.7698 | N16: =IF('Projeção 24 meses'!B16=1,Premissas!$C$8,N(N15))+M16 -> -8259.519 | O16: ='Projeção 24 meses'!I16*Premissas!$F$13/12+'Projeção 24 meses'!K16*Premissas!$F$14/12 -> 1376.1089 | P16: =N(P15)+E16-O16 -> 9179.1565
B17: ='Projeção 24 meses'!B17 -> 12 | C17: ='Projeção 24 meses'!C17 -> 46631 | D17: ='Projeção 24 meses'!H17*Premissas!$C$13+'Projeção 24 meses'!J17*Premissas!$C$14 -> 5970.8683 | E17: ='Projeção 24 meses'!AG17*Premissas!$F$13+'Projeção 24 meses'!AH17*Premissas!$F$14 -> 2202.1635 | F17: =D17+E17 -> 8173.0317 | G17: =F17*Premissas!$C$30 -> 490.3819 | H17: =F17*Premissas!$C$28+'Projeção 24 meses'!AJ17*Premissas!$C$29 -> 332.44218 | I17: ='Projeção 24 meses'!Q17 -> 59.959601 | J17: ='Projeção 24 meses'!T17 -> 3395 | K17: ='Projeção 24 meses'!U17+'Projeção 24 meses'!V17 -> 2177.3837 | L17: =G17+H17+I17+J17+K17 -> 6455.1674 | M17: =F17-L17 -> 1717.8644 | N17: =IF('Projeção 24 meses'!B17=1,Premissas!$C$8,N(N16))+M17 -> -6541.6546 | O17: ='Projeção 24 meses'!I17*Premissas!$F$13/12+'Projeção 24 meses'!K17*Premissas!$F$14/12 -> 1559.6225 | P17: =N(P16)+E17-O17 -> 9821.6975
... B29: ='Projeção 24 meses'!B29 -> 24 | C29: ='Projeção 24 meses'!C29 -> 46997 | D29: ='Projeção 24 meses'!H29*Premissas!$C$13+'Projeção 24 meses'!J29*Premissas!$C$14 -> 16673.958 | E29: ='Projeção 24 meses'!AG29*Premissas!$F$13+'Projeção 24 meses'!AH29*Premissas!$F$14 -> 6391.1003 | F29: =D29+E29 -> 23065.059 | G29: =F29*Premissas!$C$30 -> 1383.9035 | H29: =F29*Premissas!$C$28+'Projeção 24 meses'!AJ29*Premissas!$C$29 -> 936.99347 | I29: ='Projeção 24 meses'!Q29 -> 169.00932 | J29: ='Projeção 24 meses'!T29 -> 3395 | K29: ='Projeção 24 meses'!U29+'Projeção 24 meses'!V29 -> 3187.9252 | L29: =G29+H29+I29+J29+K29 -> 9072.8315 | M29: =F29-L29 -> 13992.227 | N29: =IF('Projeção 24 meses'!B29=1,Premissas!$C$8,N(N28))+M29 -> 88375.441 | O29: ='Projeção 24 meses'!I29*Premissas!$F$13/12+'Projeção 24 meses'!K29*Premissas!$F$14/12 -> 4526.3233 | P29: =N(P28)+E29-O29 -> 28504.448
B30: TOTAL | D30: =SUM(D6:D29) -> 170203.34 | E30: =SUM(E6:E29) -> 73031.35 | F30: =SUM(F6:F29) -> 243234.69 | G30: =SUM(G6:G29) -> 14594.081 | H30: =SUM(H6:H29) -> 9843.1644 | I30: =SUM(I6:I29) -> 1709.8181 | J30: =SUM(J6:J29) -> 74280 | K30: =SUM(K6:K29) -> 54432.186 | ... M30: =SUM(M6:M29) -> 88375.441 | O30: =SUM(O6:O29) -> 44526.902
B32: RESUMO DO CAIXA
B33: Caixa no fim do mês 24 | G33: =N29 -> 88375.441
B34: Menor saldo acumulado (necessidade máxima de capital) | G34: =MIN(N6:N29) -> -9905.4545
B35: Mês do menor saldo | G35: =INDEX(C6:C29,MATCH(MIN(N6:N29),N6:N29,0)) -> 46539
B36: Total recebido à vista em planos anuais (24 meses) | G36: =E30 -> 73031.35
B37: Receita anual já recebida e ainda a reconhecer no mês 24 | G37: =P29 -> 28504.448

Sheet Unit Economics
B1: ⌂ Início | C1: ▦ Dashboard
B2: ="UNIT ECONOMICS · CENÁRIO "&UPPER(Premissas!$C$9) -> UNIT ECONOMICS · CENÁRIO REALISTA
B3: Quanto cada cliente deixa, quanto custa para conquistá-lo e em quantos meses ele se paga. LTV = ticket × margem ÷ churn.
B5: CAC — CUSTO PARA CONQUISTAR UM CLIENTE
B6: Investimento em aquisição em 24 meses (anúncios + comissões) | C6: ='Projeção 24 meses'!$U$30+'Projeção 24 meses'!$V$30 -> 54432.186
B7: Novos clientes em 24 meses | C7: ='Projeção 24 meses'!$D$30 -> 465.41337
B8: CAC médio dos 24 meses | C8: =IFERROR(C6/C7,0) -> 116.9545
B9: CAC no mês 1 | C9: ='Projeção 24 meses'!$Z$6 -> 193.5
B10: CAC no mês 24 | C10: ='Projeção 24 meses'!$Z$29 -> 84.060361
B12: RETORNO POR CLIENTE — POR PLANO
B13: PLANO / COBRANÇA | C13: PESO NO MIX | D13: RECEITA POR MÊS | E13: CUSTO VARIÁVEL POR MÊS | F13: MARGEM POR MÊS | G13: MARGEM % | H13: CHURN MENSAL (EQUIV.) | I13: VIDA MÉDIA | J13: LTV | K13: LTV / CAC | L13: PAYBACK DO CAC
B14: Essencial mensal | C14: =(1-Premissas!$F$23)*(1-Premissas!$F$24) -> 0.6 | D14: =Premissas!$C$13 -> 57.9 | E14: =D14*(Premissas!$C$30+Premissas!$C$28)+1*Premissas!$C$29+Premissas!$C$31 -> 6.4905 | F14: =D14-E14 -> 51.4095 | G14: =IFERROR(F14/D14,0) -> 0.88790155 | H14: =Premissas!$F$21 -> 0.05 | I14: =IFERROR(1/H14,0) -> 20 | J14: =IFERROR(D14*G14/H14,0) -> 1028.19 | K14: =IFERROR(J14/$C$8,0) -> 8.7913679 | L14: =IFERROR($C$8/F14,0) -> 2.2749588
B15: Essencial anual | C15: =(1-Premissas!$F$23)*Premissas!$F$24 -> 0.15 | D15: =Premissas!$F$13/12 -> 49.215 | E15: =D15*(Premissas!$C$30+Premissas!$C$28)+1/12*Premissas!$C$29+Premissas!$C$31 -> 5.2162583 | F15: =D15-E15 -> 43.998742 | G15: =IFERROR(F15/D15,0) -> 0.8940108 | H15: =(1-Premissas!$F$22)/12 -> 0.029166667 | I15: =IFERROR(1/H15,0) -> 34.285714 | J15: =IFERROR(D15*G15/H15,0) -> 1508.5283 | K15: =IFERROR(J15/$C$8,0) -> 12.898421 | L15: =IFERROR($C$8/F15,0) -> 2.6581327
B16: Pro mensal | C16: =Premissas!$F$23*(1-Premissas!$F$24) -> 0.2 | D16: =Premissas!$C$14 -> 87.9 | E16: =D16*(Premissas!$C$30+Premissas!$C$28)+1*Premissas!$C$29+Premissas!$C$31 -> 9.3405 | F16: =D16-E16 -> 78.5595 | G16: =IFERROR(F16/D16,0) -> 0.8937372 | H16: =Premissas!$F$21 -> 0.05 | I16: =IFERROR(1/H16,0) -> 20 | J16: =IFERROR(D16*G16/H16,0) -> 1571.19 | K16: =IFERROR(J16/$C$8,0) -> 13.434199 | L16: =IFERROR($C$8/F16,0) -> 1.4887378
B17: Pro anual | C17: =Premissas!$F$23*Premissas!$F$24 -> 0.05 | D17: =Premissas!$F$14/12 -> 70.32 | E17: =D17*(Premissas!$C$30+Premissas!$C$28)+1/12*Premissas!$C$29+Premissas!$C$31 -> 7.2212333 | F17: =D17-E17 -> 63.098767 | G17: =IFERROR(F17/D17,0) -> 0.89730897 | H17: =(1-Premissas!$F$22)/12 -> 0.029166667 | I17: =IFERROR(1/H17,0) -> 34.285714 | J17: =IFERROR(D17*G17/H17,0) -> 2163.3863 | K17: =IFERROR(J17/$C$8,0) -> 18.497675 | L17: =IFERROR($C$8/F17,0) -> 1.8535148
B18: MÉDIA PONDERADA (mix em uso) | C18: =SUM(C14:C17) -> 1 | D18: =SUMPRODUCT($C$14:$C$17,D14:D17) -> 63.21825 | E18: =SUMPRODUCT($C$14:$C$17,E14:E17) -> 6.9059004 | F18: =SUMPRODUCT($C$14:$C$17,F14:F17) -> 56.31235 | G18: =IFERROR(F18/D18,0) -> 0.89076097 | H18: =SUMPRODUCT($C$14:$C$17,H14:H17) -> 0.045833333 | I18: =IFERROR(1/H18,0) -> 21.818182 | J18: =IFERROR(D18*G18/H18,0) -> 1228.6331 | K18: =IFERROR(J18/$C$8,0) -> 10.505223 | L18: =IFERROR($C$8/F18,0) -> 2.0768889
B19: =IF(K18>=3,"✔ Saudável: cada cliente devolve 3x ou mais o que custou para conquistar.",IF(K18>=1,"⚠ Atenção: LTV/CAC entre 1x e 3x — o cliente se paga, mas sobra pouco.","✖ Cada cliente custa mais do que devolve. Reveja CAC, preço ou churn.")) -> ✔ Saudável: cada cliente devolve 3x ou mais o que custou para conquistar.
B20: Plano anual: churn equivalente = (1 − renovação) ÷ 12. Referência de mercado SaaS: LTV/CAC ≥ 3x e payback ≤ 12 meses.
B22: VISÃO REAL DA PROJEÇÃO (24 MESES)
B23: Ticket médio real (ARPU = MRR ÷ clientes ativos) | C23: =IFERROR('Projeção 24 meses'!$L$30/SUM('Projeção 24 meses'!$G$6:$G$29),0) -> 62.793301
B24: Margem bruta real % | C24: =IFERROR('Projeção 24 meses'!$R$30/'Projeção 24 meses'!$L$30,0) -> 0.89084378
B25: Churn efetivo médio (cancelados ÷ ativos do mês anterior) | C25: =IFERROR('Projeção 24 meses'!$F$30/(SUM('Projeção 24 meses'!$G$6:$G$29)-'Projeção 24 meses'!$G$29),0) -> 0.041340217 | D25: No início quase ninguém cancela (anuais só saem no mês 13), por isso o churn efetivo fica abaixo do churn digitado.
B26: LTV (ticket × margem ÷ churn efetivo) | C26: =IFERROR(C23*C24/C25,0) -> 1353.1381
B27: LTV / CAC | C27: =IFERROR(C26/$C$8,0) -> 11.569783
B28: Payback do CAC (meses) | C28: =IFERROR($C$8/(C23*C24),0) -> 2.0907497
B30: PONTO DE EQUILÍBRIO
B31: Margem média por cliente/mês (mix em uso) | C31: =F18 -> 56.31235
B32: Custos fixos no mês 24 | C32: ='Projeção 24 meses'!$T$29 -> 3395
B33: Clientes necessários para cobrir os custos fixos | C33: =IFERROR(ROUNDUP(C32/C31,0),0) -> 61 | D33: Mesmo número que a coluna CLIENTES P/ EQUILÍBRIO da Projeção (mês a mês).
B34: Clientes necessários para cobrir fixos + marketing do mês 24 | C34: =IFERROR(ROUNDUP((C32+'Projeção 24 meses'!$U$29+'Projeção 24 meses'!$V$29)/C31,0),0) -> 117
B35: Clientes ativos no mês 24 | C35: ='Projeção 24 meses'!$G$29 -> 338.01863
B36: Primeiro mês com lucro líquido positivo | C36: =IF(COUNT('Projeção 24 meses'!$AK$6:$AK$29)=0,"Não atinge em 24 meses",INDEX('Projeção 24 meses'!$C$6:$C$29,MIN('Projeção 24 meses'!$AK$6:$AK$29))) -> 46600

Sheet Cenários
B1: ⌂ Início | C1: ▦ Dashboard
B2: CENÁRIOS · PESSIMISTA × REALISTA × OTIMISTA
B3: Os três cenários calculados ao mesmo tempo. As premissas de cada um ficam na aba Premissas (tabela PREMISSAS DE VENDA POR CENÁRIO).
B5: INDICADOR | C5: PESSIMISTA | D5: REALISTA | E5: OTIMISTA
B6: Clientes ativos — mês 12 | C6: ='Motor Cenários'!$G$17 -> 40.305359 | D6: ='Motor Cenários'!$BD$17 -> 119.9192 | E6: ='Motor Cenários'!$DA$17 -> 332.74845
B7: Clientes ativos — mês 24 | C7: ='Motor Cenários'!$G$29 -> 73.035963 | D7: ='Motor Cenários'!$BD$29 -> 338.01863 | E7: ='Motor Cenários'!$DA$29 -> 1538.7836
B8: MRR — mês 12 | C8: ='Motor Cenários'!$L$17 -> 2458.177 | D8: ='Motor Cenários'!$BI$17 -> 7530.4908 | E8: ='Motor Cenários'!$DF$17 -> 21478.715
B9: MRR — mês 24 | C9: ='Motor Cenários'!$L$29 -> 4447.9118 | D9: ='Motor Cenários'!$BI$29 -> 21200.282 | E9: ='Motor Cenários'!$DF$29 -> 99235.94
B10: ARR — mês 24 | C10: ='Motor Cenários'!$M$29 -> 53374.942 | D10: ='Motor Cenários'!$BJ$29 -> 254403.38 | E10: ='Motor Cenários'!$DG$29 -> 1190831.3
B11: Ticket médio (ARPU) — mês 24 | C11: ='Motor Cenários'!$N$29 -> 60.900297 | D11: ='Motor Cenários'!$BK$29 -> 62.719269 | E11: ='Motor Cenários'!$DH$29 -> 64.489861
B12: Lucro líquido — mês 24 | C12: ='Motor Cenários'!$X$29 -> -2444.8569 | D12: ='Motor Cenários'!$BU$29 -> 12304.604 | E12: ='Motor Cenários'!$DR$29 -> 80923.91
B13: Lucro acumulado em 24 meses | C13: ='Motor Cenários'!$Y$29 -> -74078.754 | D13: ='Motor Cenários'!$BV$29 -> 62578.916 | E13: ='Motor Cenários'!$DS$29 -> 556251.74
B14: Caixa no fim do mês 24 | C14: ='Motor Cenários'!$AU$29 -> -71046.299 | D14: ='Motor Cenários'!$CR$29 -> 88375.441 | E14: ='Motor Cenários'!$EO$29 -> 734161.51
B15: Menor saldo de caixa (capital necessário) | C15: =MIN('Motor Cenários'!$AU$6:$AU$29) -> -71046.299 | D15: =MIN('Motor Cenários'!$CR$6:$CR$29) -> -9905.4545 | E15: =MIN('Motor Cenários'!$EO$6:$EO$29) -> -383.75148
B16: Primeiro mês com lucro | C16: =IF(COUNT('Motor Cenários'!$AJ$6:$AJ$29)=0,"Não atinge",INDEX('Motor Cenários'!$C$6:$C$29,MIN('Motor Cenários'!$AJ$6:$AJ$29))) -> Não atinge | D16: =IF(COUNT('Motor Cenários'!$CG$6:$CG$29)=0,"Não atinge",INDEX('Motor Cenários'!$AZ$6:$AZ$29,MIN('Motor Cenários'!$CG$6:$CG$29))) -> 46600 | E16: =IF(COUNT('Motor Cenários'!$ED$6:$ED$29)=0,"Não atinge",INDEX('Motor Cenários'!$CW$6:$CW$29,MIN('Motor Cenários'!$ED$6:$ED$29))) -> 46388
B17: CAC médio (24 meses) | C17: =IFERROR(('Motor Cenários'!$U$30+'Motor Cenários'!$V$30)/'Motor Cenários'!$D$30,0) -> 381 | D17: =IFERROR(('Motor Cenários'!$BR$30+'Motor Cenários'!$BS$30)/'Motor Cenários'!$BA$30,0) -> 116.9545 | E17: =IFERROR(('Motor Cenários'!$DO$30+'Motor Cenários'!$DP$30)/'Motor Cenários'!$CX$30,0) -> 35.136643
B18: LTV (ticket × margem ÷ churn equivalente) | C18: =IFERROR('Motor Cenários'!$R$29/'Motor Cenários'!$G$29/(Premissas!$C$21*(1-Premissas!$C$24)+(1-Premissas!$C$22)/12*Premissas!$C$24),0) -> 711.47868 | D18: =IFERROR('Motor Cenários'!$BO$29/'Motor Cenários'!$BD$29/(Premissas!$D$21*(1-Premissas!$D$24)+(1-Premissas!$D$22)/12*Premissas!$D$24),0) -> 1219.1386 | E18: =IFERROR('Motor Cenários'!$DL$29/'Motor Cenários'!$DA$29/(Premissas!$E$21*(1-Premissas!$E$24)+(1-Premissas!$E$22)/12*Premissas!$E$24),0) -> 2212.012
B19: LTV / CAC | C19: =IFERROR(C18/C17,0) -> 1.8673981 | D19: =IFERROR(D18/D17,0) -> 10.424042 | E19: =IFERROR(E18/E17,0) -> 62.954563
B20: LTV aqui usa a margem por cliente do mês 24 e o churn equivalente do mix (mensal + anual).
B21: =IF(ABS(INDEX(C9:E9,MATCH(Premissas!$C$9,$C$5:$E$5,0))-'Projeção 24 meses'!$L$29)<0.01,"✔ Conferência: o cenário em uso bate com a aba Projeção 24 meses.","✖ Conferência: diferença entre Motor e Projeção.") -> ✔ Conferência: o cenário em uso bate com a aba Projeção 24 meses.
B54: DADOS DOS GRÁFICOS
B55: MÊS | C55: MRR PESSIMISTA | D55: MRR REALISTA | E55: MRR OTIMISTA | F55: CLIENTES PESS. | G55: CLIENTES REAL. | H55: CLIENTES OTIM. | I55: CAIXA PESS. | J55: CAIXA REAL. | K55: CAIXA OTIM.
B56: ='Motor Cenários'!$AZ$6 -> 46296 | C56: ='Motor Cenários'!$L$6 -> 245.5923 | D56: ='Motor Cenários'!$BI$6 -> 505.746 | E56: ='Motor Cenários'!$DF$6 -> 972.90787 | F56: ='Motor Cenários'!$G$6 -> 4 | G56: ='Motor Cenários'!$BD$6 -> 8 | H56: ='Motor Cenários'!$DA$6 -> 15 | I56: ='Motor Cenários'!$AU$6 -> -3292.1188 | J56: ='Motor Cenários'!$CR$6 -> -2425.2832 | K56: ='Motor Cenários'!$EO$6 -> -383.75148
B57: ='Motor Cenários'!$AZ$7 -> 46327 | C57: ='Motor Cenários'!$L$7 -> 480.58117 | D57: ='Motor Cenários'!$BI$7 -> 1025.9662 | E57: ='Motor Cenários'!$DF$7 -> 2041.0187 | F57: ='Motor Cenários'!$G$7 -> 7.832 | G57: ='Motor Cenários'!$BD$7 -> 16.24 | H57: ='Motor Cenários'!$DA$7 -> 31.485 | I57: ='Motor Cenários'!$AU$7 -> -6433.5948 | J57: ='Motor Cenários'!$CR$7 -> -4453.6485 | K57: ='Motor Cenários'!$EO$7 -> 202.98559
B58: ='Motor Cenários'!$AZ$8 -> 46357 | C58: ='Motor Cenários'!$L$8 -> 706.0862 | D58: ='Motor Cenários'!$BI$8 -> 1562.7203 | E58: ='Motor Cenários'!$DF$8 -> 3216.4032 | F58: ='Motor Cenários'!$G$8 -> 11.514 | G58: ='Motor Cenários'!$BD$8 -> 24.7528 | H58: ='Motor Cenários'!$DA$8 -> 49.64265 | I58: ='Motor Cenários'!$AU$8 -> -9434.6092 | J58: ='Motor Cenários'!$CR$8 -> -6073.2036 | K58: ='Motor Cenários'!$EO$8 -> 1862.1082
B59: ='Motor Cenários'!$AZ$9 -> 46388 | C59: ='Motor Cenários'!$L$9 -> 923.14556 | D59: ='Motor Cenários'!$BI$9 -> 2118.1596 | E59: ='Motor Cenários'!$DF$9 -> 4512.5612 | F59: ='Motor Cenários'!$G$9 -> 15.062697 | G59: ='Motor Cenários'!$BD$9 -> 33.572696 | H59: ='Motor Cenários'!$DA$9 -> 69.682834 | I59: ='Motor Cenários'!$AU$9 -> -12304.473 | J59: ='Motor Cenários'!$CR$9 -> -7270.2848 | K59: ='Motor Cenários'!$EO$9 -> 4708.4207
B60: ='Motor Cenários'!$AZ$10 -> 46419 | C60: ='Motor Cenários'!$L$10 -> 1132.7227 | D60: ='Motor Cenários'!$BI$10 -> 2694.5365 | E60: ='Motor Cenários'!$DF$10 -> 5944.5937 | F60: ='Motor Cenários'!$G$10 -> 18.493592 | G60: ='Motor Cenários'!$BD$10 -> 42.735625 | H60: ='Motor Cenários'!$DA$10 -> 91.840349 | I60: ='Motor Cenários'!$AU$10 -> -15051.693 | J60: ='Motor Cenários'!$CR$10 -> -8029.3765 | K60: ='Motor Cenários'!$EO$10 -> 8871.1709
B61: ='Motor Cenários'!$AZ$11 -> 46447 | C61: ='Motor Cenários'!$L$11 -> 1335.7128 | D61: ='Motor Cenários'!$BI$11 -> 3294.2138 | E61: ='Motor Cenários'!$DF$11 -> 7529.3956 | F61: ='Motor Cenários'!$G$11 -> 21.821094 | G61: ='Motor Cenários'!$BD$11 -> 52.279316 | H61: ='Motor Cenários'!$DA$11 -> 116.3779 | I61: ='Motor Cenários'!$AU$11 -> -17684.038 | J61: ='Motor Cenários'!$CR$11 -> -8333.0211 | K61: ='Motor Cenários'!$EO$11 -> 14495.77
B62: ='Motor Cenários'!$AZ$12 -> 46478 | C62: ='Motor Cenários'!$L$12 -> 1532.9481 | D62: ='Motor Cenários'!$BI$12 -> 3919.6748 | E62: ='Motor Cenários'!$DF$12 -> 9285.8715 | F62: ='Motor Cenários'!$G$12 -> 25.058604 | G62: ='Motor Cenários'!$BD$12 -> 62.243457 | H62: ='Motor Cenários'!$DA$12 -> 143.58945 | I62: ='Motor Cenários'!$AU$12 -> -21408.594 | J62: ='Motor Cenários'!$CR$12 -> -9361.7213 | K62: ='Motor Cenários'!$EO$12 -> 20545.723
B63: ='Motor Cenários'!$AZ$13 -> 46508 | C63: ='Motor Cenários'!$L$13 -> 1725.2035 | D63: ='Motor Cenários'!$BI$13 -> 4573.5341 | E63: ='Motor Cenários'!$DF$13 -> 11235.177 | F63: ='Motor Cenários'!$G$13 -> 28.21861 | G63: ='Motor Cenários'!$BD$13 -> 72.669857 | H63: ='Motor Cenários'!$DA$13 -> 173.80401 | I63: ='Motor Cenários'!$AU$13 -> -25031.814 | J63: ='Motor Cenários'!$CR$13 -> -9893.8342 | K63: ='Motor Cenários'!$EO$13 -> 28404.783
B64: ='Motor Cenários'!$AZ$14 -> 46539 | C64: ='Motor Cenários'!$L$14 -> 1913.2014 | D64: ='Motor Cenários'!$BI$14 -> 5258.5487 | E64: ='Motor Cenários'!$DF$14 -> 13400.991 | F64: ='Motor Cenários'!$G$14 -> 31.312757 | G64: ='Motor Cenários'!$BD$14 -> 83.602638 | H64: ='Motor Cenários'!$DA$14 -> 207.38979 | I64: ='Motor Cenários'!$AU$14 -> -28559.573 | J64: ='Motor Cenários'!$CR$14 -> -9905.4545 | K64: ='Motor Cenários'!$EO$14 -> 38279.377
B65: ='Motor Cenários'!$AZ$15 -> 46569 | C65: ='Motor Cenários'!$L$15 -> 2097.616 | D65: ='Motor Cenários'!$BI$15 -> 5977.6303 | E65: ='Motor Cenários'!$DF$15 -> 15809.816 | F65: ='Motor Cenários'!$G$15 -> 34.35192 | G65: ='Motor Cenários'!$BD$15 -> 95.088419 | H65: ='Motor Cenários'!$DA$15 -> 244.75899 | I65: ='Motor Cenários'!$AU$15 -> -31997.207 | J65: ='Motor Cenários'!$CR$15 -> -9370.2888 | K65: ='Motor Cenários'!$EO$15 -> 50401.312
B66: ='Motor Cenários'!$AZ$16 -> 46600 | C66: ='Motor Cenários'!$L$16 -> 2279.0778 | D66: ='Motor Cenários'!$BI$16 -> 6733.8578 | E66: ='Motor Cenários'!$DF$16 -> 18491.319 | F66: ='Motor Cenários'!$G$16 -> 37.346276 | G66: ='Motor Cenários'!$BD$16 -> 107.17652 | H66: ='Motor Cenários'!$DA$16 -> 286.37303 | I66: ='Motor Cenários'!$AU$16 -> -35349.558 | J66: ='Motor Cenários'!$CR$16 -> -8259.519 | K66: ='Motor Cenários'!$EO$16 -> 65030.812
B67: ='Motor Cenários'!$AZ$17 -> 46631 | C67: ='Motor Cenários'!$L$17 -> 2458.177 | D67: ='Motor Cenários'!$BI$17 -> 7530.4908 | E67: ='Motor Cenários'!$DF$17 -> 21478.715 | F67: ='Motor Cenários'!$G$17 -> 40.305359 | G67: ='Motor Cenários'!$BD$17 -> 119.9192 | H67: ='Motor Cenários'!$DA$17 -> 332.74845 | I67: ='Motor Cenários'!$AU$17 -> -38621.008 | J67: ='Motor Cenários'!$CR$17 -> -6541.6546 | K67: ='Motor Cenários'!$EO$17 -> 82459.92
B68: ='Motor Cenários'!$AZ$18 -> 46661 | C68: ='Motor Cenários'!$L$18 -> 2624.991 | D68: ='Motor Cenários'!$BI$18 -> 8340.4692 | E68: ='Motor Cenários'!$DF$18 -> 24758.245 | F68: ='Motor Cenários'!$G$18 -> 43.038119 | G68: ='Motor Cenários'!$BD$18 -> 132.81185 | H68: ='Motor Cenários'!$DA$18 -> 383.56361 | I68: ='Motor Cenários'!$AU$18 -> -41701.742 | J68: ='Motor Cenários'!$CR$18 -> -3567.1564 | K68: ='Motor Cenários'!$EO$18 -> 105227.9
B69: ='Motor Cenários'!$AZ$19 -> 46692 | C69: ='Motor Cenários'!$L$19 -> 2790.2021 | D69: ='Motor Cenários'!$BI$19 -> 9195.8374 | E69: ='Motor Cenários'!$DF$19 -> 28416.368 | F69: ='Motor Cenários'!$G$19 -> 45.746973 | G69: ='Motor Cenários'!$BD$19 -> 146.43407 | H69: ='Motor Cenários'!$DA$19 -> 440.25803 | I69: ='Motor Cenários'!$AU$19 -> -44705.588 | J69: ='Motor Cenários'!$CR$19 -> 129.43214 | K69: ='Motor Cenários'!$EO$19 -> 131756.56
B70: ='Motor Cenários'!$AZ$20 -> 46722 | C70: ='Motor Cenários'!$L$20 -> 2954.2907 | D70: ='Motor Cenários'!$BI$20 -> 10100.338 | E70: ='Motor Cenários'!$DF$20 -> 32498.966 | F70: ='Motor Cenários'!$G$20 -> 48.439677 | G70: ='Motor Cenários'!$BD$20 -> 160.84557 | H70: ='Motor Cenários'!$DA$20 -> 503.54378 | I70: ='Motor Cenários'!$AU$20 -> -47635.642 | J70: ='Motor Cenários'!$CR$20 -> 4591.6637 | K70: ='Motor Cenários'!$EO$20 -> 162490.05
B71: ='Motor Cenários'!$AZ$21 -> 46753 | C71: ='Motor Cenários'!$L$21 -> 3117.7094 | D71: ='Motor Cenários'!$BI$21 -> 11057.948 | E71: ='Motor Cenários'!$DF$21 -> 37057.409 | F71: ='Motor Cenários'!$G$21 -> 51.123538 | G71: ='Motor Cenários'!$BD$21 -> 176.10983 | H71: ='Motor Cenários'!$DA$21 -> 574.21817 | I71: ='Motor Cenários'!$AU$21 -> -50494.665 | J71: ='Motor Cenários'!$CR$21 -> 9866.6947 | K71: ='Motor Cenários'!$EO$21 -> 197926.37
B72: ='Motor Cenários'!$AZ$22 -> 46784 | C72: ='Motor Cenários'!$L$22 -> 3280.8856 | D72: ='Motor Cenários'!$BI$22 -> 12072.895 | E72: ='Motor Cenários'!$DF$22 -> 42149.221 | F72: ='Motor Cenários'!$G$22 -> 53.805461 | G72: ='Motor Cenários'!$BD$22 -> 192.29433 | H72: ='Motor Cenários'!$DA$22 -> 653.17401 | I72: ='Motor Cenários'!$AU$22 -> -53285.099 | J72: ='Motor Cenários'!$CR$22 -> 16005.516 | K72: ='Motor Cenários'!$EO$22 -> 238623.84
B73: ='Motor Cenários'!$AZ$23 -> 46813 | C73: ='Motor Cenários'!$L$23 -> 3444.2235 | D73: ='Motor Cenários'!$BI$23 -> 13149.677 | E73: ='Motor Cenários'!$DF$23 -> 47838.816 | F73: ='Motor Cenários'!$G$23 -> 56.491984 | G73: ='Motor Cenários'!$BD$23 -> 209.4709 | H73: ='Motor Cenários'!$DA$23 -> 741.41106 | I73: ='Motor Cenários'!$AU$23 -> -56009.096 | J73: ='Motor Cenários'!$CR$23 -> 23063.2 | K73: ='Motor Cenários'!$EO$23 -> 285208.32
B74: ='Motor Cenários'!$AZ$24 -> 46844 | C74: ='Motor Cenários'!$L$24 -> 3608.1068 | D74: ='Motor Cenários'!$BI$24 -> 14293.083 | E74: ='Motor Cenários'!$DF$24 -> 54198.325 | F74: ='Motor Cenários'!$G$24 -> 59.189315 | G74: ='Motor Cenários'!$BD$24 -> 227.71603 | H74: ='Motor Cenários'!$DA$24 -> 840.04888 | I74: ='Motor Cenários'!$AU$24 -> -58668.535 | J74: ='Motor Cenários'!$CR$24 -> 31099.17 | K74: ='Motor Cenários'!$EO$24 -> 338381.32
B75: ='Motor Cenários'!$AZ$25 -> 46874 | C75: ='Motor Cenários'!$L$25 -> 3772.9001 | D75: ='Motor Cenários'!$BI$25 -> 15508.215 | E75: ='Motor Cenários'!$DF$25 -> 61308.523 | F75: ='Motor Cenários'!$G$25 -> 61.903359 | G75: ='Motor Cenários'!$BD$25 -> 247.11122 | H75: ='Motor Cenários'!$DA$25 -> 950.34118 | I75: ='Motor Cenários'!$AU$25 -> -61265.04 | J75: ='Motor Cenários'!$CR$25 -> 40177.484 | K75: ='Motor Cenários'!$EO$25 -> 398929.05
B76: ='Motor Cenários'!$AZ$26 -> 46905 | C76: ='Motor Cenários'!$L$26 -> 3938.9514 | D76: ='Motor Cenários'!$BI$26 -> 16800.508 | E76: ='Motor Cenários'!$DF$26 -> 69259.865 | F76: ='Motor Cenários'!$G$26 -> 64.639756 | G76: ='Motor Cenários'!$BD$26 -> 267.74332 | H76: ='Motor Cenários'!$DA$26 -> 1073.692 | I76: ='Motor Cenários'!$AU$26 -> -63800.003 | J76: ='Motor Cenários'!$CR$26 -> 50367.141 | K76: ='Motor Cenários'!$EO$26 -> 467732.63
B77: ='Motor Cenários'!$AZ$27 -> 46935 | C77: ='Motor Cenários'!$L$27 -> 4106.5931 | D77: ='Motor Cenários'!$BI$27 -> 18175.76 | E77: ='Motor Cenários'!$DF$27 -> 78153.652 | F77: ='Motor Cenários'!$G$27 -> 67.403901 | G77: ='Motor Cenários'!$BD$27 -> 289.70494 | H77: ='Motor Cenários'!$DA$27 -> 1211.6735 | I77: ='Motor Cenários'!$AU$27 -> -66274.59 | J77: ='Motor Cenários'!$CR$27 -> 61742.417 | K77: ='Motor Cenários'!$EO$27 -> 545779.44
B78: ='Motor Cenários'!$AZ$28 -> 46966 | C78: ='Motor Cenários'!$L$28 -> 4276.1443 | D78: ='Motor Cenários'!$BI$28 -> 19640.153 | E78: ='Motor Cenários'!$DF$28 -> 88103.327 | F78: ='Motor Cenários'!$G$28 -> 70.200974 | G78: ='Motor Cenários'!$BD$28 -> 313.0949 | H78: ='Motor Cenários'!$DA$28 -> 1366.0468 | I78: ='Motor Cenários'!$AU$28 -> -68689.766 | J78: ='Motor Cenários'!$CR$28 -> 74383.214 | K78: ='Motor Cenários'!$EO$28 -> 634175.84
B79: ='Motor Cenários'!$AZ$29 -> 46997 | C79: ='Motor Cenários'!$L$29 -> 4447.9118 | D79: ='Motor Cenários'!$BI$29 -> 21200.282 | E79: ='Motor Cenários'!$DF$29 -> 99235.94 | F79: ='Motor Cenários'!$G$29 -> 73.035963 | G79: ='Motor Cenários'!$BD$29 -> 338.01863 | H79: ='Motor Cenários'!$DA$29 -> 1538.7836 | I79: ='Motor Cenários'!$AU$29 -> -71046.299 | J79: ='Motor Cenários'!$CR$29 -> 88375.441 | K79: ='Motor Cenários'!$EO$29 -> 734161.51

Sheet Motor Cenários
B1: ⌂ Início | C1: ▦ Dashboard
B2: MOTOR DOS CENÁRIOS · CÁLCULO AUTOMÁTICO — NÃO EDITAR
B3: Mesma lógica da Projeção e do Fluxo de Caixa, rodando os três cenários ao mesmo tempo para a aba Cenários.
B4: PESSIMISTA | AY4: REALISTA | CV4: OTIMISTA
B5: Nº | C5: MÊS | D5: NOVOS CLIENTES | E5: TESTES GRÁTIS NECESSÁRIOS | F5: CANCELADOS | G5: CLIENTES ATIVOS | H5: ESSENCIAL MENSAL | I5: ESSENCIAL ANUAL | J5: PRO MENSAL | K5: PRO ANUAL | L5: MRR (RECEITA RECORRENTE) | M5: ARR (MRR × 12) | N5: TICKET MÉDIO (ARPU) | O5: IMPOSTOS | P5: GATEWAY | Q5: INFRA POR CLIENTE | R5: MARGEM BRUTA | S5: MARGEM BRUTA % | T5: CUSTOS FIXOS | U5: ANÚNCIOS | V5: COMISSÕES DE INDICAÇÃO | W5: CUSTOS TOTAIS | X5: LUCRO LÍQUIDO | Y5: LUCRO ACUMULADO | Z5: CAC DO MÊS | AA5: CLIENTES P/ EQUILÍBRIO | AB5: NOVOS ESS. MENSAL | AC5: NOVOS ESS. ANUAL | AD5: NOVOS PRO MENSAL | AE5: NOVOS PRO ANUAL | AF5: COBRANÇAS ANUAIS ESS. (NOVOS + RENOV.) | AG5: COBRANÇAS ANUAIS PRO (NOVOS + RENOV.) | AH5: ANUAIS QUE NÃO RENOVARAM | AI5: Nº DE COBRANÇAS NO MÊS | AJ5: MÊS COM LUCRO? | AK5: ENTRADA MENSALIDADES | AL5: ENTRADA PLANO ANUAL (À VISTA) | AM5: TOTAL DE ENTRADAS | AN5: (−) IMPOSTOS | AO5: (−) GATEWAY | AP5: (−) INFRA | AQ5: (−) CUSTOS FIXOS | AR5: (−) MARKETING | AS5: TOTAL DE SAÍDAS | AT5: SALDO DO MÊS | AU5: SALDO ACUMULADO EM CAIXA | AV5: RECEITA ANUAL RECONHECIDA NO MÊS | AW5: RECEITA ANUAL A RECONHECER (JÁ RECEBIDA) | AY5: Nº | AZ5: MÊS | BA5: NOVOS CLIENTES | BB5: TESTES GRÁTIS NECESSÁRIOS | BC5: CANCELADOS | BD5: CLIENTES ATIVOS | BE5: ESSENCIAL MENSAL | BF5: ESSENCIAL ANUAL | BG5: PRO MENSAL | BH5: PRO ANUAL | BI5: MRR (RECEITA RECORRENTE) | BJ5: ARR (MRR × 12) | BK5: TICKET MÉDIO (ARPU) | BL5: IMPOSTOS | BM5: GATEWAY | BN5: INFRA POR CLIENTE | BO5: MARGEM BRUTA | BP5: MARGEM BRUTA % | BQ5: CUSTOS FIXOS | BR5: ANÚNCIOS | BS5: COMISSÕES DE INDICAÇÃO | BT5: CUSTOS TOTAIS | BU5: LUCRO LÍQUIDO | BV5: LUCRO ACUMULADO | BW5: CAC DO MÊS | BX5: CLIENTES P/ EQUILÍBRIO | BY5: NOVOS ESS. MENSAL | BZ5: NOVOS ESS. ANUAL | CA5: NOVOS PRO MENSAL | CB5: NOVOS PRO ANUAL | CC5: COBRANÇAS ANUAIS ESS. (NOVOS + RENOV.) | CD5: COBRANÇAS ANUAIS PRO (NOVOS + RENOV.) | CE5: ANUAIS QUE NÃO RENOVARAM | CF5: Nº DE COBRANÇAS NO MÊS | CG5: MÊS COM LUCRO? | CH5: ENTRADA MENSALIDADES | CI5: ENTRADA PLANO ANUAL (À VISTA) | CJ5: TOTAL DE ENTRADAS | CK5: (−) IMPOSTOS | CL5: (−) GATEWAY | CM5: (−) INFRA | CN5: (−) CUSTOS FIXOS | CO5: (−) MARKETING | CP5: TOTAL DE SAÍDAS | CQ5: SALDO DO MÊS | CR5: SALDO ACUMULADO EM CAIXA | CS5: RECEITA ANUAL RECONHECIDA NO MÊS | CT5: RECEITA ANUAL A RECONHECER (JÁ RECEBIDA) | CV5: Nº | CW5: MÊS | CX5: NOVOS CLIENTES | CY5: TESTES GRÁTIS NECESSÁRIOS | CZ5: CANCELADOS | DA5: CLIENTES ATIVOS | DB5: ESSENCIAL MENSAL | DC5: ESSENCIAL ANUAL | DD5: PRO MENSAL | DE5: PRO ANUAL | DF5: MRR (RECEITA RECORRENTE) | DG5: ARR (MRR × 12) | DH5: TICKET MÉDIO (ARPU) | DI5: IMPOSTOS | DJ5: GATEWAY | DK5: INFRA POR CLIENTE | DL5: MARGEM BRUTA | DM5: MARGEM BRUTA % | DN5: CUSTOS FIXOS | DO5: ANÚNCIOS | DP5: COMISSÕES DE INDICAÇÃO | DQ5: CUSTOS TOTAIS | DR5: LUCRO LÍQUIDO | DS5: LUCRO ACUMULADO | DT5: CAC DO MÊS | DU5: CLIENTES P/ EQUILÍBRIO | DV5: NOVOS ESS. MENSAL | DW5: NOVOS ESS. ANUAL | DX5: NOVOS PRO MENSAL | DY5: NOVOS PRO ANUAL | DZ5: COBRANÇAS ANUAIS ESS. (NOVOS + RENOV.) | EA5: COBRANÇAS ANUAIS PRO (NOVOS + RENOV.) | EB5: ANUAIS QUE NÃO RENOVARAM | EC5: Nº DE COBRANÇAS NO MÊS | ED5: MÊS COM LUCRO? | EE5: ENTRADA MENSALIDADES | EF5: ENTRADA PLANO ANUAL (À VISTA) | EG5: TOTAL DE ENTRADAS | EH5: (−) IMPOSTOS | EI5: (−) GATEWAY | EJ5: (−) INFRA | EK5: (−) CUSTOS FIXOS | EL5: (−) MARKETING | EM5: TOTAL DE SAÍDAS | EN5: SALDO DO MÊS | EO5: SALDO ACUMULADO EM CAIXA | EP5: RECEITA ANUAL RECONHECIDA NO MÊS | EQ5: RECEITA ANUAL A RECONHECER (JÁ RECEBIDA)
B6: =1 -> 1 | C6: =EDATE(Premissas!$C$7,B6-1) -> 46296 | D6: =Premissas!$C$19*(1+Premissas!$C$20)^(B6-1) -> 4 | E6: =IFERROR(D6/Premissas!$C$25,0) -> 40 | F6: =(N(H5)+N(J5))*Premissas!$C$21+AH6 -> 0 | G6: =H6+I6+J6+K6 -> 4 | H6: =N(H5)*(1-Premissas!$C$21)+AB6 -> 3.06 | I6: =SUM(INDEX($AF$6:$AF$29,MAX(1,B6-11)):INDEX($AF$6:$AF$29,B6)) -> 0.34 | J6: =N(J5)*(1-Premissas!$C$21)+AD6 -> 0.54 | K6: =SUM(INDEX($AG$6:$AG$29,MAX(1,B6-11)):INDEX($AG$6:$AG$29,B6)) -> 0.06 | L6: =H6*Premissas!$C$13+I6*Premissas!$F$13/12+J6*Premissas!$C$14+K6*Premissas!$F$14/12 -> 245.5923 | M6: =L6*12 -> 2947.1076 | N6: =IFERROR(L6/G6,0) -> 61.398075 | O6: =L6*Premissas!$C$30 -> 14.735538 | P6: =L6*Premissas!$C$28+AI6*Premissas!$C$29 -> 10.55573 | Q6: =G6*Premissas!$C$31 -> 2 | R6: =L6-O6-P6-Q6 -> 218.30103 | S6: =IFERROR(R6/L6,0) -> 0.88887572 | T6: =SUMPRODUCT(Premissas!$C$42:$C$61,--(Premissas!$D$42:$D$61<=B6)) -> 2195 | U6: =Premissas!$C$34*(1+Premissas!$C$35)^(B6-1) -> 1500 | V6: =D6*Premissas!$C$36*Premissas!$C$37 -> 24 | W6: =O6+P6+Q6+T6+U6+V6 -> 3746.2913 | X6: =L6-W6 -> -3500.699 | Y6: =N(Y5)+X6 -> -3500.699 | Z6: =IFERROR((U6+V6)/D6,0) -> 381 | AA6: =IFERROR(T6/(R6/G6),0) -> 40.219691 | AB6: =D6*(1-Premissas!$C$23)*(1-Premissas!$C$24) -> 3.06 | AC6: =D6*(1-Premissas!$C$23)*Premissas!$C$24 -> 0.34 | AD6: =D6*Premissas!$C$23*(1-Premissas!$C$24) -> 0.54 | AE6: =D6*Premissas!$C$23*Premissas!$C$24 -> 0.06 | AF6: =AC6+IF(B6>12,INDEX($AC$6:$AC$29,B6-12)*Premissas!$C$22,0) -> 0.34 | AG6: =AE6+IF(B6>12,INDEX($AE$6:$AE$29,B6-12)*Premissas!$C$22,0) -> 0.06 | AH6: =IF(B6>12,(INDEX($AC$6:$AC$29,B6-12)+INDEX($AE$6:$AE$29,B6-12))*(1-Premissas!$C$22),0) -> 0 | AI6: =H6+J6+AF6+AG6 -> 4 | AJ6: =IF(X6>0,B6,"") | AK6: =H6*Premissas!$C$13+J6*Premissas!$C$14 -> 224.64 | AL6: =AF6*Premissas!$F$13+AG6*Premissas!$F$14 -> 251.4276 | AM6: =AK6+AL6 -> 476.0676 | AN6: =AM6*Premissas!$C$30 -> 28.564056 | AO6: =AM6*Premissas!$C$28+AI6*Premissas!$C$29 -> 18.622366 | AP6: =Q6 -> 2 | AQ6: =T6 -> 2195 | AR6: =U6+V6 -> 1524 | AS6: =AN6+AO6+AP6+AQ6+AR6 -> 3768.1864 | AT6: =AM6-AS6 -> -3292.1188 | AU6: =IF(B6=1,Premissas!$C$8,N(AU5))+AT6 -> -3292.1188 | AV6: =I6*Premissas!$F$13/12+K6*Premissas!$F$14/12 -> 20.9523 | AW6: =N(AW5)+AL6-AV6 -> 230.4753 | AY6: =1 -> 1 | AZ6: =EDATE(Premissas!$C$7,AY6-1) -> 46296 | BA6: =Premissas!$D$19*(1+Premissas!$D$20)^(AY6-1) -> 8 | BB6: =IFERROR(BA6/Premissas!$D$25,0) -> 40 | BC6: =(N(BE5)+N(BG5))*Premissas!$D$21+CE6 -> 0 | BD6: =BE6+BF6+BG6+BH6 -> 8 | BE6: =N(BE5)*(1-Premissas!$D$21)+BY6 -> 4.8 | BF6: =SUM(INDEX($CC$6:$CC$29,MAX(1,AY6-11)):INDEX($CC$6:$CC$29,AY6)) -> 1.2 | BG6: =N(BG5)*(1-Premissas!$D$21)+CA6 -> 1.6 | BH6: =SUM(INDEX($CD$6:$CD$29,MAX(1,AY6-11)):INDEX($CD$6:$CD$29,AY6)) -> 0.4 | BI6: =BE6*Premissas!$C$13+BF6*Premissas!$F$13/12+BG6*Premissas!$C$14+BH6*Premissas!$F$14/12 -> 505.746 | BJ6: =BI6*12 -> 6068.952 | BK6: =IFERROR(BI6/BD6,0) -> 63.21825 | BL6: =BI6*Premissas!$C$30 -> 30.34476 | BM6: =BI6*Premissas!$C$28+CF6*Premissas!$C$29 -> 21.62111 | BN6: =BD6*Premissas!$C$31 -> 4 | BO6: =BI6-BL6-BM6-BN6 -> 449.78013 | BP6: =IFERROR(BO6/BI6,0) -> 0.88933997 | BQ6: =SUMPRODUCT(Premissas!$C$42:$C$61,--(Premissas!$D$42:$D$61<=AY6)) -> 2195 | BR6: =Premissas!$C$34*(1+Premissas!$C$35)^(AY6-1) -> 1500 | BS6: =BA6*Premissas!$C$36*Premissas!$C$37 -> 48 | BT6: =BL6+BM6+BN6+BQ6+BR6+BS6 -> 3798.9659 | BU6: =BI6-BT6 -> -3293.2199 | BV6: =N(BV5)+BU6 -> -3293.2199 | BW6: =IFERROR((BR6+BS6)/BA6,0) -> 193.5 | BX6: =IFERROR(BQ6/(BO6/BD6),0) -> 39.041298 | BY6: =BA6*(1-Premissas!$D$23)*(1-Premissas!$D$24) -> 4.8 | BZ6: =BA6*(1-Premissas!$D$23)*Premissas!$D$24 -> 1.2 | CA6: =BA6*Premissas!$D$23*(1-Premissas!$D$24) -> 1.6 | CB6: =BA6*Premissas!$D$23*Premissas!$D$24 -> 0.4 | CC6: =BZ6+IF(AY6>12,INDEX($BZ$6:$BZ$29,AY6-12)*Premissas!$D$22,0) -> 1.2 | CD6: =CB6+IF(AY6>12,INDEX($CB$6:$CB$29,AY6-12)*Premissas!$D$22,0) -> 0.4 | CE6: =IF(AY6>12,(INDEX($BZ$6:$BZ$29,AY6-12)+INDEX($CB$6:$CB$29,AY6-12))*(1-Premissas!$D$22),0) -> 0 | CF6: =BE6+BG6+CC6+CD6 -> 8 | CG6: =IF(BU6>0,AY6,"") | CH6: =BE6*Premissas!$C$13+BG6*Premissas!$C$14 -> 418.56 | CI6: =CC6*Premissas!$F$13+CD6*Premissas!$F$14 -> 1046.232 | CJ6: =CH6+CI6 -> 1464.792 | CK6: =CJ6*Premissas!$C$30 -> 87.88752 | CL6: =CJ6*Premissas!$C$28+CF6*Premissas!$C$29 -> 55.18772 | CM6: =BN6 -> 4 | CN6: =BQ6 -> 2195 | CO6: =BR6+BS6 -> 1548 | CP6: =CK6+CL6+CM6+CN6+CO6 -> 3890.0752 | CQ6: =CJ6-CP6 -> -2425.2832 | CR6: =IF(AY6=1,Premissas!$C$8,N(CR5))+CQ6 -> -2425.2832 | CS6: =BF6*Premissas!$F$13/12+BH6*Premissas!$F$14/12 -> 87.186 | CT6: =N(CT5)+CI6-CS6 -> 959.046 | CV6: =1 -> 1 | CW6: =EDATE(Premissas!$C$7,CV6-1) -> 46296 | CX6: =Premissas!$E$19*(1+Premissas!$E$20)^(CV6-1) -> 15 | CY6: =IFERROR(CX6/Premissas!$E$25,0) -> 50 | CZ6: =(N(DB5)+N(DD5))*Premissas!$E$21+EB6 -> 0 | DA6: =DB6+DC6+DD6+DE6 -> 15 | DB6: =N(DB5)*(1-Premissas!$E$21)+DV6 -> 6.825 | DC6: =SUM(INDEX($DZ$6:$DZ$29,MAX(1,CV6-11)):INDEX($DZ$6:$DZ$29,CV6)) -> 2.925 | DD6: =N(DD5)*(1-Premissas!$E$21)+DX6 -> 3.675 | DE6: =SUM(INDEX($EA$6:$EA$29,MAX(1,CV6-11)):INDEX($EA$6:$EA$29,CV6)) -> 1.575 | DF6: =DB6*Premissas!$C$13+DC6*Premissas!$F$13/12+DD6*Premissas!$C$14+DE6*Premissas!$F$14/12 -> 972.90787 | DG6: =DF6*12 -> 11674.895 | DH6: =IFERROR(DF6/DA6,0) -> 64.860525 | DI6: =DF6*Premissas!$C$30 -> 58.374473 | DJ6: =DF6*Premissas!$C$28+EC6*Premissas!$C$29 -> 41.401776 | DK6: =DA6*Premissas!$C$31 -> 7.5 | DL6: =DF6-DI6-DJ6-DK6 -> 865.63163 | DM6: =IFERROR(DL6/DF6,0) -> 0.88973648 | DN6: =SUMPRODUCT(Premissas!$C$42:$C$61,--(Premissas!$D$42:$D$61<=CV6)) -> 2195 | DO6: =Premissas!$C$34*(1+Premissas!$C$35)^(CV6-1) -> 1500 | DP6: =CX6*Premissas!$C$36*Premissas!$C$37 -> 90 | DQ6: =DI6+DJ6+DK6+DN6+DO6+DP6 -> 3892.2762 | DR6: =DF6-DQ6 -> -2919.3684 | DS6: =N(DS5)+DR6 -> -2919.3684 | DT6: =IFERROR((DO6+DP6)/CX6,0) -> 106 | DU6: =IFERROR(DN6/(DL6/DA6),0) -> 38.03581 | DV6: =CX6*(1-Premissas!$E$23)*(1-Premissas!$E$24) -> 6.825 | DW6: =CX6*(1-Premissas!$E$23)*Premissas!$E$24 -> 2.925 | DX6: =CX6*Premissas!$E$23*(1-Premissas!$E$24) -> 3.675 | DY6: =CX6*Premissas!$E$23*Premissas!$E$24 -> 1.575 | DZ6: =DW6+IF(CV6>12,INDEX($DW$6:$DW$29,CV6-12)*Premissas!$E$22,0) -> 2.925 | EA6: =DY6+IF(CV6>12,INDEX($DY$6:$DY$29,CV6-12)*Premissas!$E$22,0) -> 1.575 | EB6: =IF(CV6>12,(INDEX($DW$6:$DW$29,CV6-12)+INDEX($DY$6:$DY$29,CV6-12))*(1-Premissas!$E$22),0) -> 0 | EC6: =DB6+DD6+DZ6+EA6 -> 15 | ED6: =IF(DR6>0,CV6,"") | EE6: =DB6*Premissas!$C$13+DD6*Premissas!$C$14 -> 718.2 | EF6: =DZ6*Premissas!$F$13+EA6*Premissas!$F$14 -> 3056.4945 | EG6: =EE6+EF6 -> 3774.6945 | EH6: =EG6*Premissas!$C$30 -> 226.48167 | EI6: =EG6*Premissas!$C$28+EC6*Premissas!$C$29 -> 139.46431 | EJ6: =DK6 -> 7.5 | EK6: =DN6 -> 2195 | EL6: =DO6+DP6 -> 1590 | EM6: =EH6+EI6+EJ6+EK6+EL6 -> 4158.446 | EN6: =EG6-EM6 -> -383.75148 | EO6: =IF(CV6=1,Premissas!$C$8,N(EO5))+EN6 -> -383.75148 | EP6: =DC6*Premissas!$F$13/12+DE6*Premissas!$F$14/12 -> 254.70788 | EQ6: =N(EQ5)+EF6-EP6 -> 2801.7866
B7: =B6+1 -> 2 | C7: =EDATE(Premissas!$C$7,B7-1) -> 46327 | D7: =Premissas!$C$19*(1+Premissas!$C$20)^(B7-1) -> 4.12 | E7: =IFERROR(D7/Premissas!$C$25,0) -> 41.2 | F7: =(N(H6)+N(J6))*Premissas!$C$21+AH7 -> 0.288 | G7: =H7+I7+J7+K7 -> 7.832 | H7: =N(H6)*(1-Premissas!$C$21)+AB7 -> 5.967 | I7: =SUM(INDEX($AF$6:$AF$29,MAX(1,B7-11)):INDEX($AF$6:$AF$29,B7)) -> 0.6902 | J7: =N(J6)*(1-Premissas!$C$21)+AD7 -> 1.053 | K7: =SUM(INDEX($AG$6:$AG$29,MAX(1,B7-11)):INDEX($AG$6:$AG$29,B7)) -> 0.1218 | L7: =H7*Premissas!$C$13+I7*Premissas!$F$13/12+J7*Premissas!$C$14+K7*Premissas!$F$14/12 -> 480.58117 | M7: =L7*12 -> 5766.974 | N7: =IFERROR(L7/G7,0) -> 61.361232 | O7: =L7*Premissas!$C$30 -> 28.83487 | P7: =L7*Premissas!$C$28+AI7*Premissas!$C$29 -> 20.462021 | Q7: =G7*Premissas!$C$31 -> 3.916 | R7: =L7-O7-P7-Q7 -> 427.36828 | S7: =IFERROR(R7/L7,0) -> 0.88927387 | T7: =SUMPRODUCT(Premissas!$C$42:$C$61,--(Premissas!$D$42:$D$61<=B7)) -> 2195 | U7: =Premissas!$C$34*(1+Premissas!$C$35)^(B7-1) -> 1545 | V7: =D7*Premissas!$C$36*Premissas!$C$37 -> 24.72 | W7: =O7+P7+Q7+T7+U7+V7 -> 3817.9329 | X7: =L7-W7 -> -3337.3517 | Y7: =N(Y6)+X7 -> -6838.0507 | Z7: =IFERROR((U7+V7)/D7,0) -> 381 | AA7: =IFERROR(T7/(R7/G7),0) -> 40.225821 | AB7: =D7*(1-Premissas!$C$23)*(1-Premissas!$C$24) -> 3.1518 | AC7: =D7*(1-Premissas!$C$23)*Premissas!$C$24 -> 0.3502 | AD7: =D7*Premissas!$C$23*(1-Premissas!$C$24) -> 0.5562 | AE7: =D7*Premissas!$C$23*Premissas!$C$24 -> 0.0618 | AF7: =AC7+IF(B7>12,INDEX($AC$6:$AC$29,B7-12)*Premissas!$C$22,0) -> 0.3502 | AG7: =AE7+IF(B7>12,INDEX($AE$6:$AE$29,B7-12)*Premissas!$C$22,0) -> 0.0618 | AH7: =IF(B7>12,(INDEX($AC$6:$AC$29,B7-12)+INDEX($AE$6:$AE$29,B7-12))*(1-Premissas!$C$22),0) -> 0 | AI7: =H7+J7+AF7+AG7 -> 7.432 | AJ7: =IF(X7>0,B7,"") | AK7: =H7*Premissas!$C$13+J7*Premissas!$C$14 -> 438.048 | AL7: =AF7*Premissas!$F$13+AG7*Premissas!$F$14 -> 258.97043 | AM7: =AK7+AL7 -> 697.01843 | AN7: =AM7*Premissas!$C$30 -> 41.821106 | AO7: =AM7*Premissas!$C$28+AI7*Premissas!$C$29 -> 28.037325 | AP7: =Q7 -> 3.916 | AQ7: =T7 -> 2195 | AR7: =U7+V7 -> 1569.72 | AS7: =AN7+AO7+AP7+AQ7+AR7 -> 3838.4944 | AT7: =AM7-AS7 -> -3141.476 | AU7: =IF(B7=1,Premissas!$C$8,N(AU6))+AT7 -> -6433.5948 | AV7: =I7*Premissas!$F$13/12+K7*Premissas!$F$14/12 -> 42.533169 | AW7: =N(AW6)+AL7-AV7 -> 446.91256 | AY7: =AY6+1 -> 2 | AZ7: =EDATE(Premissas!$C$7,AY7-1) -> 46327 | BA7: =Premissas!$D$19*(1+Premissas!$D$20)^(AY7-1) -> 8.56 | BB7: =IFERROR(BA7/Premissas!$D$25,0) -> 42.8 | BC7: =(N(BE6)+N(BG6))*Premissas!$D$21+CE7 -> 0.32 | BD7: =BE7+BF7+BG7+BH7 -> 16.24 | BE7: =N(BE6)*(1-Premissas!$D$21)+BY7 -> 9.696 | BF7: =SUM(INDEX($CC$6:$CC$29,MAX(1,AY7-11)):INDEX($CC$6:$CC$29,AY7)) -> 2.484 | BG7: =N(BG6)*(1-Premissas!$D$21)+CA7 -> 3.232 | BH7: =SUM(INDEX($CD$6:$CD$29,MAX(1,AY7-11)):INDEX($CD$6:$CD$29,AY7)) -> 0.828 | BI7: =BE7*Premissas!$C$13+BF7*Premissas!$F$13/12+BG7*Premissas!$C$14+BH7*Premissas!$F$14/12 -> 1025.9662 | BJ7: =BI7*12 -> 12311.595 | BK7: =IFERROR(BI7/BD7,0) -> 63.17526 | BL7: =BI7*Premissas!$C$30 -> 61.557973 | BM7: =BI7*Premissas!$C$28+CF7*Premissas!$C$29 -> 43.082418 | BN7: =BD7*Premissas!$C$31 -> 8.12 | BO7: =BI7-BL7-BM7-BN7 -> 913.20583 | BP7: =IFERROR(BO7/BI7,0) -> 0.89009347 | BQ7: =SUMPRODUCT(Premissas!$C$42:$C$61,--(Premissas!$D$42:$D$61<=AY7)) -> 2195 | BR7: =Premissas!$C$34*(1+Premissas!$C$35)^(AY7-1) -> 1545 | BS7: =BA7*Premissas!$C$36*Premissas!$C$37 -> 51.36 | BT7: =BL7+BM7+BN7+BQ7+BR7+BS7 -> 3904.1204 | BU7: =BI7-BT7 -> -2878.1542 | BV7: =N(BV6)+BU7 -> -6171.374 | BW7: =IFERROR((BR7+BS7)/BA7,0) -> 186.49065 | BX7: =IFERROR(BQ7/(BO7/BD7),0) -> 39.034792 | BY7: =BA7*(1-Premissas!$D$23)*(1-Premissas!$D$24) -> 5.136 | BZ7: =BA7*(1-Premissas!$D$23)*Premissas!$D$24 -> 1.284 | CA7: =BA7*Premissas!$D$23*(1-Premissas!$D$24) -> 1.712 | CB7: =BA7*Premissas!$D$23*Premissas!$D$24 -> 0.428 | CC7: =BZ7+IF(AY7>12,INDEX($BZ$6:$BZ$29,AY7-12)*Premissas!$D$22,0) -> 1.284 | CD7: =CB7+IF(AY7>12,INDEX($CB$6:$CB$29,AY7-12)*Premissas!$D$22,0) -> 0.428 | CE7: =IF(AY7>12,(INDEX($BZ$6:$BZ$29,AY7-12)+INDEX($CB$6:$CB$29,AY7-12))*(1-Premissas!$D$22),0) -> 0 | CF7: =BE7+BG7+CC7+CD7 -> 14.64 | CG7: =IF(BU7>0,AY7,"") | CH7: =BE7*Premissas!$C$13+BG7*Premissas!$C$14 -> 845.4912 | CI7: =CC7*Premissas!$F$13+CD7*Premissas!$F$14 -> 1119.4682 | CJ7: =CH7+CI7 -> 1964.9594 | CK7: =CJ7*Premissas!$C$30 -> 117.89757 | CL7: =CJ7*Premissas!$C$28+CF7*Premissas!$C$29 -> 75.94718 | CM7: =BN7 -> 8.12 | CN7: =BQ7 -> 2195 | CO7: =BR7+BS7 -> 1596.36 | CP7: =CK7+CL7+CM7+CN7+CO7 -> 3993.3247 | CQ7: =CJ7-CP7 -> -2028.3653 | CR7: =IF(AY7=1,Premissas!$C$8,N(CR6))+CQ7 -> -4453.6485 | CS7: =BF7*Premissas!$F$13/12+BH7*Premissas!$F$14/12 -> 180.47502 | CT7: =N(CT6)+CI7-CS7 -> 1898.0392 | CV7: =CV6+1 -> 2 | CW7: =EDATE(Premissas!$C$7,CV7-1) -> 46327 | CX7: =Premissas!$E$19*(1+Premissas!$E$20)^(CV7-1) -> 16.8 | CY7: =IFERROR(CX7/Premissas!$E$25,0) -> 56 | CZ7: =(N(DB6)+N(DD6))*Premissas!$E$21+EB7 -> 0.315 | DA7: =DB7+DC7+DD7+DE7 -> 31.485 | DB7: =N(DB6)*(1-Premissas!$E$21)+DV7 -> 14.26425 | DC7: =SUM(INDEX($DZ$6:$DZ$29,MAX(1,CV7-11)):INDEX($DZ$6:$DZ$29,CV7)) -> 6.201 | DD7: =N(DD6)*(1-Premissas!$E$21)+DX7 -> 7.68075 | DE7: =SUM(INDEX($EA$6:$EA$29,MAX(1,CV7-11)):INDEX($EA$6:$EA$29,CV7)) -> 3.339 | DF7: =DB7*Premissas!$C$13+DC7*Premissas!$F$13/12+DD7*Premissas!$C$14+DE7*Premissas!$F$14/12 -> 2041.0187 | DG7: =DF7*12 -> 24492.224 | DH7: =IFERROR(DF7/DA7,0) -> 64.825113 | DI7: =DF7*Premissas!$C$30 -> 122.46112 | DJ7: =DF7*Premissas!$C$28+EC7*Premissas!$C$29 -> 84.658304 | DK7: =DA7*Premissas!$C$31 -> 15.7425 | DL7: =DF7-DI7-DJ7-DK7 -> 1818.1568 | DM7: =IFERROR(DL7/DF7,0) -> 0.89080848 | DN7: =SUMPRODUCT(Premissas!$C$42:$C$61,--(Premissas!$D$42:$D$61<=CV7)) -> 2195 | DO7: =Premissas!$C$34*(1+Premissas!$C$35)^(CV7-1) -> 1545 | DP7: =CX7*Premissas!$C$36*Premissas!$C$37 -> 100.8 | DQ7: =DI7+DJ7+DK7+DN7+DO7+DP7 -> 4063.6619 | DR7: =DF7-DQ7 -> -2022.6432 | DS7: =N(DS6)+DR7 -> -4942.0116 | DT7: =IFERROR((DO7+DP7)/CX7,0) -> 97.964286 | DU7: =IFERROR(DN7/(DL7/DA7),0) -> 38.01079 | DV7: =CX7*(1-Premissas!$E$23)*(1-Premissas!$E$24) -> 7.644 | DW7: =CX7*(1-Premissas!$E$23)*Premissas!$E$24 -> 3.276 | DX7: =CX7*Premissas!$E$23*(1-Premissas!$E$24) -> 4.116 | DY7: =CX7*Premissas!$E$23*Premissas!$E$24 -> 1.764 | DZ7: =DW7+IF(CV7>12,INDEX($DW$6:$DW$29,CV7-12)*Premissas!$E$22,0) -> 3.276 | EA7: =DY7+IF(CV7>12,INDEX($DY$6:$DY$29,CV7-12)*Premissas!$E$22,0) -> 1.764 | EB7: =IF(CV7>12,(INDEX($DW$6:$DW$29,CV7-12)+INDEX($DY$6:$DY$29,CV7-12))*(1-Premissas!$E$22),0) -> 0 | EC7: =DB7+DD7+DZ7+EA7 -> 26.985 | ED7: =IF(DR7>0,CV7,"") | EE7: =DB7*Premissas!$C$13+DD7*Premissas!$C$14 -> 1501.038 | EF7: =DZ7*Premissas!$F$13+EA7*Premissas!$F$14 -> 3423.2738 | EG7: =EE7+EF7 -> 4924.3118 | EH7: =EG7*Premissas!$C$30 -> 295.45871 | EI7: =EG7*Premissas!$C$28+EC7*Premissas!$C$29 -> 185.57356 | EJ7: =DK7 -> 15.7425 | EK7: =DN7 -> 2195 | EL7: =DO7+DP7 -> 1645.8 | EM7: =EH7+EI7+EJ7+EK7+EL7 -> 4337.5748 | EN7: =EG7-EM7 -> 586.73707 | EO7: =IF(CV7=1,Premissas!$C$8,N(EO6))+EN7 -> 202.98559 | EP7: =DC7*Premissas!$F$13/12+DE7*Premissas!$F$14/12 -> 539.98069 | EQ7: =N(EQ6)+EF7-EP7 -> 5685.0798
B8: =B7+1 -> 3 | C8: =EDATE(Premissas!$C$7,B8-1) -> 46357 | D8: =Premissas!$C$19*(1+Premissas!$C$20)^(B8-1) -> 4.2436 | E8: =IFERROR(D8/Premissas!$C$25,0) -> 42.436 | F8: =(N(H7)+N(J7))*Premissas!$C$21+AH8 -> 0.5616 | G8: =H8+I8+J8+K8 -> 11.514 | H8: =N(H7)*(1-Premissas!$C$21)+AB8 -> 8.735994 | I8: =SUM(INDEX($AF$6:$AF$29,MAX(1,B8-11)):INDEX($AF$6:$AF$29,B8)) -> 1.050906 | J8: =N(J7)*(1-Premissas!$C$21)+AD8 -> 1.541646 | K8: =SUM(INDEX($AG$6:$AG$29,MAX(1,B8-11)):INDEX($AG$6:$AG$29,B8)) -> 0.185454 | L8: =H8*Premissas!$C$13+I8*Premissas!$F$13/12+J8*Premissas!$C$14+K8*Premissas!$F$14/12 -> 706.0862 | M8: =L8*12 -> 8473.0344 | N8: =IFERROR(L8/G8,0) -> 61.324145 | O8: =L8*Premissas!$C$30 -> 42.365172 | P8: =L8*Premissas!$C$28+AI8*Premissas!$C$29 -> 29.956997 | Q8: =G8*Premissas!$C$31 -> 5.757 | R8: =L8-O8-P8-Q8 -> 628.00703 | S8: =IFERROR(R8/L8,0) -> 0.88941978 | T8: =SUMPRODUCT(Premissas!$C$42:$C$61,--(Premissas!$D$42:$D$61<=B8)) -> 2195 | U8: =Premissas!$C$34*(1+Premissas!$C$35)^(B8-1) -> 1591.35 | V8: =D8*Premissas!$C$36*Premissas!$C$37 -> 25.4616 | W8: =O8+P8+Q8+T8+U8+V8 -> 3889.8908 | X8: =L8-W8 -> -3183.8046 | Y8: =N(Y7)+X8 -> -10021.855 | Z8: =IFERROR((U8+V8)/D8,0) -> 381 | AA8: =IFERROR(T8/(R8/G8),0) -> 40.243546 | AB8: =D8*(1-Premissas!$C$23)*(1-Premissas!$C$24) -> 3.246354 | AC8: =D8*(1-Premissas!$C$23)*Premissas!$C$24 -> 0.360706 | AD8: =D8*Premissas!$C$23*(1-Premissas!$C$24) -> 0.572886 | AE8: =D8*Premissas!$C$23*Premissas!$C$24 -> 0.063654 | AF8: =AC8+IF(B8>12,INDEX($AC$6:$AC$29,B8-12)*Premissas!$C$22,0) -> 0.360706 | AG8: =AE8+IF(B8>12,INDEX($AE$6:$AE$29,B8-12)*Premissas!$C$22,0) -> 0.063654 | AH8: =IF(B8>12,(INDEX($AC$6:$AC$29,B8-12)+INDEX($AE$6:$AE$29,B8-12))*(1-Premissas!$C$22),0) -> 0 | AI8: =H8+J8+AF8+AG8 -> 10.702 | AJ8: =IF(X8>0,B8,"") | AK8: =H8*Premissas!$C$13+J8*Premissas!$C$14 -> 641.32474 | AL8: =AF8*Premissas!$F$13+AG8*Premissas!$F$14 -> 266.73954 | AM8: =AK8+AL8 -> 908.06428 | AN8: =AM8*Premissas!$C$30 -> 54.483857 | AO8: =AM8*Premissas!$C$28+AI8*Premissas!$C$29 -> 37.02623 | AP8: =Q8 -> 5.757 | AQ8: =T8 -> 2195 | AR8: =U8+V8 -> 1616.8116 | AS8: =AN8+AO8+AP8+AQ8+AR8 -> 3909.0787 | AT8: =AM8-AS8 -> -3001.0144 | AU8: =IF(B8=1,Premissas!$C$8,N(AU7))+AT8 -> -9434.6092 | AV8: =I8*Premissas!$F$13/12+K8*Premissas!$F$14/12 -> 64.761464 | AW8: =N(AW7)+AL8-AV8 -> 648.89064 | AY8: =AY7+1 -> 3 | AZ8: =EDATE(Premissas!$C$7,AY8-1) -> 46357 | BA8: =Premissas!$D$19*(1+Premissas!$D$20)^(AY8-1) -> 9.1592 | BB8: =IFERROR(BA8/Premissas!$D$25,0) -> 45.796 | BC8: =(N(BE7)+N(BG7))*Premissas!$D$21+CE8 -> 0.6464 | BD8: =BE8+BF8+BG8+BH8 -> 24.7528 | BE8: =N(BE7)*(1-Premissas!$D$21)+BY8 -> 14.70672 | BF8: =SUM(INDEX($CC$6:$CC$29,MAX(1,AY8-11)):INDEX($CC$6:$CC$29,AY8)) -> 3.85788 | BG8: =N(BG7)*(1-Premissas!$D$21)+CA8 -> 4.90224 | BH8: =SUM(INDEX($CD$6:$CD$29,MAX(1,AY8-11)):INDEX($CD$6:$CD$29,AY8)) -> 1.28596 | BI8: =BE8*Premissas!$C$13+BF8*Premissas!$F$13/12+BG8*Premissas!$C$14+BH8*Premissas!$F$14/12 -> 1562.7203 | BJ8: =BI8*12 -> 18752.643 | BK8: =IFERROR(BI8/BD8,0) -> 63.13307 | BL8: =BI8*Premissas!$C$30 -> 93.763215 | BM8: =BI8*Premissas!$C$28+CF8*Premissas!$C$29 -> 65.201201 | BN8: =BD8*Premissas!$C$31 -> 12.3764 | BO8: =BI8-BL8-BM8-BN8 -> 1391.3794 | BP8: =IFERROR(BO8/BI8,0) -> 0.89035733 | BQ8: =SUMPRODUCT(Premissas!$C$42:$C$61,--(Premissas!$D$42:$D$61<=AY8)) -> 2195 | BR8: =Premissas!$C$34*(1+Premissas!$C$35)^(AY8-1) -> 1591.35 | BS8: =BA8*Premissas!$C$36*Premissas!$C$37 -> 54.9552 | BT8: =BL8+BM8+BN8+BQ8+BR8+BS8 -> 4012.646 | BU8: =BI8-BT8 -> -2449.9258 | BV8: =N(BV7)+BU8 -> -8621.2998 | BW8: =IFERROR((BR8+BS8)/BA8,0) -> 179.74334 | BX8: =IFERROR(BQ8/(BO8/BD8),0) -> 39.049302 | BY8: =BA8*(1-Premissas!$D$23)*(1-Premissas!$D$24) -> 5.49552 | BZ8: =BA8*(1-Premissas!$D$23)*Premissas!$D$24 -> 1.37388 | CA8: =BA8*Premissas!$D$23*(1-Premissas!$D$24) -> 1.83184 | CB8: =BA8*Premissas!$D$23*Premissas!$D$24 -> 0.45796 | CC8: =BZ8+IF(AY8>12,INDEX($BZ$6:$BZ$29,AY8-12)*Premissas!$D$22,0) -> 1.37388 | CD8: =CB8+IF(AY8>12,INDEX($CB$6:$CB$29,AY8-12)*Premissas!$D$22,0) -> 0.45796 | CE8: =IF(AY8>12,(INDEX($BZ$6:$BZ$29,AY8-12)+INDEX($CB$6:$CB$29,AY8-12))*(1-Premissas!$D$22),0) -> 0 | CF8: =BE8+BG8+CC8+CD8 -> 21.4408 | CG8: =IF(BU8>0,AY8,"") | CH8: =BE8*Premissas!$C$13+BG8*Premissas!$C$14 -> 1282.426 | CI8: =CC8*Premissas!$F$13+CD8*Premissas!$F$14 -> 1197.831 | CJ8: =CH8+CI8 -> 2480.257 | CK8: =CJ8*Premissas!$C$30 -> 148.81542 | CL8: =CJ8*Premissas!$C$28+CF8*Premissas!$C$29 -> 97.314987 | CM8: =BN8 -> 12.3764 | CN8: =BQ8 -> 2195 | CO8: =BR8+BS8 -> 1646.3052 | CP8: =CK8+CL8+CM8+CN8+CO8 -> 4099.812 | CQ8: =CJ8-CP8 -> -1619.555 | CR8: =IF(AY8=1,Premissas!$C$8,N(CR7))+CQ8 -> -6073.2036 | CS8: =BF8*Premissas!$F$13/12+BH8*Premissas!$F$14/12 -> 280.29427 | CT8: =N(CT7)+CI8-CS8 -> 2815.576 | CV8: =CV7+1 -> 3 | CW8: =EDATE(Premissas!$C$7,CV8-1) -> 46357 | CX8: =Premissas!$E$19*(1+Premissas!$E$20)^(CV8-1) -> 18.816 | CY8: =IFERROR(CX8/Premissas!$E$25,0) -> 62.72 | CZ8: =(N(DB7)+N(DD7))*Premissas!$E$21+EB8 -> 0.65835 | DA8: =DB8+DC8+DD8+DE8 -> 49.64265 | DB8: =N(DB7)*(1-Premissas!$E$21)+DV8 -> 22.397603 | DC8: =SUM(INDEX($DZ$6:$DZ$29,MAX(1,CV8-11)):INDEX($DZ$6:$DZ$29,CV8)) -> 9.87012 | DD8: =N(DD7)*(1-Premissas!$E$21)+DX8 -> 12.060247 | DE8: =SUM(INDEX($EA$6:$EA$29,MAX(1,CV8-11)):INDEX($EA$6:$EA$29,CV8)) -> 5.31468 | DF8: =DB8*Premissas!$C$13+DC8*Premissas!$F$13/12+DD8*Premissas!$C$14+DE8*Premissas!$F$14/12 -> 3216.4032 | DG8: =DF8*12 -> 38596.838 | DH8: =IFERROR(DF8/DA8,0) -> 64.791126 | DI8: =DF8*Premissas!$C$30 -> 192.98419 | DJ8: =DF8*Premissas!$C$28+EC8*Premissas!$C$29 -> 132.22441 | DK8: =DA8*Premissas!$C$31 -> 24.821325 | DL8: =DF8-DI8-DJ8-DK8 -> 2866.3733 | DM8: =IFERROR(DL8/DF8,0) -> 0.89117349 | DN8: =SUMPRODUCT(Premissas!$C$42:$C$61,--(Premissas!$D$42:$D$61<=CV8)) -> 2195 | DO8: =Premissas!$C$34*(1+Premissas!$C$35)^(CV8-1) -> 1591.35 | DP8: =CX8*Premissas!$C$36*Premissas!$C$37 -> 112.896 | DQ8: =DI8+DJ8+DK8+DN8+DO8+DP8 -> 4249.2759 | DR8: =DF8-DQ8 -> -1032.8727 | DS8: =N(DS7)+DR8 -> -5974.8843 | DT8: =IFERROR((DO8+DP8)/CX8,0) -> 90.574298 | DU8: =IFERROR(DN8/(DL8/DA8),0) -> 38.015152 | DV8: =CX8*(1-Premissas!$E$23)*(1-Premissas!$E$24) -> 8.56128 | DW8: =CX8*(1-Premissas!$E$23)*Premissas!$E$24 -> 3.66912 | DX8: =CX8*Premissas!$E$23*(1-Premissas!$E$24) -> 4.60992 | DY8: =CX8*Premissas!$E$23*Premissas!$E$24 -> 1.97568 | DZ8: =DW8+IF(CV8>12,INDEX($DW$6:$DW$29,CV8-12)*Premissas!$E$22,0) -> 3.66912 | EA8: =DY8+IF(CV8>12,INDEX($DY$6:$DY$29,CV8-12)*Premissas!$E$22,0) -> 1.97568 | EB8: =IF(CV8>12,(INDEX($DW$6:$DW$29,CV8-12)+INDEX($DY$6:$DY$29,CV8-12))*(1-Premissas!$E$22),0) -> 0 | EC8: =DB8+DD8+DZ8+EA8 -> 40.10265 | ED8: =IF(DR8>0,CV8,"") | EE8: =DB8*Premissas!$C$13+DD8*Premissas!$C$14 -> 2356.9169 | EF8: =DZ8*Premissas!$F$13+EA8*Premissas!$F$14 -> 3834.0667 | EG8: =EE8+EF8 -> 6190.9836 | EH8: =EG8*Premissas!$C$30 -> 371.45902 | EI8: =EG8*Premissas!$C$28+EC8*Premissas!$C$29 -> 236.33473 | EJ8: =DK8 -> 24.821325 | EK8: =DN8 -> 2195 | EL8: =DO8+DP8 -> 1704.246 | EM8: =EH8+EI8+EJ8+EK8+EL8 -> 4531.8611 | EN8: =EG8-EM8 -> 1659.1226 | EO8: =IF(CV8=1,Premissas!$C$8,N(EO7))+EN8 -> 1862.1082 | EP8: =DC8*Premissas!$F$13/12+DE8*Premissas!$F$14/12 -> 859.48625 | EQ8: =N(EQ7)+EF8-EP8 -> 8659.6602
B9: =B8+1 -> 4 | C9: =EDATE(Premissas!$C$7,B9-1) -> 46388 | D9: =Premissas!$C$19*(1+Premissas!$C$20)^(B9-1) -> 4.370908 | E9: =IFERROR(D9/Premissas!$C$25,0) -> 43.70908 | F9: =(N(H8)+N(J8))*Premissas!$C$21+AH9 -> 0.8222112 | G9: =H9+I9+J9+K9 -> 15.062697 | H9: =N(H8)*(1-Premissas!$C$21)+AB9 -> 11.380859 | I9: =SUM(INDEX($AF$6:$AF$29,MAX(1,B9-11)):INDEX($AF$6:$AF$29,B9)) -> 1.4224332 | J9: =N(J8)*(1-Premissas!$C$21)+AD9 -> 2.0083869 | K9: =SUM(INDEX($AG$6:$AG$29,MAX(1,B9-11)):INDEX($AG$6:$AG$29,B9)) -> 0.25101762 | L9: =H9*Premissas!$C$13+I9*Premissas!$F$13/12+J9*Premissas!$C$14+K9*Premissas!$F$14/12 -> 923.14556 | M9: =L9*12 -> 11077.747 | N9: =IFERROR(L9/G9,0) -> 61.286871 | O9: =L9*Premissas!$C$30 -> 55.388734 | P9: =L9*Premissas!$C$28+AI9*Premissas!$C$29 -> 39.085 | Q9: =G9*Premissas!$C$31 -> 7.5313484 | R9: =L9-O9-P9-Q9 -> 821.14048 | S9: =IFERROR(R9/L9,0) -> 0.88950271 | T9: =SUMPRODUCT(Premissas!$C$42:$C$61,--(Premissas!$D$42:$D$61<=B9)) -> 2195 | U9: =Premissas!$C$34*(1+Premissas!$C$35)^(B9-1) -> 1639.0905 | V9: =D9*Premissas!$C$36*Premissas!$C$37 -> 26.225448 | W9: =O9+P9+Q9+T9+U9+V9 -> 3962.321 | X9: =L9-W9 -> -3039.1755 | Y9: =N(Y8)+X9 -> -13061.031 | Z9: =IFERROR((U9+V9)/D9,0) -> 381 | AA9: =IFERROR(T9/(R9/G9),0) -> 40.264267 | AB9: =D9*(1-Premissas!$C$23)*(1-Premissas!$C$24) -> 3.3437446 | AC9: =D9*(1-Premissas!$C$23)*Premissas!$C$24 -> 0.37152718 | AD9: =D9*Premissas!$C$23*(1-Premissas!$C$24) -> 0.59007258 | AE9: =D9*Premissas!$C$23*Premissas!$C$24 -> 0.06556362 | AF9: =AC9+IF(B9>12,INDEX($AC$6:$AC$29,B9-12)*Premissas!$C$22,0) -> 0.37152718 | AG9: =AE9+IF(B9>12,INDEX($AE$6:$AE$29,B9-12)*Premissas!$C$22,0) -> 0.06556362 | AH9: =IF(B9>12,(INDEX($AC$6:$AC$29,B9-12)+INDEX($AE$6:$AE$29,B9-12))*(1-Premissas!$C$22),0) -> 0 | AI9: =H9+J9+AF9+AG9 -> 13.826337 | AJ9: =IF(X9>0,B9,"") | AK9: =H9*Premissas!$C$13+J9*Premissas!$C$14 -> 835.48895 | AL9: =AF9*Premissas!$F$13+AG9*Premissas!$F$14 -> 274.74173 | AM9: =AK9+AL9 -> 1110.2307 | AN9: =AM9*Premissas!$C$30 -> 66.613841 | AO9: =AM9*Premissas!$C$28+AI9*Premissas!$C$29 -> 45.632979 | AP9: =Q9 -> 7.5313484 | AQ9: =T9 -> 2195 | AR9: =U9+V9 -> 1665.3159 | AS9: =AN9+AO9+AP9+AQ9+AR9 -> 3980.0941 | AT9: =AM9-AS9 -> -2869.8634 | AU9: =IF(B9=1,Premissas!$C$8,N(AU8))+AT9 -> -12304.473 | AV9: =I9*Premissas!$F$13/12+K9*Premissas!$F$14/12 -> 87.656608 | AW9: =N(AW8)+AL9-AV9 -> 835.97575 | AY9: =AY8+1 -> 4 | AZ9: =EDATE(Premissas!$C$7,AY9-1) -> 46388 | BA9: =Premissas!$D$19*(1+Premissas!$D$20)^(AY9-1) -> 9.800344 | BB9: =IFERROR(BA9/Premissas!$D$25,0) -> 49.00172 | BC9: =(N(BE8)+N(BG8))*Premissas!$D$21+CE9 -> 0.980448 | BD9: =BE9+BF9+BG9+BH9 -> 33.572696 | BE9: =N(BE8)*(1-Premissas!$D$21)+BY9 -> 19.85159 | BF9: =SUM(INDEX($CC$6:$CC$29,MAX(1,AY9-11)):INDEX($CC$6:$CC$29,AY9)) -> 5.3279316 | BG9: =N(BG8)*(1-Premissas!$D$21)+CA9 -> 6.6171968 | BH9: =SUM(INDEX($CD$6:$CD$29,MAX(1,AY9-11)):INDEX($CD$6:$CD$29,AY9)) -> 1.7759772 | BI9: =BE9*Premissas!$C$13+BF9*Premissas!$F$13/12+BG9*Premissas!$C$14+BH9*Premissas!$F$14/12 -> 2118.1596 | BJ9: =BI9*12 -> 25417.915 | BK9: =IFERROR(BI9/BD9,0) -> 63.091732 | BL9: =BI9*Premissas!$C$30 -> 127.08957 | BM9: =BI9*Premissas!$C$28+CF9*Premissas!$C$29 -> 88.065724 | BN9: =BD9*Premissas!$C$31 -> 16.786348 | BO9: =BI9-BL9-BM9-BN9 -> 1886.2179 | BP9: =IFERROR(BO9/BI9,0) -> 0.8904985 | BQ9: =SUMPRODUCT(Premissas!$C$42:$C$61,--(Premissas!$D$42:$D$61<=AY9)) -> 2195 | BR9: =Premissas!$C$34*(1+Premissas!$C$35)^(AY9-1) -> 1639.0905 | BS9: =BA9*Premissas!$C$36*Premissas!$C$37 -> 58.802064 | BT9: =BL9+BM9+BN9+BQ9+BR9+BS9 -> 4124.8342 | BU9: =BI9-BT9 -> -2006.6747 | BV9: =N(BV8)+BU9 -> -10627.974 | BW9: =IFERROR((BR9+BS9)/BA9,0) -> 173.24826 | BX9: =IFERROR(BQ9/(BO9/BD9),0) -> 39.068693 | BY9: =BA9*(1-Premissas!$D$23)*(1-Premissas!$D$24) -> 5.8802064 | BZ9: =BA9*(1-Premissas!$D$23)*Premissas!$D$24 -> 1.4700516 | CA9: =BA9*Premissas!$D$23*(1-Premissas!$D$24) -> 1.9600688 | CB9: =BA9*Premissas!$D$23*Premissas!$D$24 -> 0.4900172 | CC9: =BZ9+IF(AY9>12,INDEX($BZ$6:$BZ$29,AY9-12)*Premissas!$D$22,0) -> 1.4700516 | CD9: =CB9+IF(AY9>12,INDEX($CB$6:$CB$29,AY9-12)*Premissas!$D$22,0) -> 0.4900172 | CE9: =IF(AY9>12,(INDEX($BZ$6:$BZ$29,AY9-12)+INDEX($CB$6:$CB$29,AY9-12))*(1-Premissas!$D$22),0) -> 0 | CF9: =BE9+BG9+CC9+CD9 -> 28.428856 | CG9: =IF(BU9>0,AY9,"") | CH9: =BE9*Premissas!$C$13+BG9*Premissas!$C$14 -> 1731.0587 | CI9: =CC9*Premissas!$F$13+CD9*Premissas!$F$14 -> 1281.6792 | CJ9: =CH9+CI9 -> 3012.7379 | CK9: =CJ9*Premissas!$C$30 -> 180.76427 | CL9: =CJ9*Premissas!$C$28+CF9*Premissas!$C$29 -> 119.37596 | CM9: =BN9 -> 16.786348 | CN9: =BQ9 -> 2195 | CO9: =BR9+BS9 -> 1697.8926 | CP9: =CK9+CL9+CM9+CN9+CO9 -> 4209.8191 | CQ9: =CJ9-CP9 -> -1197.0813 | CR9: =IF(AY9=1,Premissas!$C$8,N(CR8))+CQ9 -> -7270.2848 | CS9: =BF9*Premissas!$F$13/12+BH9*Premissas!$F$14/12 -> 387.10087 | CT9: =N(CT8)+CI9-CS9 -> 3710.1543 | CV9: =CV8+1 -> 4 | CW9: =EDATE(Premissas!$C$7,CV9-1) -> 46388 | CX9: =Premissas!$E$19*(1+Premissas!$E$20)^(CV9-1) -> 21.07392 | CY9: =IFERROR(CX9/Premissas!$E$25,0) -> 70.2464 | CZ9: =(N(DB8)+N(DD8))*Premissas!$E$21+EB9 -> 1.0337355 | DA9: =DB9+DC9+DD9+DE9 -> 69.682834 | DB9: =N(DB8)*(1-Premissas!$E$21)+DV9 -> 31.314308 | DC9: =SUM(INDEX($DZ$6:$DZ$29,MAX(1,CV9-11)):INDEX($DZ$6:$DZ$29,CV9)) -> 13.979534 | DD9: =N(DD8)*(1-Premissas!$E$21)+DX9 -> 16.86155 | DE9: =SUM(INDEX($EA$6:$EA$29,MAX(1,CV9-11)):INDEX($EA$6:$EA$29,CV9)) -> 7.5274416 | DF9: =DB9*Premissas!$C$13+DC9*Premissas!$F$13/12+DD9*Premissas!$C$14+DE9*Premissas!$F$14/12 -> 4512.5612 | DG9: =DF9*12 -> 54150.734 | DH9: =IFERROR(DF9/DA9,0) -> 64.758577 | DI9: =DF9*Premissas!$C$30 -> 270.75367 | DJ9: =DF9*Premissas!$C$28+EC9*Premissas!$C$29 -> 184.64368 | DK9: =DA9*Premissas!$C$31 -> 34.841417 | DL9: =DF9-DI9-DJ9-DK9 -> 4022.3224 | DM9: =IFERROR(DL9/DF9,0) -> 0.8913613 | DN9: =SUMPRODUCT(Premissas!$C$42:$C$61,--(Premissas!$D$42:$D$61<=CV9)) -> 2195 | DO9: =Premissas!$C$34*(1+Premissas!$C$35)^(CV9-1) -> 1639.0905 | DP9: =CX9*Premissas!$C$36*Premissas!$C$37 -> 126.44352 | DQ9: =DI9+DJ9+DK9+DN9+DO9+DP9 -> 4450.7728 | DR9: =DF9-DQ9 -> 61.788412 | DS9: =N(DS8)+DR9 -> -5913.0959 | DT9: =IFERROR((DO9+DP9)/CX9,0) -> 83.778149 | DU9: =IFERROR(DN9/(DL9/DA9),0) -> 38.026246 | DV9: =CX9*(1-Premissas!$E$23)*(1-Premissas!$E$24) -> 9.5886336 | DW9: =CX9*(1-Premissas!$E$23)*Premissas!$E$24 -> 4.1094144 | DX9: =CX9*Premissas!$E$23*(1-Premissas!$E$24) -> 5.1631104 | DY9: =CX9*Premissas!$E$23*Premissas!$E$24 -> 2.2127616 | DZ9: =DW9+IF(CV9>12,INDEX($DW$6:$DW$29,CV9-12)*Premissas!$E$22,0) -> 4.1094144 | EA9: =DY9+IF(CV9>12,INDEX($DY$6:$DY$29,CV9-12)*Premissas!$E$22,0) -> 2.2127616 | EB9: =IF(CV9>12,(INDEX($DW$6:$DW$29,CV9-12)+INDEX($DY$6:$DY$29,CV9-12))*(1-Premissas!$E$22),0) -> 0 | EC9: =DB9+DD9+DZ9+EA9 -> 54.498035 | ED9: =IF(DR9>0,CV9,"") -> 4 | EE9: =DB9*Premissas!$C$13+DD9*Premissas!$C$14 -> 3295.2287 | EF9: =DZ9*Premissas!$F$13+EA9*Premissas!$F$14 -> 4294.1547 | EG9: =EE9+EF9 -> 7589.3834 | EH9: =EG9*Premissas!$C$30 -> 455.36301 | EI9: =EG9*Premissas!$C$28+EC9*Premissas!$C$29 -> 292.33246 | EJ9: =DK9 -> 34.841417 | EK9: =DN9 -> 2195 | EL9: =DO9+DP9 -> 1765.534 | EM9: =EH9+EI9+EJ9+EK9+EL9 -> 4743.0709 | EN9: =EG9-EM9 -> 2846.3125 | EO9: =IF(CV9=1,Premissas!$C$8,N(EO8))+EN9 -> 4708.4207 | EP9: =DC9*Premissas!$F$13/12+DE9*Premissas!$F$14/12 -> 1217.3325 | EQ9: =N(EQ8)+EF9-EP9 -> 11736.482
B10: =B9+1 -> 5 | C10: =EDATE(Premissas!$C$7,B10-1) -> 46419 | D10: =Premissas!$C$19*(1+Premissas!$C$20)^(B10-1) -> 4.5020352 | E10: =IFERROR(D10/Premissas!$C$25,0) -> 45.020352 | F10: =(N(H9)+N(J9))*Premissas!$C$21+AH10 -> 1.0711397 | G10: =H10+I10+J10+K10 -> 18.493592 | H10: =N(H9)*(1-Premissas!$C$21)+AB10 -> 13.914447 | I10: =SUM(INDEX($AF$6:$AF$29,MAX(1,B10-11)):INDEX($AF$6:$AF$29,B10)) -> 1.8051062 | J10: =N(J9)*(1-Premissas!$C$21)+AD10 -> 2.4554907 | K10: =SUM(INDEX($AG$6:$AG$29,MAX(1,B10-11)):INDEX($AG$6:$AG$29,B10)) -> 0.31854815 | L10: =H10*Premissas!$C$13+I10*Premissas!$F$13/12+J10*Premissas!$C$14+K10*Premissas!$F$14/12 -> 1132.7227 | M10: =L10*12 -> 13592.673 | N10: =IFERROR(L10/G10,0) -> 61.24947 | O10: =L10*Premissas!$C$30 -> 67.963364 | P10: =L10*Premissas!$C$28+AI10*Premissas!$C$29 -> 47.887165 | Q10: =G10*Premissas!$C$31 -> 9.2467962 | R10: =L10-O10-P10-Q10 -> 1007.6254 | S10: =IFERROR(R10/L10,0) -> 0.88956051 | T10: =SUMPRODUCT(Premissas!$C$42:$C$61,--(Premissas!$D$42:$D$61<=B10)) -> 2195 | U10: =Premissas!$C$34*(1+Premissas!$C$35)^(B10-1) -> 1688.2632 | V10: =D10*Premissas!$C$36*Premissas!$C$37 -> 27.012211 | W10: =O10+P10+Q10+T10+U10+V10 -> 4035.3728 | X10: =L10-W10 -> -2902.65 | Y10: =N(Y9)+X10 -> -15963.681 | Z10: =IFERROR((U10+V10)/D10,0) -> 381 | AA10: =IFERROR(T10/(R10/G10),0) -> 40.286236 | AB10: =D10*(1-Premissas!$C$23)*(1-Premissas!$C$24) -> 3.444057 | AC10: =D10*(1-Premissas!$C$23)*Premissas!$C$24 -> 0.382673 | AD10: =D10*Premissas!$C$23*(1-Premissas!$C$24) -> 0.60777476 | AE10: =D10*Premissas!$C$23*Premissas!$C$24 -> 0.067530529 | AF10: =AC10+IF(B10>12,INDEX($AC$6:$AC$29,B10-12)*Premissas!$C$22,0) -> 0.382673 | AG10: =AE10+IF(B10>12,INDEX($AE$6:$AE$29,B10-12)*Premissas!$C$22,0) -> 0.067530529 | AH10: =IF(B10>12,(INDEX($AC$6:$AC$29,B10-12)+INDEX($AE$6:$AE$29,B10-12))*(1-Premissas!$C$22),0) -> 0 | AI10: =H10+J10+AF10+AG10 -> 16.820142 | AJ10: =IF(X10>0,B10,"") | AK10: =H10*Premissas!$C$13+J10*Premissas!$C$14 -> 1021.4841 | AL10: =AF10*Premissas!$F$13+AG10*Premissas!$F$14 -> 282.98398 | AM10: =AK10+AL10 -> 1304.4681 | AN10: =AM10*Premissas!$C$30 -> 78.268087 | AO10: =AM10*Premissas!$C$28+AI10*Premissas!$C$29 -> 53.898253 | AP10: =Q10 -> 9.2467962 | AQ10: =T10 -> 2195 | AR10: =U10+V10 -> 1715.2754 | AS10: =AN10+AO10+AP10+AQ10+AR10 -> 4051.6886 | AT10: =AM10-AS10 -> -2747.2205 | AU10: =IF(B10=1,Premissas!$C$8,N(AU9))+AT10 -> -15051.693 | AV10: =I10*Premissas!$F$13/12+K10*Premissas!$F$14/12 -> 111.23861 | AW10: =N(AW9)+AL10-AV10 -> 1007.7211 | AY10: =AY9+1 -> 5 | AZ10: =EDATE(Premissas!$C$7,AY10-1) -> 46419 | BA10: =Premissas!$D$19*(1+Premissas!$D$20)^(AY10-1) -> 10.486368 | BB10: =IFERROR(BA10/Premissas!$D$25,0) -> 52.43184 | BC10: =(N(BE9)+N(BG9))*Premissas!$D$21+CE10 -> 1.3234394 | BD10: =BE10+BF10+BG10+BH10 -> 42.735625 | BE10: =N(BE9)*(1-Premissas!$D$21)+BY10 -> 25.150832 | BF10: =SUM(INDEX($CC$6:$CC$29,MAX(1,AY10-11)):INDEX($CC$6:$CC$29,AY10)) -> 6.9008868 | BG10: =N(BG9)*(1-Premissas!$D$21)+CA10 -> 8.3836106 | BH10: =SUM(INDEX($CD$6:$CD$29,MAX(1,AY10-11)):INDEX($CD$6:$CD$29,AY10)) -> 2.3002956 | BI10: =BE10*Premissas!$C$13+BF10*Premissas!$F$13/12+BG10*Premissas!$C$14+BH10*Premissas!$F$14/12 -> 2694.5365 | BJ10: =BI10*12 -> 32334.437 | BK10: =IFERROR(BI10/BD10,0) -> 63.051294 | BL10: =BI10*Premissas!$C$30 -> 161.67219 | BM10: =BI10*Premissas!$C$28+CF10*Premissas!$C$29 -> 111.76832 | BN10: =BD10*Premissas!$C$31 -> 21.367812 | BO10: =BI10-BL10-BM10-BN10 -> 2399.7281 | BP10: =IFERROR(BO10/BI10,0) -> 0.89059034 | BQ10: =SUMPRODUCT(Premissas!$C$42:$C$61,--(Premissas!$D$42:$D$61<=AY10)) -> 2195 | BR10: =Premissas!$C$34*(1+Premissas!$C$35)^(AY10-1) -> 1688.2632 | BS10: =BA10*Premissas!$C$36*Premissas!$C$37 -> 62.918208 | BT10: =BL10+BM10+BN10+BQ10+BR10+BS10 -> 4240.9897 | BU10: =BI10-BT10 -> -1546.4533 | BV10: =N(BV9)+BU10 -> -12174.428 | BW10: =IFERROR((BR10+BS10)/BA10,0) -> 166.99599 | BX10: =IFERROR(BQ10/(BO10/BD10),0) -> 39.089718 | BY10: =BA10*(1-Premissas!$D$23)*(1-Premissas!$D$24) -> 6.2918208 | BZ10: =BA10*(1-Premissas!$D$23)*Premissas!$D$24 -> 1.5729552 | CA10: =BA10*Premissas!$D$23*(1-Premissas!$D$24) -> 2.0972736 | CB10: =BA10*Premissas!$D$23*Premissas!$D$24 -> 0.5243184 | CC10: =BZ10+IF(AY10>12,INDEX($BZ$6:$BZ$29,AY10-12)*Premissas!$D$22,0) -> 1.5729552 | CD10: =CB10+IF(AY10>12,INDEX($CB$6:$CB$29,AY10-12)*Premissas!$D$22,0) -> 0.5243184 | CE10: =IF(AY10>12,(INDEX($BZ$6:$BZ$29,AY10-12)+INDEX($CB$6:$CB$29,AY10-12))*(1-Premissas!$D$22),0) -> 0 | CF10: =BE10+BG10+CC10+CD10 -> 35.631716 | CG10: =IF(BU10>0,AY10,"") | CH10: =BE10*Premissas!$C$13+BG10*Premissas!$C$14 -> 2193.1525 | CI10: =CC10*Premissas!$F$13+CD10*Premissas!$F$14 -> 1371.3967 | CJ10: =CH10+CI10 -> 3564.5493 | CK10: =CJ10*Premissas!$C$30 -> 213.87296 | CL10: =CJ10*Premissas!$C$28+CF10*Premissas!$C$29 -> 142.21876 | CM10: =BN10 -> 21.367812 | CN10: =BQ10 -> 2195 | CO10: =BR10+BS10 -> 1751.1814 | CP10: =CK10+CL10+CM10+CN10+CO10 -> 4323.641 | CQ10: =CJ10-CP10 -> -759.0917 | CR10: =IF(AY10=1,Premissas!$C$8,N(CR9))+CQ10 -> -8029.3765 | CS10: =BF10*Premissas!$F$13/12+BH10*Premissas!$F$14/12 -> 501.38393 | CT10: =N(CT9)+CI10-CS10 -> 4580.1671 | CV10: =CV9+1 -> 5 | CW10: =EDATE(Premissas!$C$7,CV10-1) -> 46419 | CX10: =Premissas!$E$19*(1+Premissas!$E$20)^(CV10-1) -> 23.60279 | CY10: =IFERROR(CX10/Premissas!$E$25,0) -> 78.675968 | CZ10: =(N(DB9)+N(DD9))*Premissas!$E$21+EB10 -> 1.4452758 | DA10: =DB10+DC10+DD10+DE10 -> 91.840349 | DB10: =N(DB9)*(1-Premissas!$E$21)+DV10 -> 41.114148 | DC10: =SUM(INDEX($DZ$6:$DZ$29,MAX(1,CV10-11)):INDEX($DZ$6:$DZ$29,CV10)) -> 18.582079 | DD10: =N(DD9)*(1-Premissas!$E$21)+DX10 -> 22.138388 | DE10: =SUM(INDEX($EA$6:$EA$29,MAX(1,CV10-11)):INDEX($EA$6:$EA$29,CV10)) -> 10.005735 | DF10: =DB10*Premissas!$C$13+DC10*Premissas!$F$13/12+DD10*Premissas!$C$14+DE10*Premissas!$F$14/12 -> 5944.5937 | DG10: =DF10*12 -> 71335.125 | DH10: =IFERROR(DF10/DA10,0) -> 64.727473 | DI10: =DF10*Premissas!$C$30 -> 356.67562 | DJ10: =DF10*Premissas!$C$28+EC10*Premissas!$C$29 -> 242.52413 | DK10: =DA10*Premissas!$C$31 -> 45.920175 | DL10: =DF10-DI10-DJ10-DK10 -> 5299.4738 | DM10: =IFERROR(DL10/DF10,0) -> 0.89147788 | DN10: =SUMPRODUCT(Premissas!$C$42:$C$61,--(Premissas!$D$42:$D$61<=CV10)) -> 2195 | DO10: =Premissas!$C$34*(1+Premissas!$C$35)^(CV10-1) -> 1688.2632 | DP10: =CX10*Premissas!$C$36*Premissas!$C$37 -> 141.61674 | DQ10: =DI10+DJ10+DK10+DN10+DO10+DP10 -> 4669.9999 | DR10: =DF10-DQ10 -> 1274.5938 | DS10: =N(DS9)+DR10 -> -4638.5021 | DT10: =IFERROR((DO10+DP10)/CX10,0) -> 77.52812 | DU10: =IFERROR(DN10/(DL10/DA10),0) -> 38.039544 | DV10: =CX10*(1-Premissas!$E$23)*(1-Premissas!$E$24) -> 10.73927 | DW10: =CX10*(1-Premissas!$E$23)*Premissas!$E$24 -> 4.6025441 | DX10: =CX10*Premissas!$E$23*(1-Premissas!$E$24) -> 5.7826836 | DY10: =CX10*Premissas!$E$23*Premissas!$E$24 -> 2.478293 | DZ10: =DW10+IF(CV10>12,INDEX($DW$6:$DW$29,CV10-12)*Premissas!$E$22,0) -> 4.6025441 | EA10: =DY10+IF(CV10>12,INDEX($DY$6:$DY$29,CV10-12)*Premissas!$E$22,0) -> 2.478293 | EB10: =IF(CV10>12,(INDEX($DW$6:$DW$29,CV10-12)+INDEX($DY$6:$DY$29,CV10-12))*(1-Premissas!$E$22),0) -> 0 | EC10: =DB10+DD10+DZ10+EA10 -> 70.333373 | ED10: =IF(DR10>0,CV10,"") -> 5 | EE10: =DB10*Premissas!$C$13+DD10*Premissas!$C$14 -> 4326.4735 | EF10: =DZ10*Premissas!$F$13+EA10*Premissas!$F$14 -> 4809.4533 | EG10: =EE10+EF10 -> 9135.9267 | EH10: =EG10*Premissas!$C$30 -> 548.1556 | EI10: =EG10*Premissas!$C$28+EC10*Premissas!$C$29 -> 354.22079 | EJ10: =DK10 -> 45.920175 | EK10: =DN10 -> 2195 | EL10: =DO10+DP10 -> 1829.88 | EM10: =EH10+EI10+EJ10+EK10+EL10 -> 4973.1765 | EN10: =EG10-EM10 -> 4162.7502 | EO10: =IF(CV10=1,Premissas!$C$8,N(EO9))+EN10 -> 8871.1709 | EP10: =DC10*Premissas!$F$13/12+DE10*Premissas!$F$14/12 -> 1618.1203 | EQ10: =N(EQ9)+EF10-EP10 -> 14927.815
B11: =B10+1 -> 6 | C11: =EDATE(Premissas!$C$7,B11-1) -> 46447 | D11: =Premissas!$C$19*(1+Premissas!$C$20)^(B11-1) -> 4.6370963 | E11: =IFERROR(D11/Premissas!$C$25,0) -> 46.370963 | F11: =(N(H10)+N(J10))*Premissas!$C$21+AH11 -> 1.309595 | G11: =H11+I11+J11+K11 -> 21.821094 | H11: =N(H10)*(1-Premissas!$C$21)+AB11 -> 16.34867 | I11: =SUM(INDEX($AF$6:$AF$29,MAX(1,B11-11)):INDEX($AF$6:$AF$29,B11)) -> 2.1992594 | J11: =N(J10)*(1-Premissas!$C$21)+AD11 -> 2.8850594 | K11: =SUM(INDEX($AG$6:$AG$29,MAX(1,B11-11)):INDEX($AG$6:$AG$29,B11)) -> 0.38810459 | L11: =H11*Premissas!$C$13+I11*Premissas!$F$13/12+J11*Premissas!$C$14+K11*Premissas!$F$14/12 -> 1335.7128 | M11: =L11*12 -> 16028.554 | N11: =IFERROR(L11/G11,0) -> 61.212001 | O11: =L11*Premissas!$C$30 -> 80.142768 | P11: =L11*Premissas!$C$28+AI11*Premissas!$C$29 -> 56.401693 | Q11: =G11*Premissas!$C$31 -> 10.910547 | R11: =L11-O11-P11-Q11 -> 1188.2578 | S11: =IFERROR(R11/L11,0) -> 0.88960575 | T11: =SUMPRODUCT(Premissas!$C$42:$C$61,--(Premissas!$D$42:$D$61<=B11)) -> 2195 | U11: =Premissas!$C$34*(1+Premissas!$C$35)^(B11-1) -> 1738.9111 | V11: =D11*Premissas!$C$36*Premissas!$C$37 -> 27.822578 | W11: =O11+P11+Q11+T11+U11+V11 -> 4109.1887 | X11: =L11-W11 -> -2773.4759 | Y11: =N(Y10)+X11 -> -18737.157 | Z11: =IFERROR((U11+V11)/D11,0) -> 381 | AA11: =IFERROR(T11/(R11/G11),0) -> 40.308846 | AB11: =D11*(1-Premissas!$C$23)*(1-Premissas!$C$24) -> 3.5473787 | AC11: =D11*(1-Premissas!$C$23)*Premissas!$C$24 -> 0.39415319 | AD11: =D11*Premissas!$C$23*(1-Premissas!$C$24) -> 0.626008 | AE11: =D11*Premissas!$C$23*Premissas!$C$24 -> 0.069556444 | AF11: =AC11+IF(B11>12,INDEX($AC$6:$AC$29,B11-12)*Premissas!$C$22,0) -> 0.39415319 | AG11: =AE11+IF(B11>12,INDEX($AE$6:$AE$29,B11-12)*Premissas!$C$22,0) -> 0.069556444 | AH11: =IF(B11>12,(INDEX($AC$6:$AC$29,B11-12)+INDEX($AE$6:$AE$29,B11-12))*(1-Premissas!$C$22),0) -> 0 | AI11: =H11+J11+AF11+AG11 -> 19.697439 | AJ11: =IF(X11>0,B11,"") | AK11: =H11*Premissas!$C$13+J11*Premissas!$C$14 -> 1200.1847 | AL11: =AF11*Premissas!$F$13+AG11*Premissas!$F$14 -> 291.4735 | AM11: =AK11+AL11 -> 1491.6582 | AN11: =AM11*Premissas!$C$30 -> 89.499494 | AO11: =AM11*Premissas!$C$28+AI11*Premissas!$C$29 -> 61.859783 | AP11: =Q11 -> 10.910547 | AQ11: =T11 -> 2195 | AR11: =U11+V11 -> 1766.7337 | AS11: =AN11+AO11+AP11+AQ11+AR11 -> 4124.0035 | AT11: =AM11-AS11 -> -2632.3453 | AU11: =IF(B11=1,Premissas!$C$8,N(AU10))+AT11 -> -17684.038 | AV11: =I11*Premissas!$F$13/12+K11*Premissas!$F$14/12 -> 135.52806 | AW11: =N(AW10)+AL11-AV11 -> 1163.6666 | AY11: =AY10+1 -> 6 | AZ11: =EDATE(Premissas!$C$7,AY11-1) -> 46447 | BA11: =Premissas!$D$19*(1+Premissas!$D$20)^(AY11-1) -> 11.220414 | BB11: =IFERROR(BA11/Premissas!$D$25,0) -> 56.102069 | BC11: =(N(BE10)+N(BG10))*Premissas!$D$21+CE11 -> 1.6767221 | BD11: =BE11+BF11+BG11+BH11 -> 52.279316 | BE11: =N(BE10)*(1-Premissas!$D$21)+BY11 -> 30.625538 | BF11: =SUM(INDEX($CC$6:$CC$29,MAX(1,AY11-11)):INDEX($CC$6:$CC$29,AY11)) -> 8.5839489 | BG11: =N(BG10)*(1-Premissas!$D$21)+CA11 -> 10.208513 | BH11: =SUM(INDEX($CD$6:$CD$29,MAX(1,AY11-11)):INDEX($CD$6:$CD$29,AY11)) -> 2.8613163 | BI11: =BE11*Premissas!$C$13+BF11*Premissas!$F$13/12+BG11*Premissas!$C$14+BH11*Premissas!$F$14/12 -> 3294.2138 | BJ11: =BI11*12 -> 39530.565 | BK11: =IFERROR(BI11/BD11,0) -> 63.011799 | BL11: =BI11*Premissas!$C$30 -> 197.65283 | BM11: =BI11*Premissas!$C$28+CF11*Premissas!$C$29 -> 136.40577 | BN11: =BD11*Premissas!$C$31 -> 26.139658 | BO11: =BI11-BL11-BM11-BN11 -> 2934.0155 | BP11: =IFERROR(BO11/BI11,0) -> 0.89065729 | BQ11: =SUMPRODUCT(Premissas!$C$42:$C$61,--(Premissas!$D$42:$D$61<=AY11)) -> 2195 | BR11: =Premissas!$C$34*(1+Premissas!$C$35)^(AY11-1) -> 1738.9111 | BS11: =BA11*Premissas!$C$36*Premissas!$C$37 -> 67.322483 | BT11: =BL11+BM11+BN11+BQ11+BR11+BS11 -> 4361.4318 | BU11: =BI11-BT11 -> -1067.2181 | BV11: =N(BV10)+BU11 -> -13241.646 | BW11: =IFERROR((BR11+BS11)/BA11,0) -> 160.97745 | BX11: =IFERROR(BQ11/(BO11/BD11),0) -> 39.111279 | BY11: =BA11*(1-Premissas!$D$23)*(1-Premissas!$D$24) -> 6.7322483 | BZ11: =BA11*(1-Premissas!$D$23)*Premissas!$D$24 -> 1.6830621 | CA11: =BA11*Premissas!$D$23*(1-Premissas!$D$24) -> 2.2440828 | CB11: =BA11*Premissas!$D$23*Premissas!$D$24 -> 0.56102069 | CC11: =BZ11+IF(AY11>12,INDEX($BZ$6:$BZ$29,AY11-12)*Premissas!$D$22,0) -> 1.6830621 | CD11: =CB11+IF(AY11>12,INDEX($CB$6:$CB$29,AY11-12)*Premissas!$D$22,0) -> 0.56102069 | CE11: =IF(AY11>12,(INDEX($BZ$6:$BZ$29,AY11-12)+INDEX($CB$6:$CB$29,AY11-12))*(1-Premissas!$D$22),0) -> 0 | CF11: =BE11+BG11+CC11+CD11 -> 43.078134 | CG11: =IF(BU11>0,AY11,"") | CH11: =BE11*Premissas!$C$13+BG11*Premissas!$C$14 -> 2670.547 | CI11: =CC11*Premissas!$F$13+CD11*Premissas!$F$14 -> 1467.3945 | CJ11: =CH11+CI11 -> 4137.9415 | CK11: =CJ11*Premissas!$C$30 -> 248.27649 | CL11: =CJ11*Premissas!$C$28+CF11*Premissas!$C$29 -> 165.93624 | CM11: =BN11 -> 26.139658 | CN11: =BQ11 -> 2195 | CO11: =BR11+BS11 -> 1806.2336 | CP11: =CK11+CL11+CM11+CN11+CO11 -> 4441.586 | CQ11: =CJ11-CP11 -> -303.64452 | CR11: =IF(AY11=1,Premissas!$C$8,N(CR10))+CQ11 -> -8333.0211 | CS11: =BF11*Premissas!$F$13/12+BH11*Premissas!$F$14/12 -> 623.66681 | CT11: =N(CT10)+CI11-CS11 -> 5423.8948 | CV11: =CV10+1 -> 6 | CW11: =EDATE(Premissas!$C$7,CV11-1) -> 46447 | CX11: =Premissas!$E$19*(1+Premissas!$E$20)^(CV11-1) -> 26.435125 | CY11: =IFERROR(CX11/Premissas!$E$25,0) -> 88.117084 | CZ11: =(N(DB10)+N(DD10))*Premissas!$E$21+EB11 -> 1.8975761 | DA11: =DB11+DC11+DD11+DE11 -> 116.3779 | DB11: =N(DB10)*(1-Premissas!$E$21)+DV11 -> 51.908706 | DC11: =SUM(INDEX($DZ$6:$DZ$29,MAX(1,CV11-11)):INDEX($DZ$6:$DZ$29,CV11)) -> 23.736928 | DD11: =N(DD10)*(1-Premissas!$E$21)+DX11 -> 27.950842 | DE11: =SUM(INDEX($EA$6:$EA$29,MAX(1,CV11-11)):INDEX($EA$6:$EA$29,CV11)) -> 12.781423 | DF11: =DB11*Premissas!$C$13+DC11*Premissas!$F$13/12+DD11*Premissas!$C$14+DE11*Premissas!$F$14/12 -> 7529.3956 | DG11: =DF11*12 -> 90352.747 | DH11: =IFERROR(DF11/DA11,0) -> 64.697814 | DI11: =DF11*Premissas!$C$30 -> 451.76374 | DJ11: =DF11*Premissas!$C$28+EC11*Premissas!$C$29 -> 306.54599 | DK11: =DA11*Premissas!$C$31 -> 58.188949 | DL11: =DF11-DI11-DJ11-DK11 -> 6712.8969 | DM11: =IFERROR(DL11/DF11,0) -> 0.89155854 | DN11: =SUMPRODUCT(Premissas!$C$42:$C$61,--(Premissas!$D$42:$D$61<=CV11)) -> 2195 | DO11: =Premissas!$C$34*(1+Premissas!$C$35)^(CV11-1) -> 1738.9111 | DP11: =CX11*Premissas!$C$36*Premissas!$C$37 -> 158.61075 | DQ11: =DI11+DJ11+DK11+DN11+DO11+DP11 -> 4909.0205 | DR11: =DF11-DQ11 -> 2620.3751 | DS11: =N(DS10)+DR11 -> -2018.127 | DT11: =IFERROR((DO11+DP11)/CX11,0) -> 71.780324 | DU11: =IFERROR(DN11/(DL11/DA11),0) -> 38.053539 | DV11: =CX11*(1-Premissas!$E$23)*(1-Premissas!$E$24) -> 12.027982 | DW11: =CX11*(1-Premissas!$E$23)*Premissas!$E$24 -> 5.1548494 | DX11: =CX11*Premissas!$E$23*(1-Premissas!$E$24) -> 6.4766057 | DY11: =CX11*Premissas!$E$23*Premissas!$E$24 -> 2.7756882 | DZ11: =DW11+IF(CV11>12,INDEX($DW$6:$DW$29,CV11-12)*Premissas!$E$22,0) -> 5.1548494 | EA11: =DY11+IF(CV11>12,INDEX($DY$6:$DY$29,CV11-12)*Premissas!$E$22,0) -> 2.7756882 | EB11: =IF(CV11>12,(INDEX($DW$6:$DW$29,CV11-12)+INDEX($DY$6:$DY$29,CV11-12))*(1-Premissas!$E$22),0) -> 0 | EC11: =DB11+DD11+DZ11+EA11 -> 87.790085 | ED11: =IF(DR11>0,CV11,"") -> 6 | EE11: =DB11*Premissas!$C$13+DD11*Premissas!$C$14 -> 5462.3931 | EF11: =DZ11*Premissas!$F$13+EA11*Premissas!$F$14 -> 5386.5877 | EG11: =EE11+EF11 -> 10848.981 | EH11: =EG11*Premissas!$C$30 -> 650.93884 | EI11: =EG11*Premissas!$C$28+EC11*Premissas!$C$29 -> 422.73147 | EJ11: =DK11 -> 58.188949 | EK11: =DN11 -> 2195 | EL11: =DO11+DP11 -> 1897.5219 | EM11: =EH11+EI11+EJ11+EK11+EL11 -> 5224.3811 | EN11: =EG11-EM11 -> 5624.5996 | EO11: =IF(CV11=1,Premissas!$C$8,N(EO10))+EN11 -> 14495.77 | EP11: =DC11*Premissas!$F$13/12+DE11*Premissas!$F$14/12 -> 2067.0026 | EQ11: =N(EQ10)+EF11-EP11 -> 18247.401
B12: =B11+1 -> 7 | C12: =EDATE(Premissas!$C$7,B12-1) -> 46478 | D12: =Premissas!$C$19*(1+Premissas!$C$20)^(B12-1) -> 4.7762092 | E12: =IFERROR(D12/Premissas!$C$25,0) -> 47.762092 | F12: =(N(H11)+N(J11))*Premissas!$C$21+AH12 -> 1.5386984 | G12: =H12+I12+J12+K12 -> 25.058604 | H12: =N(H11)*(1-Premissas!$C$21)+AB12 -> 18.694577 | I12: =SUM(INDEX($AF$6:$AF$29,MAX(1,B12-11)):INDEX($AF$6:$AF$29,B12)) -> 2.6052371 | J12: =N(J11)*(1-Premissas!$C$21)+AD12 -> 3.2990429 | K12: =SUM(INDEX($AG$6:$AG$29,MAX(1,B12-11)):INDEX($AG$6:$AG$29,B12)) -> 0.45974773 | L12: =H12*Premissas!$C$13+I12*Premissas!$F$13/12+J12*Premissas!$C$14+K12*Premissas!$F$14/12 -> 1532.9481 | M12: =L12*12 -> 18395.377 | N12: =IFERROR(L12/G12,0) -> 61.174519 | O12: =L12*Premissas!$C$30 -> 91.976884 | P12: =L12*Premissas!$C$28+AI12*Premissas!$C$29 -> 64.66409 | Q12: =G12*Premissas!$C$31 -> 12.529302 | R12: =L12-O12-P12-Q12 -> 1363.7778 | S12: =IFERROR(R12/L12,0) -> 0.88964383 | T12: =SUMPRODUCT(Premissas!$C$42:$C$61,--(Premissas!$D$42:$D$61<=B12)) -> 3395 | U12: =Premissas!$C$34*(1+Premissas!$C$35)^(B12-1) -> 1791.0784 | V12: =D12*Premissas!$C$36*Premissas!$C$37 -> 28.657255 | W12: =O12+P12+Q12+T12+U12+V12 -> 5383.906 | X12: =L12-W12 -> -3850.9579 | Y12: =N(Y11)+X12 -> -22588.115 | Z12: =IFERROR((U12+V12)/D12,0) -> 381 | AA12: =IFERROR(T12/(R12/G12),0) -> 62.381102 | AB12: =D12*(1-Premissas!$C$23)*(1-Premissas!$C$24) -> 3.6538 | AC12: =D12*(1-Premissas!$C$23)*Premissas!$C$24 -> 0.40597778 | AD12: =D12*Premissas!$C$23*(1-Premissas!$C$24) -> 0.64478824 | AE12: =D12*Premissas!$C$23*Premissas!$C$24 -> 0.071643138 | AF12: =AC12+IF(B12>12,INDEX($AC$6:$AC$29,B12-12)*Premissas!$C$22,0) -> 0.40597778 | AG12: =AE12+IF(B12>12,INDEX($AE$6:$AE$29,B12-12)*Premissas!$C$22,0) -> 0.071643138 | AH12: =IF(B12>12,(INDEX($AC$6:$AC$29,B12-12)+INDEX($AE$6:$AE$29,B12-12))*(1-Premissas!$C$22),0) -> 0 | AI12: =H12+J12+AF12+AG12 -> 22.47124 | AJ12: =IF(X12>0,B12,"") | AK12: =H12*Premissas!$C$13+J12*Premissas!$C$14 -> 1372.4019 | AL12: =AF12*Premissas!$F$13+AG12*Premissas!$F$14 -> 300.2177 | AM12: =AK12+AL12 -> 1672.6196 | AN12: =AM12*Premissas!$C$30 -> 100.35717 | AO12: =AM12*Premissas!$C$28+AI12*Premissas!$C$29 -> 69.552593 | AP12: =Q12 -> 12.529302 | AQ12: =T12 -> 3395 | AR12: =U12+V12 -> 1819.7357 | AS12: =AN12+AO12+AP12+AQ12+AR12 -> 5397.1748 | AT12: =AM12-AS12 -> -3724.5552 | AU12: =IF(B12=1,Premissas!$C$8,N(AU11))+AT12 -> -21408.594 | AV12: =I12*Premissas!$F$13/12+K12*Premissas!$F$14/12 -> 160.54621 | AW12: =N(AW11)+AL12-AV12 -> 1303.3381 | AY12: =AY11+1 -> 7 | AZ12: =EDATE(Premissas!$C$7,AY12-1) -> 46478 | BA12: =Premissas!$D$19*(1+Premissas!$D$20)^(AY12-1) -> 12.005843 | BB12: =IFERROR(BA12/Premissas!$D$25,0) -> 60.029214 | BC12: =(N(BE11)+N(BG11))*Premissas!$D$21+CE12 -> 2.0417026 | BD12: =BE12+BF12+BG12+BH12 -> 62.243457 | BE12: =N(BE11)*(1-Premissas!$D$21)+BY12 -> 36.297767 | BF12: =SUM(INDEX($CC$6:$CC$29,MAX(1,AY12-11)):INDEX($CC$6:$CC$29,AY12)) -> 10.384825 | BG12: =N(BG11)*(1-Premissas!$D$21)+CA12 -> 12.099256 | BH12: =SUM(INDEX($CD$6:$CD$29,MAX(1,AY12-11)):INDEX($CD$6:$CD$29,AY12)) -> 3.4616084 | BI12: =BE12*Premissas!$C$13+BF12*Premissas!$F$13/12+BG12*Premissas!$C$14+BH12*Premissas!$F$14/12 -> 3919.6748 | BJ12: =BI12*12 -> 47036.097 | BK12: =IFERROR(BI12/BD12,0) -> 62.973283 | BL12: =BI12*Premissas!$C$30 -> 235.18049 | BM12: =BI12*Premissas!$C$28+CF12*Premissas!$C$29 -> 162.07973 | BN12: =BD12*Premissas!$C$31 -> 31.121728 | BO12: =BI12-BL12-BM12-BN12 -> 3491.2928 | BP12: =IFERROR(BO12/BI12,0) -> 0.89070982 | BQ12: =SUMPRODUCT(Premissas!$C$42:$C$61,--(Premissas!$D$42:$D$61<=AY12)) -> 3395 | BR12: =Premissas!$C$34*(1+Premissas!$C$35)^(AY12-1) -> 1791.0784 | BS12: =BA12*Premissas!$C$36*Premissas!$C$37 -> 72.035057 | BT12: =BL12+BM12+BN12+BQ12+BR12+BS12 -> 5686.4954 | BU12: =BI12-BT12 -> -1766.8207 | BV12: =N(BV11)+BU12 -> -15008.466 | BW12: =IFERROR((BR12+BS12)/BA12,0) -> 155.1839 | BX12: =IFERROR(BQ12/(BO12/BD12),0) -> 60.526729 | BY12: =BA12*(1-Premissas!$D$23)*(1-Premissas!$D$24) -> 7.2035057 | BZ12: =BA12*(1-Premissas!$D$23)*Premissas!$D$24 -> 1.8008764 | CA12: =BA12*Premissas!$D$23*(1-Premissas!$D$24) -> 2.4011686 | CB12: =BA12*Premissas!$D$23*Premissas!$D$24 -> 0.60029214 | CC12: =BZ12+IF(AY12>12,INDEX($BZ$6:$BZ$29,AY12-12)*Premissas!$D$22,0) -> 1.8008764 | CD12: =CB12+IF(AY12>12,INDEX($CB$6:$CB$29,AY12-12)*Premissas!$D$22,0) -> 0.60029214 | CE12: =IF(AY12>12,(INDEX($BZ$6:$BZ$29,AY12-12)+INDEX($CB$6:$CB$29,AY12-12))*(1-Premissas!$D$22),0) -> 0 | CF12: =BE12+BG12+CC12+CD12 -> 50.798192 | CG12: =IF(BU12>0,AY12,"") | CH12: =BE12*Premissas!$C$13+BG12*Premissas!$C$14 -> 3165.1653 | CI12: =CC12*Premissas!$F$13+CD12*Premissas!$F$14 -> 1570.1121 | CJ12: =CH12+CI12 -> 4735.2774 | CK12: =CJ12*Premissas!$C$30 -> 284.11665 | CL12: =CJ12*Premissas!$C$28+CF12*Premissas!$C$29 -> 190.62582 | CM12: =BN12 -> 31.121728 | CN12: =BQ12 -> 3395 | CO12: =BR12+BS12 -> 1863.1135 | CP12: =CK12+CL12+CM12+CN12+CO12 -> 5763.9777 | CQ12: =CJ12-CP12 -> -1028.7003 | CR12: =IF(AY12=1,Premissas!$C$8,N(CR11))+CQ12 -> -9361.7213 | CS12: =BF12*Premissas!$F$13/12+BH12*Premissas!$F$14/12 -> 754.50948 | CT12: =N(CT11)+CI12-CS12 -> 6239.4974 | CV12: =CV11+1 -> 7 | CW12: =EDATE(Premissas!$C$7,CV12-1) -> 46478 | CX12: =Premissas!$E$19*(1+Premissas!$E$20)^(CV12-1) -> 29.60734 | CY12: =IFERROR(CX12/Premissas!$E$25,0) -> 98.691134 | CZ12: =(N(DB11)+N(DD11))*Premissas!$E$21+EB12 -> 2.3957864 | DA12: =DB12+DC12+DD12+DE12 -> 143.58945 | DB12: =N(DB11)*(1-Premissas!$E$21)+DV12 -> 63.822785 | DC12: =SUM(INDEX($DZ$6:$DZ$29,MAX(1,CV12-11)):INDEX($DZ$6:$DZ$29,CV12)) -> 29.510359 | DD12: =N(DD11)*(1-Premissas!$E$21)+DX12 -> 34.366115 | DE12: =SUM(INDEX($EA$6:$EA$29,MAX(1,CV12-11)):INDEX($EA$6:$EA$29,CV12)) -> 15.890193 | DF12: =DB12*Premissas!$C$13+DC12*Premissas!$F$13/12+DD12*Premissas!$C$14+DE12*Premissas!$F$14/12 -> 9285.8715 | DG12: =DF12*12 -> 111430.46 | DH12: =IFERROR(DF12/DA12,0) -> 64.669593 | DI12: =DF12*Premissas!$C$30 -> 557.15229 | DJ12: =DF12*Premissas!$C$28+EC12*Premissas!$C$29 -> 377.47034 | DK12: =DA12*Premissas!$C$31 -> 71.794726 | DL12: =DF12-DI12-DJ12-DK12 -> 8279.4541 | DM12: =IFERROR(DL12/DF12,0) -> 0.89161843 | DN12: =SUMPRODUCT(Premissas!$C$42:$C$61,--(Premissas!$D$42:$D$61<=CV12)) -> 3395 | DO12: =Premissas!$C$34*(1+Premissas!$C$35)^(CV12-1) -> 1791.0784 | DP12: =CX12*Premissas!$C$36*Premissas!$C$37 -> 177.64404 | DQ12: =DI12+DJ12+DK12+DN12+DO12+DP12 -> 6370.1398 | DR12: =DF12-DQ12 -> 2915.7316 | DS12: =N(DS11)+DR12 -> 897.60459 | DT12: =IFERROR((DO12+DP12)/CX12,0) -> 66.494405 | DU12: =IFERROR(DN12/(DL12/DA12),0) -> 58.879026 | DV12: =CX12*(1-Premissas!$E$23)*(1-Premissas!$E$24) -> 13.47134 | DW12: =CX12*(1-Premissas!$E$23)*Premissas!$E$24 -> 5.7734314 | DX12: =CX12*Premissas!$E$23*(1-Premissas!$E$24) -> 7.2537984 | DY12: =CX12*Premissas!$E$23*Premissas!$E$24 -> 3.1087707 | DZ12: =DW12+IF(CV12>12,INDEX($DW$6:$DW$29,CV12-12)*Premissas!$E$22,0) -> 5.7734314 | EA12: =DY12+IF(CV12>12,INDEX($DY$6:$DY$29,CV12-12)*Premissas!$E$22,0) -> 3.1087707 | EB12: =IF(CV12>12,(INDEX($DW$6:$DW$29,CV12-12)+INDEX($DY$6:$DY$29,CV12-12))*(1-Premissas!$E$22),0) -> 0 | EC12: =DB12+DD12+DZ12+EA12 -> 107.0711 | ED12: =IF(DR12>0,CV12,"") -> 7 | EE12: =DB12*Premissas!$C$13+DD12*Premissas!$C$14 -> 6716.1207 | EF12: =DZ12*Premissas!$F$13+EA12*Premissas!$F$14 -> 6032.9782 | EG12: =EE12+EF12 -> 12749.099 | EH12: =EG12*Premissas!$C$30 -> 764.94593 | EI12: =EG12*Premissas!$C$28+EC12*Premissas!$C$29 -> 498.6833 | EJ12: =DK12 -> 71.794726 | EK12: =DN12 -> 3395 | EL12: =DO12+DP12 -> 1968.7225 | EM12: =EH12+EI12+EJ12+EK12+EL12 -> 6699.1464 | EN12: =EG12-EM12 -> 6049.9525 | EO12: =IF(CV12=1,Premissas!$C$8,N(EO11))+EN12 -> 20545.723 | EP12: =DC12*Premissas!$F$13/12+DE12*Premissas!$F$14/12 -> 2569.7507 | EQ12: =N(EQ11)+EF12-EP12 -> 21710.628
B13: =B12+1 -> 8 | C13: =EDATE(Premissas!$C$7,B13-1) -> 46508 | D13: =Premissas!$C$19*(1+Premissas!$C$20)^(B13-1) -> 4.9194955 | E13: =IFERROR(D13/Premissas!$C$25,0) -> 49.194955 | F13: =(N(H12)+N(J12))*Premissas!$C$21+AH13 -> 1.7594896 | G13: =H13+I13+J13+K13 -> 28.21861 | H13: =N(H12)*(1-Premissas!$C$21)+AB13 -> 20.962425 | I13: =SUM(INDEX($AF$6:$AF$29,MAX(1,B13-11)):INDEX($AF$6:$AF$29,B13)) -> 3.0233943 | J13: =N(J12)*(1-Premissas!$C$21)+AD13 -> 3.6992514 | K13: =SUM(INDEX($AG$6:$AG$29,MAX(1,B13-11)):INDEX($AG$6:$AG$29,B13)) -> 0.53354016 | L13: =H13*Premissas!$C$13+I13*Premissas!$F$13/12+J13*Premissas!$C$14+K13*Premissas!$F$14/12 -> 1725.2035 | M13: =L13*12 -> 20702.442 | N13: =IFERROR(L13/G13,0) -> 61.137081 | O13: =L13*Premissas!$C$30 -> 103.51221 | P13: =L13*Premissas!$C$28+AI13*Premissas!$C$29 -> 72.707398 | Q13: =G13*Premissas!$C$31 -> 14.109305 | R13: =L13-O13-P13-Q13 -> 1534.8746 | S13: =IFERROR(R13/L13,0) -> 0.88967741 | T13: =SUMPRODUCT(Premissas!$C$42:$C$61,--(Premissas!$D$42:$D$61<=B13)) -> 3395 | U13: =Premissas!$C$34*(1+Premissas!$C$35)^(B13-1) -> 1844.8108 | V13: =D13*Premissas!$C$36*Premissas!$C$37 -> 29.516973 | W13: =O13+P13+Q13+T13+U13+V13 -> 5459.6567 | X13: =L13-W13 -> -3734.4532 | Y13: =N(Y12)+X13 -> -26322.568 | Z13: =IFERROR((U13+V13)/D13,0) -> 381 | AA13: =IFERROR(T13/(R13/G13),0) -> 62.416946 | AB13: =D13*(1-Premissas!$C$23)*(1-Premissas!$C$24) -> 3.763414 | AC13: =D13*(1-Premissas!$C$23)*Premissas!$C$24 -> 0.41815711 | AD13: =D13*Premissas!$C$23*(1-Premissas!$C$24) -> 0.66413189 | AE13: =D13*Premissas!$C$23*Premissas!$C$24 -> 0.073792432 | AF13: =AC13+IF(B13>12,INDEX($AC$6:$AC$29,B13-12)*Premissas!$C$22,0) -> 0.41815711 | AG13: =AE13+IF(B13>12,INDEX($AE$6:$AE$29,B13-12)*Premissas!$C$22,0) -> 0.073792432 | AH13: =IF(B13>12,(INDEX($AC$6:$AC$29,B13-12)+INDEX($AE$6:$AE$29,B13-12))*(1-Premissas!$C$22),0) -> 0 | AI13: =H13+J13+AF13+AG13 -> 25.153625 | AJ13: =IF(X13>0,B13,"") | AK13: =H13*Premissas!$C$13+J13*Premissas!$C$14 -> 1538.8886 | AL13: =AF13*Premissas!$F$13+AG13*Premissas!$F$14 -> 309.22423 | AM13: =AK13+AL13 -> 1848.1128 | AN13: =AM13*Premissas!$C$30 -> 110.88677 | AO13: =AM13*Premissas!$C$28+AI13*Premissas!$C$29 -> 77.009225 | AP13: =Q13 -> 14.109305 | AQ13: =T13 -> 3395 | AR13: =U13+V13 -> 1874.3278 | AS13: =AN13+AO13+AP13+AQ13+AR13 -> 5471.3331 | AT13: =AM13-AS13 -> -3623.2203 | AU13: =IF(B13=1,Premissas!$C$8,N(AU12))+AT13 -> -25031.814 | AV13: =I13*Premissas!$F$13/12+K13*Premissas!$F$14/12 -> 186.31489 | AW13: =N(AW12)+AL13-AV13 -> 1426.2474 | AY13: =AY12+1 -> 8 | AZ13: =EDATE(Premissas!$C$7,AY13-1) -> 46508 | BA13: =Premissas!$D$19*(1+Premissas!$D$20)^(AY13-1) -> 12.846252 | BB13: =IFERROR(BA13/Premissas!$D$25,0) -> 64.231259 | BC13: =(N(BE12)+N(BG12))*Premissas!$D$21+CE13 -> 2.4198511 | BD13: =BE13+BF13+BG13+BH13 -> 72.669857 | BE13: =N(BE12)*(1-Premissas!$D$21)+BY13 -> 42.19063 | BF13: =SUM(INDEX($CC$6:$CC$29,MAX(1,AY13-11)):INDEX($CC$6:$CC$29,AY13)) -> 12.311763 | BG13: =N(BG12)*(1-Premissas!$D$21)+CA13 -> 14.063543 | BH13: =SUM(INDEX($CD$6:$CD$29,MAX(1,AY13-11)):INDEX($CD$6:$CD$29,AY13)) -> 4.103921 | BI13: =BE13*Premissas!$C$13+BF13*Premissas!$F$13/12+BG13*Premissas!$C$14+BH13*Premissas!$F$14/12 -> 4573.5341 | BJ13: =BI13*12 -> 54882.409 | BK13: =IFERROR(BI13/BD13,0) -> 62.935779 | BL13: =BI13*Premissas!$C$30 -> 274.41204 | BM13: =BI13*Premissas!$C$28+CF13*Premissas!$C$29 -> 188.89717 | BN13: =BD13*Premissas!$C$31 -> 36.334929 | BO13: =BI13-BL13-BM13-BN13 -> 4073.8899 | BP13: =IFERROR(BO13/BI13,0) -> 0.89075316 | BQ13: =SUMPRODUCT(Premissas!$C$42:$C$61,--(Premissas!$D$42:$D$61<=AY13)) -> 3395 | BR13: =Premissas!$C$34*(1+Premissas!$C$35)^(AY13-1) -> 1844.8108 | BS13: =BA13*Premissas!$C$36*Premissas!$C$37 -> 77.077511 | BT13: =BL13+BM13+BN13+BQ13+BR13+BS13 -> 5816.5325 | BU13: =BI13-BT13 -> -1242.9984 | BV13: =N(BV12)+BU13 -> -16251.465 | BW13: =IFERROR((BR13+BS13)/BA13,0) -> 149.60693 | BX13: =IFERROR(BQ13/(BO13/BD13),0) -> 60.559851 | BY13: =BA13*(1-Premissas!$D$23)*(1-Premissas!$D$24) -> 7.7077511 | BZ13: =BA13*(1-Premissas!$D$23)*Premissas!$D$24 -> 1.9269378 | CA13: =BA13*Premissas!$D$23*(1-Premissas!$D$24) -> 2.5692504 | CB13: =BA13*Premissas!$D$23*Premissas!$D$24 -> 0.64231259 | CC13: =BZ13+IF(AY13>12,INDEX($BZ$6:$BZ$29,AY13-12)*Premissas!$D$22,0) -> 1.9269378 | CD13: =CB13+IF(AY13>12,INDEX($CB$6:$CB$29,AY13-12)*Premissas!$D$22,0) -> 0.64231259 | CE13: =IF(AY13>12,(INDEX($BZ$6:$BZ$29,AY13-12)+INDEX($CB$6:$CB$29,AY13-12))*(1-Premissas!$D$22),0) -> 0 | CF13: =BE13+BG13+CC13+CD13 -> 58.823424 | CG13: =IF(BU13>0,AY13,"") | CH13: =BE13*Premissas!$C$13+BG13*Premissas!$C$14 -> 3679.0229 | CI13: =CC13*Premissas!$F$13+CD13*Premissas!$F$14 -> 1680.02 | CJ13: =CH13+CI13 -> 5359.0429 | CK13: =CJ13*Premissas!$C$30 -> 321.54257 | CL13: =CJ13*Premissas!$C$28+CF13*Premissas!$C$29 -> 216.38998 | CM13: =BN13 -> 36.334929 | CN13: =BQ13 -> 3395 | CO13: =BR13+BS13 -> 1921.8883 | CP13: =CK13+CL13+CM13+CN13+CO13 -> 5891.1558 | CQ13: =CJ13-CP13 -> -532.11289 | CR13: =IF(AY13=1,Premissas!$C$8,N(CR12))+CQ13 -> -9893.8342 | CS13: =BF13*Premissas!$F$13/12+BH13*Premissas!$F$14/12 -> 894.51115 | CT13: =N(CT12)+CI13-CS13 -> 7025.0062 | CV13: =CV12+1 -> 8 | CW13: =EDATE(Premissas!$C$7,CV13-1) -> 46508 | CX13: =Premissas!$E$19*(1+Premissas!$E$20)^(CV13-1) -> 33.160221 | CY13: =IFERROR(CX13/Premissas!$E$25,0) -> 110.53407 | CZ13: =(N(DB12)+N(DD12))*Premissas!$E$21+EB13 -> 2.945667 | DA13: =DB13+DC13+DD13+DE13 -> 173.80401 | DB13: =N(DB12)*(1-Premissas!$E$21)+DV13 -> 76.996002 | DC13: =SUM(INDEX($DZ$6:$DZ$29,MAX(1,CV13-11)):INDEX($DZ$6:$DZ$29,CV13)) -> 35.976602 | DD13: =N(DD12)*(1-Premissas!$E$21)+DX13 -> 41.459386 | DE13: =SUM(INDEX($EA$6:$EA$29,MAX(1,CV13-11)):INDEX($EA$6:$EA$29,CV13)) -> 19.372017 | DF13: =DB13*Premissas!$C$13+DC13*Premissas!$F$13/12+DD13*Premissas!$C$14+DE13*Premissas!$F$14/12 -> 11235.177 | DG13: =DF13*12 -> 134822.13 | DH13: =IFERROR(DF13/DA13,0) -> 64.642798 | DI13: =DF13*Premissas!$C$30 -> 674.11063 | DJ13: =DF13*Premissas!$C$28+EC13*Premissas!$C$29 -> 456.14889 | DK13: =DA13*Premissas!$C$31 -> 86.902003 | DL13: =DF13-DI13-DJ13-DK13 -> 10018.016 | DM13: =IFERROR(DL13/DF13,0) -> 0.89166512 | DN13: =SUMPRODUCT(Premissas!$C$42:$C$61,--(Premissas!$D$42:$D$61<=CV13)) -> 3395 | DO13: =Premissas!$C$34*(1+Premissas!$C$35)^(CV13-1) -> 1844.8108 | DP13: =CX13*Premissas!$C$36*Premissas!$C$37 -> 198.96133 | DQ13: =DI13+DJ13+DK13+DN13+DO13+DP13 -> 6655.9337 | DR13: =DF13-DQ13 -> 4579.2435 | DS13: =N(DS12)+DR13 -> 5476.8481 | DT13: =IFERROR((DO13+DP13)/CX13,0) -> 61.633248 | DU13: =IFERROR(DN13/(DL13/DA13),0) -> 58.900347 | DV13: =CX13*(1-Premissas!$E$23)*(1-Premissas!$E$24) -> 15.087901 | DW13: =CX13*(1-Premissas!$E$23)*Premissas!$E$24 -> 6.4662431 | DX13: =CX13*Premissas!$E$23*(1-Premissas!$E$24) -> 8.1242542 | DY13: =CX13*Premissas!$E$23*Premissas!$E$24 -> 3.4818232 | DZ13: =DW13+IF(CV13>12,INDEX($DW$6:$DW$29,CV13-12)*Premissas!$E$22,0) -> 6.4662431 | EA13: =DY13+IF(CV13>12,INDEX($DY$6:$DY$29,CV13-12)*Premissas!$E$22,0) -> 3.4818232 | EB13: =IF(CV13>12,(INDEX($DW$6:$DW$29,CV13-12)+INDEX($DY$6:$DY$29,CV13-12))*(1-Premissas!$E$22),0) -> 0 | EC13: =DB13+DD13+DZ13+EA13 -> 128.40345 | ED13: =IF(DR13>0,CV13,"") -> 8 | EE13: =DB13*Premissas!$C$13+DD13*Premissas!$C$14 -> 8102.3485 | EF13: =DZ13*Premissas!$F$13+EA13*Premissas!$F$14 -> 6756.9356 | EG13: =EE13+EF13 -> 14859.284 | EH13: =EG13*Premissas!$C$30 -> 891.55704 | EI13: =EG13*Premissas!$C$28+EC13*Premissas!$C$29 -> 582.99263 | EJ13: =DK13 -> 86.902003 | EK13: =DN13 -> 3395 | EL13: =DO13+DP13 -> 2043.7721 | EM13: =EH13+EI13+EJ13+EK13+EL13 -> 7000.2238 | EN13: =EG13-EM13 -> 7859.0602 | EO13: =IF(CV13=1,Premissas!$C$8,N(EO12))+EN13 -> 28404.783 | EP13: =DC13*Premissas!$F$13/12+DE13*Premissas!$F$14/12 -> 3132.8287 | EQ13: =N(EQ12)+EF13-EP13 -> 25334.735
B14: =B13+1 -> 9 | C14: =EDATE(Premissas!$C$7,B14-1) -> 46539 | D14: =Premissas!$C$19*(1+Premissas!$C$20)^(B14-1) -> 5.0670803 | E14: =IFERROR(D14/Premissas!$C$25,0) -> 50.670803 | F14: =(N(H13)+N(J13))*Premissas!$C$21+AH14 -> 1.9729341 | G14: =H14+I14+J14+K14 -> 31.312757 | H14: =N(H13)*(1-Premissas!$C$21)+AB14 -> 23.161747 | I14: =SUM(INDEX($AF$6:$AF$29,MAX(1,B14-11)):INDEX($AF$6:$AF$29,B14)) -> 3.4540961 | J14: =N(J13)*(1-Premissas!$C$21)+AD14 -> 4.0873671 | K14: =SUM(INDEX($AG$6:$AG$29,MAX(1,B14-11)):INDEX($AG$6:$AG$29,B14)) -> 0.60954637 | L14: =H14*Premissas!$C$13+I14*Premissas!$F$13/12+J14*Premissas!$C$14+K14*Premissas!$F$14/12 -> 1913.2014 | M14: =L14*12 -> 22958.416 | N14: =IFERROR(L14/G14,0) -> 61.099742 | O14: =L14*Premissas!$C$30 -> 114.79208 | P14: =L14*Premissas!$C$28+AI14*Premissas!$C$29 -> 80.5624 | Q14: =G14*Premissas!$C$31 -> 15.656378 | R14: =L14-O14-P14-Q14 -> 1702.1905 | S14: =IFERROR(R14/L14,0) -> 0.88970797 | T14: =SUMPRODUCT(Premissas!$C$42:$C$61,--(Premissas!$D$42:$D$61<=B14)) -> 3395 | U14: =Premissas!$C$34*(1+Premissas!$C$35)^(B14-1) -> 1900.1551 | V14: =D14*Premissas!$C$36*Premissas!$C$37 -> 30.402482 | W14: =O14+P14+Q14+T14+U14+V14 -> 5536.5685 | X14: =L14-W14 -> -3623.3671 | Y14: =N(Y13)+X14 -> -29945.935 | Z14: =IFERROR((U14+V14)/D14,0) -> 381 | AA14: =IFERROR(T14/(R14/G14),0) -> 62.452944 | AB14: =D14*(1-Premissas!$C$23)*(1-Premissas!$C$24) -> 3.8763164 | AC14: =D14*(1-Premissas!$C$23)*Premissas!$C$24 -> 0.43070183 | AD14: =D14*Premissas!$C$23*(1-Premissas!$C$24) -> 0.68405584 | AE14: =D14*Premissas!$C$23*Premissas!$C$24 -> 0.076006205 | AF14: =AC14+IF(B14>12,INDEX($AC$6:$AC$29,B14-12)*Premissas!$C$22,0) -> 0.43070183 | AG14: =AE14+IF(B14>12,INDEX($AE$6:$AE$29,B14-12)*Premissas!$C$22,0) -> 0.076006205 | AH14: =IF(B14>12,(INDEX($AC$6:$AC$29,B14-12)+INDEX($AE$6:$AE$29,B14-12))*(1-Premissas!$C$22),0) -> 0 | AI14: =H14+J14+AF14+AG14 -> 27.755822 | AJ14: =IF(X14>0,B14,"") | AK14: =H14*Premissas!$C$13+J14*Premissas!$C$14 -> 1700.3447 | AL14: =AF14*Premissas!$F$13+AG14*Premissas!$F$14 -> 318.50096 | AM14: =AK14+AL14 -> 2018.8457 | AN14: =AM14*Premissas!$C$30 -> 121.13074 | AO14: =AM14*Premissas!$C$28+AI14*Premissas!$C$29 -> 84.259952 | AP14: =Q14 -> 15.656378 | AQ14: =T14 -> 3395 | AR14: =U14+V14 -> 1930.5576 | AS14: =AN14+AO14+AP14+AQ14+AR14 -> 5546.6047 | AT14: =AM14-AS14 -> -3527.759 | AU14: =IF(B14=1,Premissas!$C$8,N(AU13))+AT14 -> -28559.573 | AV14: =I14*Premissas!$F$13/12+K14*Premissas!$F$14/12 -> 212.85664 | AW14: =N(AW13)+AL14-AV14 -> 1531.8917 | AY14: =AY13+1 -> 9 | AZ14: =EDATE(Premissas!$C$7,AY14-1) -> 46539 | BA14: =Premissas!$D$19*(1+Premissas!$D$20)^(AY14-1) -> 13.745489 | BB14: =IFERROR(BA14/Premissas!$D$25,0) -> 68.727447 | BC14: =(N(BE13)+N(BG13))*Premissas!$D$21+CE14 -> 2.8127087 | BD14: =BE14+BF14+BG14+BH14 -> 83.602638 | BE14: =N(BE13)*(1-Premissas!$D$21)+BY14 -> 48.328392 | BF14: =SUM(INDEX($CC$6:$CC$29,MAX(1,AY14-11)):INDEX($CC$6:$CC$29,AY14)) -> 14.373586 | BG14: =N(BG13)*(1-Premissas!$D$21)+CA14 -> 16.109464 | BH14: =SUM(INDEX($CD$6:$CD$29,MAX(1,AY14-11)):INDEX($CD$6:$CD$29,AY14)) -> 4.7911955 | BI14: =BE14*Premissas!$C$13+BF14*Premissas!$F$13/12+BG14*Premissas!$C$14+BH14*Premissas!$F$14/12 -> 5258.5487 | BJ14: =BI14*12 -> 63102.585 | BK14: =IFERROR(BI14/BD14,0) -> 62.899316 | BL14: =BI14*Premissas!$C$30 -> 315.51292 | BM14: =BI14*Premissas!$C$28+CF14*Premissas!$C$29 -> 216.97081 | BN14: =BD14*Premissas!$C$31 -> 41.801319 | BO14: =BI14-BL14-BM14-BN14 -> 4684.2637 | BP14: =IFERROR(BO14/BI14,0) -> 0.8907902 | BQ14: =SUMPRODUCT(Premissas!$C$42:$C$61,--(Premissas!$D$42:$D$61<=AY14)) -> 3395 | BR14: =Premissas!$C$34*(1+Premissas!$C$35)^(AY14-1) -> 1900.1551 | BS14: =BA14*Premissas!$C$36*Premissas!$C$37 -> 82.472937 | BT14: =BL14+BM14+BN14+BQ14+BR14+BS14 -> 5951.9131 | BU14: =BI14-BT14 -> -693.36439 | BV14: =N(BV13)+BU14 -> -16944.829 | BW14: =IFERROR((BR14+BS14)/BA14,0) -> 144.23845 | BX14: =IFERROR(BQ14/(BO14/BD14),0) -> 60.592438 | BY14: =BA14*(1-Premissas!$D$23)*(1-Premissas!$D$24) -> 8.2472937 | BZ14: =BA14*(1-Premissas!$D$23)*Premissas!$D$24 -> 2.0618234 | CA14: =BA14*Premissas!$D$23*(1-Premissas!$D$24) -> 2.7490979 | CB14: =BA14*Premissas!$D$23*Premissas!$D$24 -> 0.68727447 | CC14: =BZ14+IF(AY14>12,INDEX($BZ$6:$BZ$29,AY14-12)*Premissas!$D$22,0) -> 2.0618234 | CD14: =CB14+IF(AY14>12,INDEX($CB$6:$CB$29,AY14-12)*Premissas!$D$22,0) -> 0.68727447 | CE14: =IF(AY14>12,(INDEX($BZ$6:$BZ$29,AY14-12)+INDEX($CB$6:$CB$29,AY14-12))*(1-Premissas!$D$22),0) -> 0 | CF14: =BE14+BG14+CC14+CD14 -> 67.186954 | CG14: =IF(BU14>0,AY14,"") | CH14: =BE14*Premissas!$C$13+BG14*Premissas!$C$14 -> 4214.2358 | CI14: =CC14*Premissas!$F$13+CD14*Premissas!$F$14 -> 1797.6214 | CJ14: =CH14+CI14 -> 6011.8572 | CK14: =CJ14*Premissas!$C$30 -> 360.71143 | CL14: =CJ14*Premissas!$C$28+CF14*Premissas!$C$29 -> 243.33661 | CM14: =BN14 -> 41.801319 | CN14: =BQ14 -> 3395 | CO14: =BR14+BS14 -> 1982.6281 | CP14: =CK14+CL14+CM14+CN14+CO14 -> 6023.4774 | CQ14: =CJ14-CP14 -> -11.62026 | CR14: =IF(AY14=1,Premissas!$C$8,N(CR13))+CQ14 -> -9905.4545 | CS14: =BF14*Premissas!$F$13/12+BH14*Premissas!$F$14/12 -> 1044.3129 | CT14: =N(CT13)+CI14-CS14 -> 7778.3147 | CV14: =CV13+1 -> 9 | CW14: =EDATE(Premissas!$C$7,CV14-1) -> 46539 | CX14: =Premissas!$E$19*(1+Premissas!$E$20)^(CV14-1) -> 37.139448 | CY14: =IFERROR(CX14/Premissas!$E$25,0) -> 123.79816 | CZ14: =(N(DB13)+N(DD13))*Premissas!$E$21+EB14 -> 3.5536616 | DA14: =DB14+DC14+DD14+DE14 -> 207.38979 | DB14: =N(DB13)*(1-Premissas!$E$21)+DV14 -> 91.58457 | DC14: =SUM(INDEX($DZ$6:$DZ$29,MAX(1,CV14-11)):INDEX($DZ$6:$DZ$29,CV14)) -> 43.218795 | DD14: =N(DD13)*(1-Premissas!$E$21)+DX14 -> 49.314769 | DE14: =SUM(INDEX($EA$6:$EA$29,MAX(1,CV14-11)):INDEX($EA$6:$EA$29,CV14)) -> 23.271659 | DF14: =DB14*Premissas!$C$13+DC14*Premissas!$F$13/12+DD14*Premissas!$C$14+DE14*Premissas!$F$14/12 -> 13400.991 | DG14: =DF14*12 -> 160811.89 | DH14: =IFERROR(DF14/DA14,0) -> 64.617408 | DI14: =DF14*Premissas!$C$30 -> 804.05945 | DJ14: =DF14*Premissas!$C$28+EC14*Premissas!$C$29 -> 543.53485 | DK14: =DA14*Premissas!$C$31 -> 103.6949 | DL14: =DF14-DI14-DJ14-DK14 -> 11949.702 | DM14: =IFERROR(DL14/DF14,0) -> 0.89170284 | DN14: =SUMPRODUCT(Premissas!$C$42:$C$61,--(Premissas!$D$42:$D$61<=CV14)) -> 3395 | DO14: =Premissas!$C$34*(1+Premissas!$C$35)^(CV14-1) -> 1900.1551 | DP14: =CX14*Premissas!$C$36*Premissas!$C$37 -> 222.83669 | DQ14: =DI14+DJ14+DK14+DN14+DO14+DP14 -> 6969.281 | DR14: =DF14-DQ14 -> 6431.7098 | DS14: =N(DS13)+DR14 -> 11908.558 | DT14: =IFERROR((DO14+DP14)/CX14,0) -> 57.162719 | DU14: =IFERROR(DN14/(DL14/DA14),0) -> 58.920998 | DV14: =CX14*(1-Premissas!$E$23)*(1-Premissas!$E$24) -> 16.898449 | DW14: =CX14*(1-Premissas!$E$23)*Premissas!$E$24 -> 7.2421923 | DX14: =CX14*Premissas!$E$23*(1-Premissas!$E$24) -> 9.0991647 | DY14: =CX14*Premissas!$E$23*Premissas!$E$24 -> 3.899642 | DZ14: =DW14+IF(CV14>12,INDEX($DW$6:$DW$29,CV14-12)*Premissas!$E$22,0) -> 7.2421923 | EA14: =DY14+IF(CV14>12,INDEX($DY$6:$DY$29,CV14-12)*Premissas!$E$22,0) -> 3.899642 | EB14: =IF(CV14>12,(INDEX($DW$6:$DW$29,CV14-12)+INDEX($DY$6:$DY$29,CV14-12))*(1-Premissas!$E$22),0) -> 0 | EC14: =DB14+DD14+DZ14+EA14 -> 152.04117 | ED14: =IF(DR14>0,CV14,"") -> 9 | EE14: =DB14*Premissas!$C$13+DD14*Premissas!$C$14 -> 9637.5148 | EF14: =DZ14*Premissas!$F$13+EA14*Premissas!$F$14 -> 7567.7678 | EG14: =EE14+EF14 -> 17205.283 | EH14: =EG14*Premissas!$C$30 -> 1032.317 | EI14: =EG14*Premissas!$C$28+EC14*Premissas!$C$29 -> 676.68507 | EJ14: =DK14 -> 103.6949 | EK14: =DN14 -> 3395 | EL14: =DO14+DP14 -> 2122.9918 | EM14: =EH14+EI14+EJ14+EK14+EL14 -> 7330.6887 | EN14: =EG14-EM14 -> 9874.5939 | EO14: =IF(CV14=1,Premissas!$C$8,N(EO13))+EN14 -> 38279.377 | EP14: =DC14*Premissas!$F$13/12+DE14*Premissas!$F$14/12 -> 3763.476 | EQ14: =N(EQ13)+EF14-EP14 -> 29139.027
B15: =B14+1 -> 10 | C15: =EDATE(Premissas!$C$7,B15-1) -> 46569 | D15: =Premissas!$C$19*(1+Premissas!$C$20)^(B15-1) -> 5.2190927 | E15: =IFERROR(D15/Premissas!$C$25,0) -> 52.190927 | F15: =(N(H14)+N(J14))*Premissas!$C$21+AH15 -> 2.1799291 | G15: =H15+I15+J15+K15 -> 34.35192 | H15: =N(H14)*(1-Premissas!$C$21)+AB15 -> 25.301413 | I15: =SUM(INDEX($AF$6:$AF$29,MAX(1,B15-11)):INDEX($AF$6:$AF$29,B15)) -> 3.897719 | J15: =N(J14)*(1-Premissas!$C$21)+AD15 -> 4.4649553 | K15: =SUM(INDEX($AG$6:$AG$29,MAX(1,B15-11)):INDEX($AG$6:$AG$29,B15)) -> 0.68783276 | L15: =H15*Premissas!$C$13+I15*Premissas!$F$13/12+J15*Premissas!$C$14+K15*Premissas!$F$14/12 -> 2097.616 | M15: =L15*12 -> 25171.392 | N15: =IFERROR(L15/G15,0) -> 61.062555 | O15: =L15*Premissas!$C$30 -> 125.85696 | P15: =L15*Premissas!$C$28+AI15*Premissas!$C$29 -> 88.257817 | Q15: =G15*Premissas!$C$31 -> 17.17596 | R15: =L15-O15-P15-Q15 -> 1866.3253 | S15: =IFERROR(R15/L15,0) -> 0.88973638 | T15: =SUMPRODUCT(Premissas!$C$42:$C$61,--(Premissas!$D$42:$D$61<=B15)) -> 3395 | U15: =Premissas!$C$34*(1+Premissas!$C$35)^(B15-1) -> 1957.1598 | V15: =D15*Premissas!$C$36*Premissas!$C$37 -> 31.314556 | W15: =O15+P15+Q15+T15+U15+V15 -> 5614.7651 | X15: =L15-W15 -> -3517.149 | Y15: =N(Y14)+X15 -> -33463.084 | Z15: =IFERROR((U15+V15)/D15,0) -> 381 | AA15: =IFERROR(T15/(R15/G15),0) -> 62.488983 | AB15: =D15*(1-Premissas!$C$23)*(1-Premissas!$C$24) -> 3.9926059 | AC15: =D15*(1-Premissas!$C$23)*Premissas!$C$24 -> 0.44362288 | AD15: =D15*Premissas!$C$23*(1-Premissas!$C$24) -> 0.70457752 | AE15: =D15*Premissas!$C$23*Premissas!$C$24 -> 0.078286391 | AF15: =AC15+IF(B15>12,INDEX($AC$6:$AC$29,B15-12)*Premissas!$C$22,0) -> 0.44362288 | AG15: =AE15+IF(B15>12,INDEX($AE$6:$AE$29,B15-12)*Premissas!$C$22,0) -> 0.078286391 | AH15: =IF(B15>12,(INDEX($AC$6:$AC$29,B15-12)+INDEX($AE$6:$AE$29,B15-12))*(1-Premissas!$C$22),0) -> 0 | AI15: =H15+J15+AF15+AG15 -> 30.288278 | AJ15: =IF(X15>0,B15,"") | AK15: =H15*Premissas!$C$13+J15*Premissas!$C$14 -> 1857.4214 | AL15: =AF15*Premissas!$F$13+AG15*Premissas!$F$14 -> 328.05599 | AM15: =AK15+AL15 -> 2185.4774 | AN15: =AM15*Premissas!$C$30 -> 131.12864 | AO15: =AM15*Premissas!$C$28+AI15*Premissas!$C$29 -> 91.332964 | AP15: =Q15 -> 17.17596 | AQ15: =T15 -> 3395 | AR15: =U15+V15 -> 1988.4743 | AS15: =AN15+AO15+AP15+AQ15+AR15 -> 5623.1119 | AT15: =AM15-AS15 -> -3437.6345 | AU15: =IF(B15=1,Premissas!$C$8,N(AU14))+AT15 -> -31997.207 | AV15: =I15*Premissas!$F$13/12+K15*Premissas!$F$14/12 -> 240.19464 | AW15: =N(AW14)+AL15-AV15 -> 1619.7531 | AY15: =AY14+1 -> 10 | AZ15: =EDATE(Premissas!$C$7,AY15-1) -> 46569 | BA15: =Premissas!$D$19*(1+Premissas!$D$20)^(AY15-1) -> 14.707674 | BB15: =IFERROR(BA15/Premissas!$D$25,0) -> 73.538368 | BC15: =(N(BE14)+N(BG14))*Premissas!$D$21+CE15 -> 3.2218928 | BD15: =BE15+BF15+BG15+BH15 -> 95.088419 | BE15: =N(BE14)*(1-Premissas!$D$21)+BY15 -> 54.736577 | BF15: =SUM(INDEX($CC$6:$CC$29,MAX(1,AY15-11)):INDEX($CC$6:$CC$29,AY15)) -> 16.579738 | BG15: =N(BG14)*(1-Premissas!$D$21)+CA15 -> 18.245526 | BH15: =SUM(INDEX($CD$6:$CD$29,MAX(1,AY15-11)):INDEX($CD$6:$CD$29,AY15)) -> 5.5265792 | BI15: =BE15*Premissas!$C$13+BF15*Premissas!$F$13/12+BG15*Premissas!$C$14+BH15*Premissas!$F$14/12 -> 5977.6303 | BJ15: =BI15*12 -> 71731.564 | BK15: =IFERROR(BI15/BD15,0) -> 62.863915 | BL15: =BI15*Premissas!$C$30 -> 358.65782 | BM15: =BI15*Premissas!$C$28+CF15*Premissas!$C$29 -> 246.41964 | BN15: =BD15*Premissas!$C$31 -> 47.54421 | BO15: =BI15-BL15-BM15-BN15 -> 5325.0086 | BP15: =IFERROR(BO15/BI15,0) -> 0.89082268 | BQ15: =SUMPRODUCT(Premissas!$C$42:$C$61,--(Premissas!$D$42:$D$61<=AY15)) -> 3395 | BR15: =Premissas!$C$34*(1+Premissas!$C$35)^(AY15-1) -> 1957.1598 | BS15: =BA15*Premissas!$C$36*Premissas!$C$37 -> 88.246042 | BT15: =BL15+BM15+BN15+BQ15+BR15+BS15 -> 6093.0275 | BU15: =BI15-BT15 -> -115.39717 | BV15: =N(BV14)+BU15 -> -17060.226 | BW15: =IFERROR((BR15+BS15)/BA15,0) -> 139.07066 | BX15: =IFERROR(BQ15/(BO15/BD15),0) -> 60.624349 | BY15: =BA15*(1-Premissas!$D$23)*(1-Premissas!$D$24) -> 8.8246042 | BZ15: =BA15*(1-Premissas!$D$23)*Premissas!$D$24 -> 2.2061511 | CA15: =BA15*Premissas!$D$23*(1-Premissas!$D$24) -> 2.9415347 | CB15: =BA15*Premissas!$D$23*Premissas!$D$24 -> 0.73538368 | CC15: =BZ15+IF(AY15>12,INDEX($BZ$6:$BZ$29,AY15-12)*Premissas!$D$22,0) -> 2.2061511 | CD15: =CB15+IF(AY15>12,INDEX($CB$6:$CB$29,AY15-12)*Premissas!$D$22,0) -> 0.73538368 | CE15: =IF(AY15>12,(INDEX($BZ$6:$BZ$29,AY15-12)+INDEX($CB$6:$CB$29,AY15-12))*(1-Premissas!$D$22),0) -> 0 | CF15: =BE15+BG15+CC15+CD15 -> 75.923637 | CG15: =IF(BU15>0,AY15,"") | CH15: =BE15*Premissas!$C$13+BG15*Premissas!$C$14 -> 4773.0295 | CI15: =CC15*Premissas!$F$13+CD15*Premissas!$F$14 -> 1923.4549 | CJ15: =CH15+CI15 -> 6696.4843 | CK15: =CJ15*Premissas!$C$30 -> 401.78906 | CL15: =CJ15*Premissas!$C$28+CF15*Premissas!$C$29 -> 271.57953 | CM15: =BN15 -> 47.54421 | CN15: =BQ15 -> 3395 | CO15: =BR15+BS15 -> 2045.4058 | CP15: =CK15+CL15+CM15+CN15+CO15 -> 6161.3186 | CQ15: =CJ15-CP15 -> 535.16573 | CR15: =IF(AY15=1,Premissas!$C$8,N(CR14))+CQ15 -> -9370.2888 | CS15: =BF15*Premissas!$F$13/12+BH15*Premissas!$F$14/12 -> 1204.6008 | CT15: =N(CT14)+CI15-CS15 -> 8497.1687 | CV15: =CV14+1 -> 10 | CW15: =EDATE(Premissas!$C$7,CV15-1) -> 46569 | CX15: =Premissas!$E$19*(1+Premissas!$E$20)^(CV15-1) -> 41.596181 | CY15: =IFERROR(CX15/Premissas!$E$25,0) -> 138.65394 | CZ15: =(N(DB14)+N(DD14))*Premissas!$E$21+EB15 -> 4.2269802 | DA15: =DB15+DC15+DD15+DE15 -> 244.75899 | DB15: =N(DB14)*(1-Premissas!$E$21)+DV15 -> 107.7633 | DC15: =SUM(INDEX($DZ$6:$DZ$29,MAX(1,CV15-11)):INDEX($DZ$6:$DZ$29,CV15)) -> 51.33005 | DD15: =N(DD14)*(1-Premissas!$E$21)+DX15 -> 58.02639 | DE15: =SUM(INDEX($EA$6:$EA$29,MAX(1,CV15-11)):INDEX($EA$6:$EA$29,CV15)) -> 27.639258 | DF15: =DB15*Premissas!$C$13+DC15*Premissas!$F$13/12+DD15*Premissas!$C$14+DE15*Premissas!$F$14/12 -> 15809.816 | DG15: =DF15*12 -> 189717.79 | DH15: =IFERROR(DF15/DA15,0) -> 64.5934 | DI15: =DF15*Premissas!$C$30 -> 948.58893 | DJ15: =DF15*Premissas!$C$28+EC15*Premissas!$C$29 -> 640.69513 | DK15: =DA15*Premissas!$C$31 -> 122.3795 | DL15: =DF15-DI15-DJ15-DK15 -> 14098.152 | DM15: =IFERROR(DL15/DF15,0) -> 0.89173412 | DN15: =SUMPRODUCT(Premissas!$C$42:$C$61,--(Premissas!$D$42:$D$61<=CV15)) -> 3395 | DO15: =Premissas!$C$34*(1+Premissas!$C$35)^(CV15-1) -> 1957.1598 | DP15: =CX15*Premissas!$C$36*Premissas!$C$37 -> 249.57709 | DQ15: =DI15+DJ15+DK15+DN15+DO15+DP15 -> 7313.4004 | DR15: =DF15-DQ15 -> 8496.4151 | DS15: =N(DS14)+DR15 -> 20404.973 | DT15: =IFERROR((DO15+DP15)/CX15,0) -> 53.051429 | DU15: =IFERROR(DN15/(DL15/DA15),0) -> 58.94083 | DV15: =CX15*(1-Premissas!$E$23)*(1-Premissas!$E$24) -> 18.926263 | DW15: =CX15*(1-Premissas!$E$23)*Premissas!$E$24 -> 8.1112554 | DX15: =CX15*Premissas!$E$23*(1-Premissas!$E$24) -> 10.191064 | DY15: =CX15*Premissas!$E$23*Premissas!$E$24 -> 4.367599 | DZ15: =DW15+IF(CV15>12,INDEX($DW$6:$DW$29,CV15-12)*Premissas!$E$22,0) -> 8.1112554 | EA15: =DY15+IF(CV15>12,INDEX($DY$6:$DY$29,CV15-12)*Premissas!$E$22,0) -> 4.367599 | EB15: =IF(CV15>12,(INDEX($DW$6:$DW$29,CV15-12)+INDEX($DY$6:$DY$29,CV15-12))*(1-Premissas!$E$22),0) -> 0 | EC15: =DB15+DD15+DZ15+EA15 -> 178.26854 | ED15: =IF(DR15>0,CV15,"") -> 10 | EE15: =DB15*Premissas!$C$13+DD15*Premissas!$C$14 -> 11340.015 | EF15: =DZ15*Premissas!$F$13+EA15*Premissas!$F$14 -> 8475.9 | EG15: =EE15+EF15 -> 19815.914 | EH15: =EG15*Premissas!$C$30 -> 1188.9549 | EI15: =EG15*Premissas!$C$28+EC15*Premissas!$C$29 -> 780.90859 | EJ15: =DK15 -> 122.3795 | EK15: =DN15 -> 3395 | EL15: =DO15+DP15 -> 2206.7369 | EM15: =EH15+EI15+EJ15+EK15+EL15 -> 7693.9798 | EN15: =EG15-EM15 -> 12121.935 | EO15: =IF(CV15=1,Premissas!$C$8,N(EO14))+EN15 -> 50401.312 | EP15: =DC15*Premissas!$F$13/12+DE15*Premissas!$F$14/12 -> 4469.801 | EQ15: =N(EQ14)+EF15-EP15 -> 33145.126
B16: =B15+1 -> 11 | C16: =EDATE(Premissas!$C$7,B16-1) -> 46600 | D16: =Premissas!$C$19*(1+Premissas!$C$20)^(B16-1) -> 5.3756655 | E16: =IFERROR(D16/Premissas!$C$25,0) -> 53.756655 | F16: =(N(H15)+N(J15))*Premissas!$C$21+AH16 -> 2.3813095 | G16: =H16+I16+J16+K16 -> 37.346276 | H16: =N(H15)*(1-Premissas!$C$21)+AB16 -> 27.389684 | I16: =SUM(INDEX($AF$6:$AF$29,MAX(1,B16-11)):INDEX($AF$6:$AF$29,B16)) -> 4.3546505 | J16: =N(J15)*(1-Premissas!$C$21)+AD16 -> 4.8334737 | K16: =SUM(INDEX($AG$6:$AG$29,MAX(1,B16-11)):INDEX($AG$6:$AG$29,B16)) -> 0.76846774 | L16: =H16*Premissas!$C$13+I16*Premissas!$F$13/12+J16*Premissas!$C$14+K16*Premissas!$F$14/12 -> 2279.0778 | M16: =L16*12 -> 27348.934 | N16: =IFERROR(L16/G16,0) -> 61.025571 | O16: =L16*Premissas!$C$30 -> 136.74467 | P16: =L16*Premissas!$C$28+AI16*Premissas!$C$29 -> 95.820479 | Q16: =G16*Premissas!$C$31 -> 18.673138 | R16: =L16-O16-P16-Q16 -> 2027.8395 | S16: =IFERROR(R16/L16,0) -> 0.88976318 | T16: =SUMPRODUCT(Premissas!$C$42:$C$61,--(Premissas!$D$42:$D$61<=B16)) -> 3395 | U16: =Premissas!$C$34*(1+Premissas!$C$35)^(B16-1) -> 2015.8746 | V16: =D16*Premissas!$C$36*Premissas!$C$37 -> 32.253993 | W16: =O16+P16+Q16+T16+U16+V16 -> 5694.3668 | X16: =L16-W16 -> -3415.289 | Y16: =N(Y15)+X16 -> -36878.373 | Z16: =IFERROR((U16+V16)/D16,0) -> 381 | AA16: =IFERROR(T16/(R16/G16),0) -> 62.52497 | AB16: =D16*(1-Premissas!$C$23)*(1-Premissas!$C$24) -> 4.1123841 | AC16: =D16*(1-Premissas!$C$23)*Premissas!$C$24 -> 0.45693157 | AD16: =D16*Premissas!$C$23*(1-Premissas!$C$24) -> 0.72571484 | AE16: =D16*Premissas!$C$23*Premissas!$C$24 -> 0.080634983 | AF16: =AC16+IF(B16>12,INDEX($AC$6:$AC$29,B16-12)*Premissas!$C$22,0) -> 0.45693157 | AG16: =AE16+IF(B16>12,INDEX($AE$6:$AE$29,B16-12)*Premissas!$C$22,0) -> 0.080634983 | AH16: =IF(B16>12,(INDEX($AC$6:$AC$29,B16-12)+INDEX($AE$6:$AE$29,B16-12))*(1-Premissas!$C$22),0) -> 0 | AI16: =H16+J16+AF16+AG16 -> 32.760724 | AJ16: =IF(X16>0,B16,"") | AK16: =H16*Premissas!$C$13+J16*Premissas!$C$14 -> 2010.7251 | AL16: =AF16*Premissas!$F$13+AG16*Premissas!$F$14 -> 337.89767 | AM16: =AK16+AL16 -> 2348.6227 | AN16: =AM16*Premissas!$C$30 -> 140.91736 | AO16: =AM16*Premissas!$C$28+AI16*Premissas!$C$29 -> 98.25455 | AP16: =Q16 -> 18.673138 | AQ16: =T16 -> 3395 | AR16: =U16+V16 -> 2048.1286 | AS16: =AN16+AO16+AP16+AQ16+AR16 -> 5700.9736 | AT16: =AM16-AS16 -> -3352.3509 | AU16: =IF(B16=1,Premissas!$C$8,N(AU15))+AT16 -> -35349.558 | AV16: =I16*Premissas!$F$13/12+K16*Premissas!$F$14/12 -> 268.35278 | AW16: =N(AW15)+AL16-AV16 -> 1689.298 | AY16: =AY15+1 -> 11 | AZ16: =EDATE(Premissas!$C$7,AY16-1) -> 46600 | BA16: =Premissas!$D$19*(1+Premissas!$D$20)^(AY16-1) -> 15.737211 | BB16: =IFERROR(BA16/Premissas!$D$25,0) -> 78.686054 | BC16: =(N(BE15)+N(BG15))*Premissas!$D$21+CE16 -> 3.6491051 | BD16: =BE16+BF16+BG16+BH16 -> 107.17652 | BE16: =N(BE15)*(1-Premissas!$D$21)+BY16 -> 61.442074 | BF16: =SUM(INDEX($CC$6:$CC$29,MAX(1,AY16-11)):INDEX($CC$6:$CC$29,AY16)) -> 18.940319 | BG16: =N(BG15)*(1-Premissas!$D$21)+CA16 -> 20.480691 | BH16: =SUM(INDEX($CD$6:$CD$29,MAX(1,AY16-11)):INDEX($CD$6:$CD$29,AY16)) -> 6.3134397 | BI16: =BE16*Premissas!$C$13+BF16*Premissas!$F$13/12+BG16*Premissas!$C$14+BH16*Premissas!$F$14/12 -> 6733.8578 | BJ16: =BI16*12 -> 80806.293 | BK16: =IFERROR(BI16/BD16,0) -> 62.829596 | BL16: =BI16*Premissas!$C$30 -> 404.03147 | BM16: =BI16*Premissas!$C$28+CF16*Premissas!$C$29 -> 277.36942 | BN16: =BD16*Premissas!$C$31 -> 53.588262 | BO16: =BI16-BL16-BM16-BN16 -> 5998.8686 | BP16: =IFERROR(BO16/BI16,0) -> 0.8908517 | BQ16: =SUMPRODUCT(Premissas!$C$42:$C$61,--(Premissas!$D$42:$D$61<=AY16)) -> 3395 | BR16: =Premissas!$C$34*(1+Premissas!$C$35)^(AY16-1) -> 2015.8746 | BS16: =BA16*Premissas!$C$36*Premissas!$C$37 -> 94.423265 | BT16: =BL16+BM16+BN16+BQ16+BR16+BS16 -> 6240.287 | BU16: =BI16-BT16 -> 493.57079 | BV16: =N(BV15)+BU16 -> -16566.656 | BW16: =IFERROR((BR16+BS16)/BA16,0) -> 134.09605 | BX16: =IFERROR(BQ16/(BO16/BD16),0) -> 60.655488 | BY16: =BA16*(1-Premissas!$D$23)*(1-Premissas!$D$24) -> 9.4423265 | BZ16: =BA16*(1-Premissas!$D$23)*Premissas!$D$24 -> 2.3605816 | CA16: =BA16*Premissas!$D$23*(1-Premissas!$D$24) -> 3.1474422 | CB16: =BA16*Premissas!$D$23*Premissas!$D$24 -> 0.78686054 | CC16: =BZ16+IF(AY16>12,INDEX($BZ$6:$BZ$29,AY16-12)*Premissas!$D$22,0) -> 2.3605816 | CD16: =CB16+IF(AY16>12,INDEX($CB$6:$CB$29,AY16-12)*Premissas!$D$22,0) -> 0.78686054 | CE16: =IF(AY16>12,(INDEX($BZ$6:$BZ$29,AY16-12)+INDEX($CB$6:$CB$29,AY16-12))*(1-Premissas!$D$22),0) -> 0 | CF16: =BE16+BG16+CC16+CD16 -> 85.070208 | CG16: =IF(BU16>0,AY16,"") -> 11 | CH16: =BE16*Premissas!$C$13+BG16*Premissas!$C$14 -> 5357.7489 | CI16: =CC16*Premissas!$F$13+CD16*Premissas!$F$14 -> 2058.0967 | CJ16: =CH16+CI16 -> 7415.8456 | CK16: =CJ16*Premissas!$C$30 -> 444.95074 | CL16: =CJ16*Premissas!$C$28+CF16*Premissas!$C$29 -> 301.239 | CM16: =BN16 -> 53.588262 | CN16: =BQ16 -> 3395 | CO16: =BR16+BS16 -> 2110.2978 | CP16: =CK16+CL16+CM16+CN16+CO16 -> 6305.0758 | CQ16: =CJ16-CP16 -> 1110.7698 | CR16: =IF(AY16=1,Premissas!$C$8,N(CR15))+CQ16 -> -8259.519 | CS16: =BF16*Premissas!$F$13/12+BH16*Premissas!$F$14/12 -> 1376.1089 | CT16: =N(CT15)+CI16-CS16 -> 9179.1565 | CV16: =CV15+1 -> 11 | CW16: =EDATE(Premissas!$C$7,CV16-1) -> 46600 | CX16: =Premissas!$E$19*(1+Premissas!$E$20)^(CV16-1) -> 46.587723 | CY16: =IFERROR(CX16/Premissas!$E$25,0) -> 155.29241 | CZ16: =(N(DB15)+N(DD15))*Premissas!$E$21+EB16 -> 4.9736906 | DA16: =DB16+DC16+DD16+DE16 -> 286.37303 | DB16: =N(DB15)*(1-Premissas!$E$21)+DV16 -> 125.72781 | DC16: =SUM(INDEX($DZ$6:$DZ$29,MAX(1,CV16-11)):INDEX($DZ$6:$DZ$29,CV16)) -> 60.414656 | DD16: =N(DD15)*(1-Premissas!$E$21)+DX16 -> 67.69959 | DE16: =SUM(INDEX($EA$6:$EA$29,MAX(1,CV16-11)):INDEX($EA$6:$EA$29,CV16)) -> 32.530969 | DF16: =DB16*Premissas!$C$13+DC16*Premissas!$F$13/12+DD16*Premissas!$C$14+DE16*Premissas!$F$14/12 -> 18491.319 | DG16: =DF16*12 -> 221895.83 | DH16: =IFERROR(DF16/DA16,0) -> 64.570744 | DI16: =DF16*Premissas!$C$30 -> 1109.4792 | DJ16: =DF16*Premissas!$C$28+EC16*Premissas!$C$29 -> 748.824 | DK16: =DA16*Premissas!$C$31 -> 143.18651 | DL16: =DF16-DI16-DJ16-DK16 -> 16489.83 | DM16: =IFERROR(DL16/DF16,0) -> 0.89176058 | DN16: =SUMPRODUCT(Premissas!$C$42:$C$61,--(Premissas!$D$42:$D$61<=CV16)) -> 3395 | DO16: =Premissas!$C$34*(1+Premissas!$C$35)^(CV16-1) -> 2015.8746 | DP16: =CX16*Premissas!$C$36*Premissas!$C$37 -> 279.52634 | DQ16: =DI16+DJ16+DK16+DN16+DO16+DP16 -> 7691.8906 | DR16: =DF16-DQ16 -> 10799.429 | DS16: =N(DS15)+DR16 -> 31204.402 | DT16: =IFERROR((DO16+DP16)/CX16,0) -> 49.270511 | DU16: =IFERROR(DN16/(DL16/DA16),0) -> 58.959762 | DV16: =CX16*(1-Premissas!$E$23)*(1-Premissas!$E$24) -> 21.197414 | DW16: =CX16*(1-Premissas!$E$23)*Premissas!$E$24 -> 9.084606 | DX16: =CX16*Premissas!$E$23*(1-Premissas!$E$24) -> 11.413992 | DY16: =CX16*Premissas!$E$23*Premissas!$E$24 -> 4.8917109 | DZ16: =DW16+IF(CV16>12,INDEX($DW$6:$DW$29,CV16-12)*Premissas!$E$22,0) -> 9.084606 | EA16: =DY16+IF(CV16>12,INDEX($DY$6:$DY$29,CV16-12)*Premissas!$E$22,0) -> 4.8917109 | EB16: =IF(CV16>12,(INDEX($DW$6:$DW$29,CV16-12)+INDEX($DY$6:$DY$29,CV16-12))*(1-Premissas!$E$22),0) -> 0 | EC16: =DB16+DD16+DZ16+EA16 -> 207.40372 | ED16: =IF(DR16>0,CV16,"") -> 11 | EE16: =DB16*Premissas!$C$13+DD16*Premissas!$C$14 -> 13230.434 | EF16: =DZ16*Premissas!$F$13+EA16*Premissas!$F$14 -> 9493.008 | EG16: =EE16+EF16 -> 22723.442 | EH16: =EG16*Premissas!$C$30 -> 1363.4065 | EI16: =EG16*Premissas!$C$28+EC16*Premissas!$C$29 -> 896.9483 | EJ16: =DK16 -> 143.18651 | EK16: =DN16 -> 3395 | EL16: =DO16+DP16 -> 2295.4009 | EM16: =EH16+EI16+EJ16+EK16+EL16 -> 8093.9423 | EN16: =EG16-EM16 -> 14629.5 | EO16: =IF(CV16=1,Premissas!$C$8,N(EO15))+EN16 -> 65030.812 | EP16: =DC16*Premissas!$F$13/12+DE16*Premissas!$F$14/12 -> 5260.885 | EQ16: =N(EQ15)+EF16-EP16 -> 37377.249
B17: =B16+1 -> 12 | C17: =EDATE(Premissas!$C$7,B17-1) -> 46631 | D17: =Premissas!$C$19*(1+Premissas!$C$20)^(B17-1) -> 5.5369355 | E17: =IFERROR(D17/Premissas!$C$25,0) -> 55.369355 | F17: =(N(H16)+N(J16))*Premissas!$C$21+AH17 -> 2.5778526 | G17: =H17+I17+J17+K17 -> 40.305359 | H17: =N(H16)*(1-Premissas!$C$21)+AB17 -> 29.434265 | I17: =SUM(INDEX($AF$6:$AF$29,MAX(1,B17-11)):INDEX($AF$6:$AF$29,B17)) -> 4.8252901 | J17: =N(J16)*(1-Premissas!$C$21)+AD17 -> 5.1942821 | K17: =SUM(INDEX($AG$6:$AG$29,MAX(1,B17-11)):INDEX($AG$6:$AG$29,B17)) -> 0.85152177 | L17: =H17*Premissas!$C$13+I17*Premissas!$F$13/12+J17*Premissas!$C$14+K17*Premissas!$F$14/12 -> 2458.177 | M17: =L17*12 -> 29498.124 | N17: =IFERROR(L17/G17,0) -> 60.988838 | O17: =L17*Premissas!$C$30 -> 147.49062 | P17: =L17*Premissas!$C$28+AI17*Premissas!$C$29 -> 103.27549 | Q17: =G17*Premissas!$C$31 -> 20.15268 | R17: =L17-O17-P17-Q17 -> 2187.2582 | S17: =IFERROR(R17/L17,0) -> 0.88978874 | T17: =SUMPRODUCT(Premissas!$C$42:$C$61,--(Premissas!$D$42:$D$61<=B17)) -> 3395 | U17: =Premissas!$C$34*(1+Premissas!$C$35)^(B17-1) -> 2076.3508 | V17: =D17*Premissas!$C$36*Premissas!$C$37 -> 33.221613 | W17: =O17+P17+Q17+T17+U17+V17 -> 5775.4912 | X17: =L17-W17 -> -3317.3142 | Y17: =N(Y16)+X17 -> -40195.687 | Z17: =IFERROR((U17+V17)/D17,0) -> 381 | AA17: =IFERROR(T17/(R17/G17),0) -> 62.560832 | AB17: =D17*(1-Premissas!$C$23)*(1-Premissas!$C$24) -> 4.2357556 | AC17: =D17*(1-Premissas!$C$23)*Premissas!$C$24 -> 0.47063952 | AD17: =D17*Premissas!$C$23*(1-Premissas!$C$24) -> 0.74748629 | AE17: =D17*Premissas!$C$23*Premissas!$C$24 -> 0.083054032 | AF17: =AC17+IF(B17>12,INDEX($AC$6:$AC$29,B17-12)*Premissas!$C$22,0) -> 0.47063952 | AG17: =AE17+IF(B17>12,INDEX($AE$6:$AE$29,B17-12)*Premissas!$C$22,0) -> 0.083054032 | AH17: =IF(B17>12,(INDEX($AC$6:$AC$29,B17-12)+INDEX($AE$6:$AE$29,B17-12))*(1-Premissas!$C$22),0) -> 0 | AI17: =H17+J17+AF17+AG17 -> 35.182241 | AJ17: =IF(X17>0,B17,"") | AK17: =H17*Premissas!$C$13+J17*Premissas!$C$14 -> 2160.8213 | AL17: =AF17*Premissas!$F$13+AG17*Premissas!$F$14 -> 348.0346 | AM17: =AK17+AL17 -> 2508.8559 | AN17: =AM17*Premissas!$C$30 -> 150.53136 | AO17: =AM17*Premissas!$C$28+AI17*Premissas!$C$29 -> 105.04926 | AP17: =Q17 -> 20.15268 | AQ17: =T17 -> 3395 | AR17: =U17+V17 -> 2109.5724 | AS17: =AN17+AO17+AP17+AQ17+AR17 -> 5780.3057 | AT17: =AM17-AS17 -> -3271.4498 | AU17: =IF(B17=1,Premissas!$C$8,N(AU16))+AT17 -> -38621.008 | AV17: =I17*Premissas!$F$13/12+K17*Premissas!$F$14/12 -> 297.35566 | AW17: =N(AW16)+AL17-AV17 -> 1739.9769 | AY17: =AY16+1 -> 12 | AZ17: =EDATE(Premissas!$C$7,AY17-1) -> 46631 | BA17: =Premissas!$D$19*(1+Premissas!$D$20)^(AY17-1) -> 16.838816 | BB17: =IFERROR(BA17/Premissas!$D$25,0) -> 84.194078 | BC17: =(N(BE16)+N(BG16))*Premissas!$D$21+CE17 -> 4.0961383 | BD17: =BE17+BF17+BG17+BH17 -> 119.9192 | BE17: =N(BE16)*(1-Premissas!$D$21)+BY17 -> 68.47326 | BF17: =SUM(INDEX($CC$6:$CC$29,MAX(1,AY17-11)):INDEX($CC$6:$CC$29,AY17)) -> 21.466142 | BG17: =N(BG16)*(1-Premissas!$D$21)+CA17 -> 22.82442 | BH17: =SUM(INDEX($CD$6:$CD$29,MAX(1,AY17-11)):INDEX($CD$6:$CD$29,AY17)) -> 7.1553805 | BI17: =BE17*Premissas!$C$13+BF17*Premissas!$F$13/12+BG17*Premissas!$C$14+BH17*Premissas!$F$14/12 -> 7530.4908 | BJ17: =BI17*12 -> 90365.889 | BK17: =IFERROR(BI17/BD17,0) -> 62.796372 | BL17: =BI17*Premissas!$C$30 -> 451.82945 | BM17: =BI17*Premissas!$C$28+CF17*Premissas!$C$29 -> 309.95324 | BN17: =BD17*Premissas!$C$31 -> 59.959601 | BO17: =BI17-BL17-BM17-BN17 -> 6708.7485 | BP17: =IFERROR(BO17/BI17,0) -> 0.89087799 | BQ17: =SUMPRODUCT(Premissas!$C$42:$C$61,--(Premissas!$D$42:$D$61<=AY17)) -> 3395 | BR17: =Premissas!$C$34*(1+Premissas!$C$35)^(AY17-1) -> 2076.3508 | BS17: =BA17*Premissas!$C$36*Premissas!$C$37 -> 101.03289 | BT17: =BL17+BM17+BN17+BQ17+BR17+BS17 -> 6394.126 | BU17: =BI17-BT17 -> 1136.3648 | BV17: =N(BV16)+BU17 -> -15430.291 | BW17: =IFERROR((BR17+BS17)/BA17,0) -> 129.30741 | BX17: =IFERROR(BQ17/(BO17/BD17),0) -> 60.685788 | BY17: =BA17*(1-Premissas!$D$23)*(1-Premissas!$D$24) -> 10.103289 | BZ17: =BA17*(1-Premissas!$D$23)*Premissas!$D$24 -> 2.5258223 | CA17: =BA17*Premissas!$D$23*(1-Premissas!$D$24) -> 3.3677631 | CB17: =BA17*Premissas!$D$23*Premissas!$D$24 -> 0.84194078 | CC17: =BZ17+IF(AY17>12,INDEX($BZ$6:$BZ$29,AY17-12)*Premissas!$D$22,0) -> 2.5258223 | CD17: =CB17+IF(AY17>12,INDEX($CB$6:$CB$29,AY17-12)*Premissas!$D$22,0) -> 0.84194078 | CE17: =IF(AY17>12,(INDEX($BZ$6:$BZ$29,AY17-12)+INDEX($CB$6:$CB$29,AY17-12))*(1-Premissas!$D$22),0) -> 0 | CF17: =BE17+BG17+CC17+CD17 -> 94.665443 | CG17: =IF(BU17>0,AY17,"") -> 12 | CH17: =BE17*Premissas!$C$13+BG17*Premissas!$C$14 -> 5970.8683 | CI17: =CC17*Premissas!$F$13+CD17*Premissas!$F$14 -> 2202.1635 | CJ17: =CH17+CI17 -> 8173.0317 | CK17: =CJ17*Premissas!$C$30 -> 490.3819 | CL17: =CJ17*Premissas!$C$28+CF17*Premissas!$C$29 -> 332.44218 | CM17: =BN17 -> 59.959601 | CN17: =BQ17 -> 3395 | CO17: =BR17+BS17 -> 2177.3837 | CP17: =CK17+CL17+CM17+CN17+CO17 -> 6455.1674 | CQ17: =CJ17-CP17 -> 1717.8644 | CR17: =IF(AY17=1,Premissas!$C$8,N(CR16))+CQ17 -> -6541.6546 | CS17: =BF17*Premissas!$F$13/12+BH17*Premissas!$F$14/12 -> 1559.6225 | CT17: =N(CT16)+CI17-CS17 -> 9821.6975 | CV17: =CV16+1 -> 12 | CW17: =EDATE(Premissas!$C$7,CV17-1) -> 46631 | CX17: =Premissas!$E$19*(1+Premissas!$E$20)^(CV17-1) -> 52.17825 | CY17: =IFERROR(CX17/Premissas!$E$25,0) -> 173.9275 | CZ17: =(N(DB16)+N(DD16))*Premissas!$E$21+EB17 -> 5.802822 | DA17: =DB17+DC17+DD17+DE17 -> 332.74845 | DB17: =N(DB16)*(1-Premissas!$E$21)+DV17 -> 145.69708 | DC17: =SUM(INDEX($DZ$6:$DZ$29,MAX(1,CV17-11)):INDEX($DZ$6:$DZ$29,CV17)) -> 70.589415 | DD17: =N(DD16)*(1-Premissas!$E$21)+DX17 -> 78.452274 | DE17: =SUM(INDEX($EA$6:$EA$29,MAX(1,CV17-11)):INDEX($EA$6:$EA$29,CV17)) -> 38.009685 | DF17: =DB17*Premissas!$C$13+DC17*Premissas!$F$13/12+DD17*Premissas!$C$14+DE17*Premissas!$F$14/12 -> 21478.715 | DG17: =DF17*12 -> 257744.58 | DH17: =IFERROR(DF17/DA17,0) -> 64.549406 | DI17: =DF17*Premissas!$C$30 -> 1288.7229 | DJ17: =DF17*Premissas!$C$28+EC17*Premissas!$C$29 -> 869.25841 | DK17: =DA17*Premissas!$C$31 -> 166.37423 | DL17: =DF17-DI17-DJ17-DK17 -> 19154.359 | DM17: =IFERROR(DL17/DF17,0) -> 0.89178331 | DN17: =SUMPRODUCT(Premissas!$C$42:$C$61,--(Premissas!$D$42:$D$61<=CV17)) -> 3395 | DO17: =Premissas!$C$34*(1+Premissas!$C$35)^(CV17-1) -> 2076.3508 | DP17: =CX17*Premissas!$C$36*Premissas!$C$37 -> 313.0695 | DQ17: =DI17+DJ17+DK17+DN17+DO17+DP17 -> 8108.7758 | DR17: =DF17-DQ17 -> 13369.939 | DS17: =N(DS16)+DR17 -> 44574.341 | DT17: =IFERROR((DO17+DP17)/CX17,0) -> 45.793416 | DU17: =IFERROR(DN17/(DL17/DA17),0) -> 58.977749 | DV17: =CX17*(1-Premissas!$E$23)*(1-Premissas!$E$24) -> 23.741104 | DW17: =CX17*(1-Premissas!$E$23)*Premissas!$E$24 -> 10.174759 | DX17: =CX17*Premissas!$E$23*(1-Premissas!$E$24) -> 12.783671 | DY17: =CX17*Premissas!$E$23*Premissas!$E$24 -> 5.4787162 | DZ17: =DW17+IF(CV17>12,INDEX($DW$6:$DW$29,CV17-12)*Premissas!$E$22,0) -> 10.174759 | EA17: =DY17+IF(CV17>12,INDEX($DY$6:$DY$29,CV17-12)*Premissas!$E$22,0) -> 5.4787162 | EB17: =IF(CV17>12,(INDEX($DW$6:$DW$29,CV17-12)+INDEX($DY$6:$DY$29,CV17-12))*(1-Premissas!$E$22),0) -> 0 | EC17: =DB17+DD17+DZ17+EA17 -> 239.80283 | ED17: =IF(DR17>0,CV17,"") -> 12 | EE17: =DB17*Premissas!$C$13+DD17*Premissas!$C$14 -> 15331.816 | EF17: =DZ17*Premissas!$F$13+EA17*Premissas!$F$14 -> 10632.169 | EG17: =EE17+EF17 -> 25963.985 | EH17: =EG17*Premissas!$C$30 -> 1557.8391 | EI17: =EG17*Premissas!$C$28+EC17*Premissas!$C$29 -> 1026.2429 | EJ17: =DK17 -> 166.37423 | EK17: =DN17 -> 3395 | EL17: =DO17+DP17 -> 2389.4203 | EM17: =EH17+EI17+EJ17+EK17+EL17 -> 8534.8765 | EN17: =EG17-EM17 -> 17429.108 | EO17: =IF(CV17=1,Premissas!$C$8,N(EO16))+EN17 -> 82459.92 | EP17: =DC17*Premissas!$F$13/12+DE17*Premissas!$F$14/12 -> 6146.8991 | EQ17: =N(EQ16)+EF17-EP17 -> 41862.518
B18: =B17+1 -> 13 | C18: =EDATE(Premissas!$C$7,B18-1) -> 46661 | D18: =Premissas!$C$19*(1+Premissas!$C$20)^(B18-1) -> 5.7030435 | E18: =IFERROR(D18/Premissas!$C$25,0) -> 57.030435 | F18: =(N(H17)+N(J17))*Premissas!$C$21+AH18 -> 2.9702838 | G18: =H18+I18+J18+K18 -> 43.038119 | H18: =N(H17)*(1-Premissas!$C$21)+AB18 -> 31.442352 | I18: =SUM(INDEX($AF$6:$AF$29,MAX(1,B18-11)):INDEX($AF$6:$AF$29,B18)) -> 5.1400488 | J18: =N(J17)*(1-Premissas!$C$21)+AD18 -> 5.5486504 | K18: =SUM(INDEX($AG$6:$AG$29,MAX(1,B18-11)):INDEX($AG$6:$AG$29,B18)) -> 0.90706743 | L18: =H18*Premissas!$C$13+I18*Premissas!$F$13/12+J18*Premissas!$C$14+K18*Premissas!$F$14/12 -> 2624.991 | M18: =L18*12 -> 31499.893 | N18: =IFERROR(L18/G18,0) -> 60.992235 | O18: =L18*Premissas!$C$30 -> 157.49946 | P18: =L18*Premissas!$C$28+AI18*Premissas!$C$29 -> 110.37773 | Q18: =G18*Premissas!$C$31 -> 21.519059 | R18: =L18-O18-P18-Q18 -> 2335.5948 | S18: =IFERROR(R18/L18,0) -> 0.88975343 | T18: =SUMPRODUCT(Premissas!$C$42:$C$61,--(Premissas!$D$42:$D$61<=B18)) -> 3395 | U18: =Premissas!$C$34*(1+Premissas!$C$35)^(B18-1) -> 2138.6413 | V18: =D18*Premissas!$C$36*Premissas!$C$37 -> 34.218261 | W18: =O18+P18+Q18+T18+U18+V18 -> 5857.2558 | X18: =L18-W18 -> -3232.2648 | Y18: =N(Y17)+X18 -> -43427.952 | Z18: =IFERROR((U18+V18)/D18,0) -> 381 | AA18: =IFERROR(T18/(R18/G18),0) -> 62.55983 | AB18: =D18*(1-Premissas!$C$23)*(1-Premissas!$C$24) -> 4.3628283 | AC18: =D18*(1-Premissas!$C$23)*Premissas!$C$24 -> 0.4847587 | AD18: =D18*Premissas!$C$23*(1-Premissas!$C$24) -> 0.76991088 | AE18: =D18*Premissas!$C$23*Premissas!$C$24 -> 0.085545653 | AF18: =AC18+IF(B18>12,INDEX($AC$6:$AC$29,B18-12)*Premissas!$C$22,0) -> 0.6547587 | AG18: =AE18+IF(B18>12,INDEX($AE$6:$AE$29,B18-12)*Premissas!$C$22,0) -> 0.11554565 | AH18: =IF(B18>12,(INDEX($AC$6:$AC$29,B18-12)+INDEX($AE$6:$AE$29,B18-12))*(1-Premissas!$C$22),0) -> 0.2 | AI18: =H18+J18+AF18+AG18 -> 37.761307 | AJ18: =IF(X18>0,B18,"") | AK18: =H18*Premissas!$C$13+J18*Premissas!$C$14 -> 2308.2386 | AL18: =AF18*Premissas!$F$13+AG18*Premissas!$F$14 -> 484.18944 | AM18: =AK18+AL18 -> 2792.428 | AN18: =AM18*Premissas!$C$30 -> 167.54568 | AO18: =AM18*Premissas!$C$28+AI18*Premissas!$C$29 -> 116.23802 | AP18: =Q18 -> 21.519059 | AQ18: =T18 -> 3395 | AR18: =U18+V18 -> 2172.8596 | AS18: =AN18+AO18+AP18+AQ18+AR18 -> 5873.1624 | AT18: =AM18-AS18 -> -3080.7343 | AU18: =IF(B18=1,Premissas!$C$8,N(AU17))+AT18 -> -41701.742 | AV18: =I18*Premissas!$F$13/12+K18*Premissas!$F$14/12 -> 316.75248 | AW18: =N(AW17)+AL18-AV18 -> 1907.4139 | AY18: =AY17+1 -> 13 | AZ18: =EDATE(Premissas!$C$7,AY18-1) -> 46661 | BA18: =Premissas!$D$19*(1+Premissas!$D$20)^(AY18-1) -> 18.017533 | BB18: =IFERROR(BA18/Premissas!$D$25,0) -> 90.087664 | BC18: =(N(BE17)+N(BG17))*Premissas!$D$21+CE18 -> 5.124884 | BD18: =BE18+BF18+BG18+BH18 -> 132.81185 | BE18: =N(BE17)*(1-Premissas!$D$21)+BY18 -> 75.860117 | BF18: =SUM(INDEX($CC$6:$CC$29,MAX(1,AY18-11)):INDEX($CC$6:$CC$29,AY18)) -> 23.748771 | BG18: =N(BG17)*(1-Premissas!$D$21)+CA18 -> 25.286706 | BH18: =SUM(INDEX($CD$6:$CD$29,MAX(1,AY18-11)):INDEX($CD$6:$CD$29,AY18)) -> 7.9162571 | BI18: =BE18*Premissas!$C$13+BF18*Premissas!$F$13/12+BG18*Premissas!$C$14+BH18*Premissas!$F$14/12 -> 8340.4692 | BJ18: =BI18*12 -> 100085.63 | BK18: =IFERROR(BI18/BD18,0) -> 62.799134 | BL18: =BI18*Premissas!$C$30 -> 500.42815 | BM18: =BI18*Premissas!$C$28+CF18*Premissas!$C$29 -> 343.75368 | BN18: =BD18*Premissas!$C$31 -> 66.405925 | BO18: =BI18-BL18-BM18-BN18 -> 7429.8814 | BP18: =IFERROR(BO18/BI18,0) -> 0.89082296 | BQ18: =SUMPRODUCT(Premissas!$C$42:$C$61,--(Premissas!$D$42:$D$61<=AY18)) -> 3395 | BR18: =Premissas!$C$34*(1+Premissas!$C$35)^(AY18-1) -> 2138.6413 | BS18: =BA18*Premissas!$C$36*Premissas!$C$37 -> 108.1052 | BT18: =BL18+BM18+BN18+BQ18+BR18+BS18 -> 6552.3343 | BU18: =BI18-BT18 -> 1788.1349 | BV18: =N(BV17)+BU18 -> -13642.156 | BW18: =IFERROR((BR18+BS18)/BA18,0) -> 124.69779 | BX18: =IFERROR(BQ18/(BO18/BD18),0) -> 60.686868 | BY18: =BA18*(1-Premissas!$D$23)*(1-Premissas!$D$24) -> 10.81052 | BZ18: =BA18*(1-Premissas!$D$23)*Premissas!$D$24 -> 2.7026299 | CA18: =BA18*Premissas!$D$23*(1-Premissas!$D$24) -> 3.6035065 | CB18: =BA18*Premissas!$D$23*Premissas!$D$24 -> 0.90087664 | CC18: =BZ18+IF(AY18>12,INDEX($BZ$6:$BZ$29,AY18-12)*Premissas!$D$22,0) -> 3.4826299 | CD18: =CB18+IF(AY18>12,INDEX($CB$6:$CB$29,AY18-12)*Premissas!$D$22,0) -> 1.1608766 | CE18: =IF(AY18>12,(INDEX($BZ$6:$BZ$29,AY18-12)+INDEX($CB$6:$CB$29,AY18-12))*(1-Premissas!$D$22),0) -> 0.56 | CF18: =BE18+BG18+CC18+CD18 -> 105.79033 | CG18: =IF(BU18>0,AY18,"") -> 13 | CH18: =BE18*Premissas!$C$13+BG18*Premissas!$C$14 -> 6615.0022 | CI18: =CC18*Premissas!$F$13+CD18*Premissas!$F$14 -> 3036.3657 | CJ18: =CH18+CI18 -> 9651.3679 | CK18: =CJ18*Premissas!$C$30 -> 579.08207 | CL18: =CJ18*Premissas!$C$28+CF18*Premissas!$C$29 -> 389.63514 | CM18: =BN18 -> 66.405925 | CN18: =BQ18 -> 3395 | CO18: =BR18+BS18 -> 2246.7465 | CP18: =CK18+CL18+CM18+CN18+CO18 -> 6676.8697 | CQ18: =CJ18-CP18 -> 2974.4982 | CR18: =IF(AY18=1,Premissas!$C$8,N(CR17))+CQ18 -> -3567.1564 | CS18: =BF18*Premissas!$F$13/12+BH18*Premissas!$F$14/12 -> 1725.467 | CT18: =N(CT17)+CI18-CS18 -> 11132.596 | CV18: =CV17+1 -> 13 | CW18: =EDATE(Premissas!$C$7,CV18-1) -> 46661 | CX18: =Premissas!$E$19*(1+Premissas!$E$20)^(CV18-1) -> 58.43964 | CY18: =IFERROR(CX18/Premissas!$E$25,0) -> 194.7988 | CZ18: =(N(DB17)+N(DD17))*Premissas!$E$21+EB18 -> 7.6244806 | DA18: =DB18+DC18+DD18+DE18 -> 383.56361 | DB18: =N(DB17)*(1-Premissas!$E$21)+DV18 -> 167.9162 | DC18: =SUM(INDEX($DZ$6:$DZ$29,MAX(1,CV18-11)):INDEX($DZ$6:$DZ$29,CV18)) -> 81.400145 | DD18: =N(DD17)*(1-Premissas!$E$21)+DX18 -> 90.416418 | DE18: =SUM(INDEX($EA$6:$EA$29,MAX(1,CV18-11)):INDEX($EA$6:$EA$29,CV18)) -> 43.830847 | DF18: =DB18*Premissas!$C$13+DC18*Premissas!$F$13/12+DD18*Premissas!$C$14+DE18*Premissas!$F$14/12 -> 24758.245 | DG18: =DF18*12 -> 297098.94 | DH18: =IFERROR(DF18/DA18,0) -> 64.547949 | DI18: =DF18*Premissas!$C$30 -> 1485.4947 | DJ18: =DF18*Premissas!$C$28+EC18*Premissas!$C$29 -> 1003.4762 | DK18: =DA18*Premissas!$C$31 -> 191.78181 | DL18: =DF18-DI18-DJ18-DK18 -> 22077.492 | DM18: =IFERROR(DL18/DF18,0) -> 0.89172283 | DN18: =SUMPRODUCT(Premissas!$C$42:$C$61,--(Premissas!$D$42:$D$61<=CV18)) -> 3395 | DO18: =Premissas!$C$34*(1+Premissas!$C$35)^(CV18-1) -> 2138.6413 | DP18: =CX18*Premissas!$C$36*Premissas!$C$37 -> 350.63784 | DQ18: =DI18+DJ18+DK18+DN18+DO18+DP18 -> 8565.0318 | DR18: =DF18-DQ18 -> 16193.213 | DS18: =N(DS17)+DR18 -> 60767.554 | DT18: =IFERROR((DO18+DP18)/CX18,0) -> 42.595731 | DU18: =IFERROR(DN18/(DL18/DA18),0) -> 58.98308 | DV18: =CX18*(1-Premissas!$E$23)*(1-Premissas!$E$24) -> 26.590036 | DW18: =CX18*(1-Premissas!$E$23)*Premissas!$E$24 -> 11.39573 | DX18: =CX18*Premissas!$E$23*(1-Premissas!$E$24) -> 14.317712 | DY18: =CX18*Premissas!$E$23*Premissas!$E$24 -> 6.1361622 | DZ18: =DW18+IF(CV18>12,INDEX($DW$6:$DW$29,CV18-12)*Premissas!$E$22,0) -> 13.73573 | EA18: =DY18+IF(CV18>12,INDEX($DY$6:$DY$29,CV18-12)*Premissas!$E$22,0) -> 7.3961622 | EB18: =IF(CV18>12,(INDEX($DW$6:$DW$29,CV18-12)+INDEX($DY$6:$DY$29,CV18-12))*(1-Premissas!$E$22),0) -> 0.9 | EC18: =DB18+DD18+DZ18+EA18 -> 279.46451 | ED18: =IF(DR18>0,CV18,"") -> 13 | EE18: =DB18*Premissas!$C$13+DD18*Premissas!$C$14 -> 17669.951 | EF18: =DZ18*Premissas!$F$13+EA18*Premissas!$F$14 -> 14353.225 | EG18: =EE18+EF18 -> 32023.176 | EH18: =EG18*Premissas!$C$30 -> 1921.3906 | EI18: =EG18*Premissas!$C$28+EC18*Premissas!$C$29 -> 1257.7488 | EJ18: =DK18 -> 191.78181 | EK18: =DN18 -> 3395 | EL18: =DO18+DP18 -> 2489.2792 | EM18: =EH18+EI18+EJ18+EK18+EL18 -> 9255.2003 | EN18: =EG18-EM18 -> 22767.976 | EO18: =IF(CV18=1,Premissas!$C$8,N(EO17))+EN18 -> 105227.9 | EP18: =DC18*Premissas!$F$13/12+DE18*Premissas!$F$14/12 -> 7088.2933 | EQ18: =N(EQ17)+EF18-EP18 -> 49127.45
... B29: =B28+1 -> 24 | C29: =EDATE(Premissas!$C$7,B29-1) -> 46997 | D29: =Premissas!$C$19*(1+Premissas!$C$20)^(B29-1) -> 7.894346 | E29: =IFERROR(D29/Premissas!$C$25,0) -> 78.94346 | F29: =(N(H28)+N(J28))*Premissas!$C$21+AH29 -> 5.0593572 | G29: =H29+I29+J29+K29 -> 73.035963 | H29: =N(H28)*(1-Premissas!$C$21)+AB29 -> 52.788214 | I29: =SUM(INDEX($AF$6:$AF$29,MAX(1,B29-11)):INDEX($AF$6:$AF$29,B29)) -> 9.2923548 | J29: =N(J28)*(1-Premissas!$C$21)+AD29 -> 9.3155672 | K29: =SUM(INDEX($AG$6:$AG$29,MAX(1,B29-11)):INDEX($AG$6:$AG$29,B29)) -> 1.6398273 | L29: =H29*Premissas!$C$13+I29*Premissas!$F$13/12+J29*Premissas!$C$14+K29*Premissas!$F$14/12 -> 4447.9118 | M29: =L29*12 -> 53374.942 | N29: =IFERROR(L29/G29,0) -> 60.900297 | O29: =L29*Premissas!$C$30 -> 266.87471 | P29: =L29*Premissas!$C$28+AI29*Premissas!$C$29 -> 186.63025 | Q29: =G29*Premissas!$C$31 -> 36.517982 | R29: =L29-O29-P29-Q29 -> 3957.8889 | S29: =IFERROR(R29/L29,0) -> 0.88983079 | T29: =SUMPRODUCT(Premissas!$C$42:$C$61,--(Premissas!$D$42:$D$61<=B29)) -> 3395 | U29: =Premissas!$C$34*(1+Premissas!$C$35)^(B29-1) -> 2960.3798 | V29: =D29*Premissas!$C$36*Premissas!$C$37 -> 47.366076 | W29: =O29+P29+Q29+T29+U29+V29 -> 6892.7688 | X29: =L29-W29 -> -2444.8569 | Y29: =N(Y28)+X29 -> -74078.754 | Z29: =IFERROR((U29+V29)/D29,0) -> 381 | AA29: =IFERROR(T29/(R29/G29),0) -> 62.648827 | AB29: =D29*(1-Premissas!$C$23)*(1-Premissas!$C$24) -> 6.0391747 | AC29: =D29*(1-Premissas!$C$23)*Premissas!$C$24 -> 0.67101941 | AD29: =D29*Premissas!$C$23*(1-Premissas!$C$24) -> 1.0657367 | AE29: =D29*Premissas!$C$23*Premissas!$C$24 -> 0.11841519 | AF29: =AC29+IF(B29>12,INDEX($AC$6:$AC$29,B29-12)*Premissas!$C$22,0) -> 0.90633917 | AG29: =AE29+IF(B29>12,INDEX($AE$6:$AE$29,B29-12)*Premissas!$C$22,0) -> 0.15994221 | AH29: =IF(B29>12,(INDEX($AC$6:$AC$29,B29-12)+INDEX($AE$6:$AE$29,B29-12))*(1-Premissas!$C$22),0) -> 0.27684677 | AI29: =H29+J29+AF29+AG29 -> 63.170062 | AJ29: =IF(X29>0,B29,"") | AK29: =H29*Premissas!$C$13+J29*Premissas!$C$14 -> 3875.2759 | AL29: =AF29*Premissas!$F$13+AG29*Premissas!$F$14 -> 670.23142 | AM29: =AK29+AL29 -> 4545.5074 | AN29: =AM29*Premissas!$C$30 -> 272.73044 | AO29: =AM29*Premissas!$C$28+AI29*Premissas!$C$29 -> 190.04609 | AP29: =Q29 -> 36.517982 | AQ29: =T29 -> 3395 | AR29: =U29+V29 -> 3007.7458 | AS29: =AN29+AO29+AP29+AQ29+AR29 -> 6902.0404 | AT29: =AM29-AS29 -> -2356.533 | AU29: =IF(B29=1,Premissas!$C$8,N(AU28))+AT29 -> -71046.299 | AV29: =I29*Premissas!$F$13/12+K29*Premissas!$F$14/12 -> 572.6359 | AW29: =N(AW28)+AL29-AV29 -> 3350.7795 | AY29: =AY28+1 -> 24 | AZ29: =EDATE(Premissas!$C$7,AY29-1) -> 46997 | BA29: =Premissas!$D$19*(1+Premissas!$D$20)^(AY29-1) -> 37.924239 | BB29: =IFERROR(BA29/Premissas!$D$25,0) -> 189.62119 | BC29: =(N(BE28)+N(BG28))*Premissas!$D$21+CE29 -> 13.000512 | BD29: =BE29+BF29+BG29+BH29 -> 338.01863 | BE29: =N(BE28)*(1-Premissas!$D$21)+BY29 -> 191.21512 | BF29: =SUM(INDEX($CC$6:$CC$29,MAX(1,AY29-11)):INDEX($CC$6:$CC$29,AY29)) -> 62.298855 | BG29: =N(BG28)*(1-Premissas!$D$21)+CA29 -> 63.738372 | BH29: =SUM(INDEX($CD$6:$CD$29,MAX(1,AY29-11)):INDEX($CD$6:$CD$29,AY29)) -> 20.766285 | BI29: =BE29*Premissas!$C$13+BF29*Premissas!$F$13/12+BG29*Premissas!$C$14+BH29*Premissas!$F$14/12 -> 21200.282 | BJ29: =BI29*12 -> 254403.38 | BK29: =IFERROR(BI29/BD29,0) -> 62.719269 | BL29: =BI29*Premissas!$C$30 -> 1272.0169 | BM29: =BI29*Premissas!$C$28+CF29*Premissas!$C$29 -> 871.72627 | BN29: =BD29*Premissas!$C$31 -> 169.00932 | BO29: =BI29-BL29-BM29-BN29 -> 18887.529 | BP29: =IFERROR(BO29/BI29,0) -> 0.89090935 | BQ29: =SUMPRODUCT(Premissas!$C$42:$C$61,--(Premissas!$D$42:$D$61<=AY29)) -> 3395 | BR29: =Premissas!$C$34*(1+Premissas!$C$35)^(AY29-1) -> 2960.3798 | BS29: =BA29*Premissas!$C$36*Premissas!$C$37 -> 227.54543 | BT29: =BL29+BM29+BN29+BQ29+BR29+BS29 -> 8895.6777 | BU29: =BI29-BT29 -> 12304.604 | BV29: =N(BV28)+BU29 -> 62578.916 | BW29: =IFERROR((BR29+BS29)/BA29,0) -> 84.060361 | BX29: =IFERROR(BQ29/(BO29/BD29),0) -> 60.758252 | BY29: =BA29*(1-Premissas!$D$23)*(1-Premissas!$D$24) -> 22.754543 | BZ29: =BA29*(1-Premissas!$D$23)*Premissas!$D$24 -> 5.6886358 | CA29: =BA29*Premissas!$D$23*(1-Premissas!$D$24) -> 7.5848478 | CB29: =BA29*Premissas!$D$23*Premissas!$D$24 -> 1.8962119 | CC29: =BZ29+IF(AY29>12,INDEX($BZ$6:$BZ$29,AY29-12)*Premissas!$D$22,0) -> 7.3304204 | CD29: =CB29+IF(AY29>12,INDEX($CB$6:$CB$29,AY29-12)*Premissas!$D$22,0) -> 2.4434735 | CE29: =IF(AY29>12,(INDEX($BZ$6:$BZ$29,AY29-12)+INDEX($CB$6:$CB$29,AY29-12))*(1-Premissas!$D$22),0) -> 1.1787171 | CF29: =BE29+BG29+CC29+CD29 -> 264.72738 | CG29: =IF(BU29>0,AY29,"") -> 24 | CH29: =BE29*Premissas!$C$13+BG29*Premissas!$C$14 -> 16673.958 | CI29: =CC29*Premissas!$F$13+CD29*Premissas!$F$14 -> 6391.1003 | CJ29: =CH29+CI29 -> 23065.059 | CK29: =CJ29*Premissas!$C$30 -> 1383.9035 | CL29: =CJ29*Premissas!$C$28+CF29*Premissas!$C$29 -> 936.99347 | CM29: =BN29 -> 169.00932 | CN29: =BQ29 -> 3395 | CO29: =BR29+BS29 -> 3187.9252 | CP29: =CK29+CL29+CM29+CN29+CO29 -> 9072.8315 | CQ29: =CJ29-CP29 -> 13992.227 | CR29: =IF(AY29=1,Premissas!$C$8,N(CR28))+CQ29 -> 88375.441 | CS29: =BF29*Premissas!$F$13/12+BH29*Premissas!$F$14/12 -> 4526.3233 | CT29: =N(CT28)+CI29-CS29 -> 28504.448 | CV29: =CV28+1 -> 24 | CW29: =EDATE(Premissas!$C$7,CV29-1) -> 46997 | CX29: =Premissas!$E$19*(1+Premissas!$E$20)^(CV29-1) -> 203.28521 | CY29: =IFERROR(CX29/Premissas!$E$25,0) -> 677.61736 | CZ29: =(N(DB28)+N(DD28))*Premissas!$E$21+EB29 -> 30.548381 | DA29: =DB29+DC29+DD29+DE29 -> 1538.7836 | DB29: =N(DB28)*(1-Premissas!$E$21)+DV29 -> 668.72313 | DC29: =SUM(INDEX($DZ$6:$DZ$29,MAX(1,CV29-11)):INDEX($DZ$6:$DZ$29,CV29)) -> 331.4862 | DD29: =N(DD28)*(1-Premissas!$E$21)+DX29 -> 360.08169 | DE29: =SUM(INDEX($EA$6:$EA$29,MAX(1,CV29-11)):INDEX($EA$6:$EA$29,CV29)) -> 178.49257 | DF29: =DB29*Premissas!$C$13+DC29*Premissas!$F$13/12+DD29*Premissas!$C$14+DE29*Premissas!$F$14/12 -> 99235.94 | DG29: =DF29*12 -> 1190831.3 | DH29: =IFERROR(DF29/DA29,0) -> 64.489861 | DI29: =DF29*Premissas!$C$30 -> 5954.1564 | DJ29: =DF29*Premissas!$C$28+EC29*Premissas!$C$29 -> 4013.3914 | DK29: =DA29*Premissas!$C$31 -> 769.39179 | DL29: =DF29-DI29-DJ29-DK29 -> 88499.001 | DM29: =IFERROR(DL29/DF29,0) -> 0.89180392 | DN29: =SUMPRODUCT(Premissas!$C$42:$C$61,--(Premissas!$D$42:$D$61<=CV29)) -> 3395 | DO29: =Premissas!$C$34*(1+Premissas!$C$35)^(CV29-1) -> 2960.3798 | DP29: =CX29*Premissas!$C$36*Premissas!$C$37 -> 1219.7113 | DQ29: =DI29+DJ29+DK29+DN29+DO29+DP29 -> 18312.031 | DR29: =DF29-DQ29 -> 80923.91 | DS29: =N(DS28)+DR29 -> 556251.74 | DT29: =IFERROR((DO29+DP29)/CX29,0) -> 20.562691 | DU29: =IFERROR(DN29/(DL29/DA29),0) -> 59.030839 | DV29: =CX29*(1-Premissas!$E$23)*(1-Premissas!$E$24) -> 92.49477 | DW29: =CX29*(1-Premissas!$E$23)*Premissas!$E$24 -> 39.640616 | DX29: =CX29*Premissas!$E$23*(1-Premissas!$E$24) -> 49.804876 | DY29: =CX29*Premissas!$E$23*Premissas!$E$24 -> 21.344947 | DZ29: =DW29+IF(CV29>12,INDEX($DW$6:$DW$29,CV29-12)*Premissas!$E$22,0) -> 47.780423 | EA29: =DY29+IF(CV29>12,INDEX($DY$6:$DY$29,CV29-12)*Premissas!$E$22,0) -> 25.72792 | EB29: =IF(CV29>12,(INDEX($DW$6:$DW$29,CV29-12)+INDEX($DY$6:$DY$29,CV29-12))*(1-Premissas!$E$22),0) -> 3.130695 | EC29: =DB29+DD29+DZ29+EA29 -> 1102.3132 | ED29: =IF(DR29>0,CV29,"") -> 24 | EE29: =DB29*Premissas!$C$13+DD29*Premissas!$C$14 -> 70370.25 | EF29: =DZ29*Premissas!$F$13+EA29*Premissas!$F$14 -> 49928.41 | EG29: =EE29+EF29 -> 120298.66 | EH29: =EG29*Premissas!$C$30 -> 7217.9196 | EI29: =EG29*Premissas!$C$28+EC29*Premissas!$C$29 -> 4750.5865 | EJ29: =DK29 -> 769.39179 | EK29: =DN29 -> 3395 | EL29: =DO29+DP29 -> 4180.091 | EM29: =EH29+EI29+EJ29+EK29+EL29 -> 20312.989 | EN29: =EG29-EM29 -> 99985.671 | EO29: =IF(CV29=1,Premissas!$C$8,N(EO28))+EN29 -> 734161.51 | EP29: =DC29*Premissas!$F$13/12+DE29*Premissas!$F$14/12 -> 28865.691 | EQ29: =N(EQ28)+EF29-EP29 -> 196585.38
D30: =SUM(D6:D29) -> 137.70588 | E30: =SUM(E6:E29) -> 1377.0588 | F30: =SUM(F6:F29) -> 64.669918 | L30: =SUM(L6:L29) -> 59192.974 | O30: =SUM(O6:O29) -> 3551.5785 | P30: =SUM(P6:P29) -> 2489.0414 | Q30: =SUM(Q6:Q29) -> 485.16797 | R30: =SUM(R6:R29) -> 52667.187 | T30: =SUM(T6:T29) -> 74280 | U30: =SUM(U6:U29) -> 51639.705 | V30: =SUM(V6:V29) -> 826.23529 | W30: =SUM(W6:W29) -> 133271.73 | X30: =SUM(X6:X29) -> -74078.754 | AB30: =SUM(AB6:AB29) -> 105.345 | AC30: =SUM(AC6:AC29) -> 11.705 | AD30: =SUM(AD6:AD29) -> 18.590294 | AE30: =SUM(AE6:AE29) -> 2.0655882 | AF30: =SUM(AF6:AF29) -> 14.117645 | AG30: =SUM(AG6:AG29) -> 2.4913491 | AH30: =SUM(AH6:AH29) -> 2.8384059 | AI30: =SUM(AI6:AI29) -> 851.60667 | AK30: =SUM(AK6:AK29) -> 52103.855 | AL30: =SUM(AL6:AL29) -> 10439.899 | AM30: =SUM(AM6:AM29) -> 62543.754 | AN30: =SUM(AN6:AN29) -> 3752.6252 | AO30: =SUM(AO6:AO29) -> 2606.3187 | AP30: =SUM(AP6:AP29) -> 485.16797 | AQ30: =SUM(AQ6:AQ29) -> 74280 | AR30: =SUM(AR6:AR29) -> 52465.941 | ... AT30: =SUM(AT6:AT29) -> -71046.299 | AV30: =SUM(AV6:AV29) -> 7089.1193 | BA30: =SUM(BA6:BA29) -> 465.41337 | BB30: =SUM(BB6:BB29) -> 2327.0668 | BC30: =SUM(BC6:BC29) -> 127.39474 | BI30: =SUM(BI6:BI29) -> 214730.24 | BL30: =SUM(BL6:BL29) -> 12883.815 | BM30: =SUM(BM6:BM29) -> 8845.5088 | BN30: =SUM(BN6:BN29) -> 1709.8181 | BO30: =SUM(BO6:BO29) -> 191291.1 | BQ30: =SUM(BQ6:BQ29) -> 74280 | BR30: =SUM(BR6:BR29) -> 51639.705 | BS30: =SUM(BS6:BS29) -> 2792.4802 | BT30: =SUM(BT6:BT29) -> 152151.33 | BU30: =SUM(BU6:BU29) -> 62578.916 | BY30: =SUM(BY6:BY29) -> 279.24802 | BZ30: =SUM(BZ6:BZ29) -> 69.812005 | CA30: =SUM(CA6:CA29) -> 93.082673 | CB30: =SUM(CB6:CB29) -> 23.270668 | CC30: =SUM(CC6:CC29) -> 83.764997 | CD30: =SUM(CD6:CD29) -> 27.921666 | CE30: =SUM(CE6:CE29) -> 10.017533 | CF30: =SUM(CF6:CF29) -> 2714.1842 | CH30: =SUM(CH6:CH29) -> 170203.34 | CI30: =SUM(CI6:CI29) -> 73031.35 | CJ30: =SUM(CJ6:CJ29) -> 243234.69 | CK30: =SUM(CK6:CK29) -> 14594.081 | CL30: =SUM(CL6:CL29) -> 9843.1644 | CM30: =SUM(CM6:CM29) -> 1709.8181 | CN30: =SUM(CN6:CN29) -> 74280 | CO30: =SUM(CO6:CO29) -> 54432.186 | ... CQ30: =SUM(CQ6:CQ29) -> 88375.441 | CS30: =SUM(CS6:CS29) -> 44526.902 | CX30: =SUM(CX6:CX29) -> 1772.3286 | CY30: =SUM(CY6:CY29) -> 5907.7621 | CZ30: =SUM(CZ6:CZ29) -> 233.54503 | DF30: =SUM(DF6:DF29) -> 776897.43 | DI30: =SUM(DI6:DI29) -> 46613.846 | DJ30: =SUM(DJ6:DJ29) -> 31458.439 | DK30: =SUM(DK6:DK29) -> 6019.7235 | DL30: =SUM(DL6:DL29) -> 692805.42 | DN30: =SUM(DN6:DN29) -> 74280 | DO30: =SUM(DO6:DO29) -> 51639.705 | DP30: =SUM(DP6:DP29) -> 10633.972 | DQ30: =SUM(DQ6:DQ29) -> 220645.69 | DR30: =SUM(DR6:DR29) -> 556251.74 | DV30: =SUM(DV6:DV29) -> 806.40952 | DW30: =SUM(DW6:DW29) -> 345.60408 | DX30: =SUM(DX6:DX29) -> 434.22051 | DY30: =SUM(DY6:DY29) -> 186.0945 | DZ30: =SUM(DZ6:DZ29) -> 402.07561 | EA30: =SUM(EA6:EA29) -> 216.50225 | EB30: =SUM(EB6:EB29) -> 21.71982 | EC30: =SUM(EC6:EC29) -> 8708.2231 | EE30: =SUM(EE6:EE29) -> 553331.73 | EF30: =SUM(EF6:EF29) -> 420151.08 | EG30: =SUM(EG6:EG29) -> 973482.81 | EH30: =SUM(EH6:EH29) -> 58408.969 | EI30: =SUM(EI6:EI29) -> 38338.928 | EJ30: =SUM(EJ6:EJ29) -> 6019.7235 | EK30: =SUM(EK6:EK29) -> 74280 | EL30: =SUM(EL6:EL29) -> 62273.677 | ... EN30: =SUM(EN6:EN29) -> 734161.51 | EP30: =SUM(EP6:EP29) -> 223565.69
