Workbook

Sheet Painel
B1: ⚙ Premissas | E1: ✎ Meu Mês | H1: ↗ Projeção
B2: ="SAIAÊ · PAINEL · CENÁRIO "&UPPER(Premissas!$C$8) -> SAIAÊ · PAINEL · CENÁRIO REALISTA
B3: Como usar: 1) Premissas — ajuste uma vez. 2) Meu Mês — no fim de cada mês, lance 6 números. 3) Painel — veja se está no rumo. | Q3: Lançar o mês →
B5: O PLANO · O NEGÓCIO SE PAGA?
B6: EQUILÍBRIO | E6: CAPITAL NECESSÁRIO | H6: 1º MÊS COM LUCRO | K6: LTV / CAC | N6: CLIENTES — MÊS 12 | Q6: MRR — MÊS 12
B7: =IFERROR(ROUNDUP(Premissas!$C$43/Premissas!$C$41,0),0) -> 0 | E7: =MAX(0,-MIN(Projeção!$K$6:$K$29)) -> 0 | H7: =IF(COUNT(Projeção!$L$6:$L$29)=0,"Não atinge",INDEX(Projeção!$C$6:$C$29,MIN(Projeção!$L$6:$L$29))) -> Não atinge | K7: =IFERROR((Premissas!$C$41/Premissas!$F$19)/(Premissas!$C$25*24/Projeção!$D$30),0) -> 0 | N7: =Projeção!$F$17 -> 0 | Q7: =Projeção!$G$17 -> 0
B8: pagam fixos + anúncios | E8: maior buraco no caixa | H8: no cenário em uso | K8: =IFERROR(Premissas!$C$41/Premissas!$F$19,0) -> 0 | N8: =Projeção!$F$29 -> 0 | Q8: =Projeção!$G$29 -> 0
B10: A REALIDADE · O QUE VOCÊ LANÇOU NO MEU MÊS
B11: MESES LANÇADOS | E11: CLIENTES REAL × PLANO | H11: CHURN REAL | K11: CAC REAL | N11: SOBROU NO CAIXA | Q11: CAIXA NO PLANO
B12: =COUNT('Meu Mês'!$D$6:$D$29) -> 0 | E12: =IF(COUNT('Meu Mês'!$D$6:$D$29)=0,"—",IFERROR(INDEX('Meu Mês'!$D$6:$D$29,COUNT('Meu Mês'!$D$6:$D$29))/INDEX('Meu Mês'!$J$6:$J$29,COUNT('Meu Mês'!$D$6:$D$29))-1,"—")) -> — | H12: =IFERROR(AVERAGE('Meu Mês'!$L$6:$L$29),"—") -> — | K12: =IFERROR(SUM('Meu Mês'!$I$6:$I$29)/SUM('Meu Mês'!$E$6:$E$29),"—") -> — | N12: =SUM('Meu Mês'!$N$6:$N$29) -> 0 | Q12: =SUMPRODUCT((Projeção!$B$6:$B$29<=COUNT('Meu Mês'!$D$6:$D$29))*Projeção!$J$6:$J$29) -> 0
B13: linhas preenchidas | E13: =IF(COUNT('Meu Mês'!$D$6:$D$29)=0,0,INDEX('Meu Mês'!$D$6:$D$29,COUNT('Meu Mês'!$D$6:$D$29))) -> 0 | H13: =Premissas!$F$19 -> 0 | K13: =IFERROR(Premissas!$C$25*24/Projeção!$D$30,0) -> 0 | N13: soma dos meses lançados | Q13: mesmos meses, projetado
B15: EVOLUÇÃO
B33: ALERTAS
B34: =IF(U34="","· Preencha as Premissas para ver este alerta",IF(U34,"✖ Você vai precisar de capital: o caixa fica negativo no começo (veja o card CAPITAL NECESSÁRIO)","✔ O caixa nunca fica negativo no plano")) -> · Preencha as Premissas para ver este alerta | U34: =IF(COUNT(Premissas!$C$17:$E$21)=0,"",E7>0)
B35: =IF(U35="","· Preencha as Premissas para ver este alerta",IF(U35,"✖ LTV/CAC abaixo de 3x — cada cliente devolve pouco do que custa para conquistar","✔ LTV/CAC saudável: cada cliente devolve 3x ou mais o que custou")) -> · Preencha as Premissas para ver este alerta | U35: =IF(COUNT(Premissas!$C$17:$E$21)=0,"",K7<3)
B36: =IF(U36="","· Preencha as Premissas para ver este alerta",IF(U36,"✖ Você está mais de 10% abaixo do plano em clientes — reveja anúncios ou churn","✔ Clientes dentro do plano (ou ainda sem lançamentos)")) -> · Preencha as Premissas para ver este alerta | U36: =IF(COUNT(Premissas!$C$17:$E$21)=0,"",AND(ISNUMBER(E12),E12<-0.1))
B38: Quer mais detalhe (plano anual separado, unit economics por plano, três cenários lado a lado)? Use a versão completa: Saiae_Financeiro.xlsx.

Sheet Premissas
B1: ⌂ Painel
B2: PREMISSAS · PREENCHA UMA VEZ
B3: Campos AMARELO-CLAROS = você preenche. Clique em cada um para ver uma dica.
B5: GERAL
B6: Mês de início | C6: =DATE(YEAR(TODAY()),MONTH(TODAY())+1,1) -> 46296 | D6: Primeiro mês de vendas
B7: Caixa inicial (R$) | D7: Dinheiro que já existe para bancar o começo
B8: Cenário em uso | C8: Realista | D8: Pessimista, Realista ou Otimista
B10: PREÇOS
B11: PLANO | C11: MENSAL | D11: DESCONTO ANUAL | E11: ANUAL (POR MÊS) | F11: ANUAL (COBRADO)
B12: Essencial | E12: =C12*(1-D12) -> 0 | F12: =ROUND(E12*12,2) -> 0
B13: Pro | E13: =C13*(1-D13) -> 0 | F13: =ROUND(E13*12,2) -> 0
B15: CLIENTES · POR CENÁRIO
B16: PREMISSA | C16: PESSIMISTA | D16: REALISTA | E16: OTIMISTA | F16: EM USO | G16: O QUE É
B17: Novos clientes no mês 1 | F17: =INDEX(C17:E17,MATCH($C$8,$C$16:$E$16,0)) -> 0 | G17: Assinaturas novas no primeiro mês
B18: Crescimento dos novos clientes (ao mês) | F18: =INDEX(C18:E18,MATCH($C$8,$C$16:$E$16,0)) -> 0 | G18: Ex.: 7% → 8; 8,6; 9,2 novos...
B19: Churn mensal | F19: =INDEX(C19:E19,MATCH($C$8,$C$16:$E$16,0)) -> 0 | G19: % dos clientes que cancelam por mês
B20: % no plano Pro | F20: =INDEX(C20:E20,MATCH($C$8,$C$16:$E$16,0)) -> 0 | G20: O restante fica no Essencial
B21: % que paga anual | F21: =INDEX(C21:E21,MATCH($C$8,$C$16:$E$16,0)) -> 0 | G21: O restante paga mensal
B23: CUSTOS
B24: Taxas sobre o faturamento (imposto + gateway) | D24: Ex.: Simples 6% + gateway 3,5%. Confirme com o contador.
B25: Anúncios por mês (R$) | D25: Meta/Google/Instagram + comissão de indicação
B27: CUSTOS FIXOS DO MÊS
B28: DESCRIÇÃO | C28: VALOR MENSAL
B29: Hospedagem, banco de dados e tempo real
B30: Domínio e e-mail
B31: Ferramentas (IA, design, site)
B32: WhatsApp de atendimento
B33: Pró-labore
B34: Contador
B37: TOTAL DE CUSTOS FIXOS | C37: =SUM(C29:C36) -> 0
B39: CALCULADO (não precisa mexer)
B40: Ticket médio por cliente/mês | C40: =(1-Premissas!$F$20)*((1-Premissas!$F$21)*C12+Premissas!$F$21*F12/12)+Premissas!$F$20*((1-Premissas!$F$21)*C13+Premissas!$F$21*F13/12) -> 0 | D40: Mistura de planos e de mensal/anual
B41: Sobra por cliente/mês (depois das taxas) | C41: =C40*(1-C24) -> 0 | D41: É o que cada cliente paga das contas
B42: Valor médio pago à vista no plano anual | C42: =(1-Premissas!$F$20)*F12+Premissas!$F$20*F13 -> 0 | D42: Entra de uma vez no caixa
B43: Contas do mês (fixos + anúncios) | C43: =C37+C25 -> 0

Sheet Meu Mês
B1: ⌂ Painel
B2: MEU MÊS · O QUE ACONTECEU DE VERDADE
B3: No fim de cada mês, preencha os 6 campos amarelo-claros da linha do mês. O resto compara com a projeção sozinho.
D4: VOCÊ LANÇA | J4: A PLANILHA CALCULA
B5: Nº | C5: MÊS | D5: CLIENTES ATIVOS (FIM DO MÊS) | E5: NOVOS | F5: CANCELADOS | G5: RECEBIDO (R$) | H5: GASTO TOTAL (R$) | I5: DESSE GASTO, ANÚNCIOS (R$) | J5: CLIENTES PROJETADOS | K5: REAL × PROJETADO | L5: CHURN REAL | M5: CAC REAL | N5: SOBROU NO CAIXA
B6: =Projeção!B6 -> 1 | C6: =Projeção!C6 -> 46296 | J6: =Projeção!F6 -> 0 | K6: =IF(D6="","",IFERROR(D6/J6-1,"")) | L6: =IF(OR(D6="",F6=""),"",IFERROR(F6/(D6-E6+F6),"")) | M6: =IF(OR(I6="",E6=""),"",IFERROR(I6/E6,"")) | N6: =IF(OR(G6="",H6=""),"",G6-H6)
B7: =Projeção!B7 -> 2 | C7: =Projeção!C7 -> 46327 | J7: =Projeção!F7 -> 0 | K7: =IF(D7="","",IFERROR(D7/J7-1,"")) | L7: =IF(OR(D7="",F7=""),"",IFERROR(F7/(D7-E7+F7),"")) | M7: =IF(OR(I7="",E7=""),"",IFERROR(I7/E7,"")) | N7: =IF(OR(G7="",H7=""),"",G7-H7)
B8: =Projeção!B8 -> 3 | C8: =Projeção!C8 -> 46357 | J8: =Projeção!F8 -> 0 | K8: =IF(D8="","",IFERROR(D8/J8-1,"")) | L8: =IF(OR(D8="",F8=""),"",IFERROR(F8/(D8-E8+F8),"")) | M8: =IF(OR(I8="",E8=""),"",IFERROR(I8/E8,"")) | N8: =IF(OR(G8="",H8=""),"",G8-H8)
B9: =Projeção!B9 -> 4 | C9: =Projeção!C9 -> 46388 | J9: =Projeção!F9 -> 0 | K9: =IF(D9="","",IFERROR(D9/J9-1,"")) | L9: =IF(OR(D9="",F9=""),"",IFERROR(F9/(D9-E9+F9),"")) | M9: =IF(OR(I9="",E9=""),"",IFERROR(I9/E9,"")) | N9: =IF(OR(G9="",H9=""),"",G9-H9)
B10: =Projeção!B10 -> 5 | C10: =Projeção!C10 -> 46419 | J10: =Projeção!F10 -> 0 | K10: =IF(D10="","",IFERROR(D10/J10-1,"")) | L10: =IF(OR(D10="",F10=""),"",IFERROR(F10/(D10-E10+F10),"")) | M10: =IF(OR(I10="",E10=""),"",IFERROR(I10/E10,"")) | N10: =IF(OR(G10="",H10=""),"",G10-H10)
B11: =Projeção!B11 -> 6 | C11: =Projeção!C11 -> 46447 | J11: =Projeção!F11 -> 0 | K11: =IF(D11="","",IFERROR(D11/J11-1,"")) | L11: =IF(OR(D11="",F11=""),"",IFERROR(F11/(D11-E11+F11),"")) | M11: =IF(OR(I11="",E11=""),"",IFERROR(I11/E11,"")) | N11: =IF(OR(G11="",H11=""),"",G11-H11)
B12: =Projeção!B12 -> 7 | C12: =Projeção!C12 -> 46478 | J12: =Projeção!F12 -> 0 | K12: =IF(D12="","",IFERROR(D12/J12-1,"")) | L12: =IF(OR(D12="",F12=""),"",IFERROR(F12/(D12-E12+F12),"")) | M12: =IF(OR(I12="",E12=""),"",IFERROR(I12/E12,"")) | N12: =IF(OR(G12="",H12=""),"",G12-H12)
B13: =Projeção!B13 -> 8 | C13: =Projeção!C13 -> 46508 | J13: =Projeção!F13 -> 0 | K13: =IF(D13="","",IFERROR(D13/J13-1,"")) | L13: =IF(OR(D13="",F13=""),"",IFERROR(F13/(D13-E13+F13),"")) | M13: =IF(OR(I13="",E13=""),"",IFERROR(I13/E13,"")) | N13: =IF(OR(G13="",H13=""),"",G13-H13)
B14: =Projeção!B14 -> 9 | C14: =Projeção!C14 -> 46539 | J14: =Projeção!F14 -> 0 | K14: =IF(D14="","",IFERROR(D14/J14-1,"")) | L14: =IF(OR(D14="",F14=""),"",IFERROR(F14/(D14-E14+F14),"")) | M14: =IF(OR(I14="",E14=""),"",IFERROR(I14/E14,"")) | N14: =IF(OR(G14="",H14=""),"",G14-H14)
B15: =Projeção!B15 -> 10 | C15: =Projeção!C15 -> 46569 | J15: =Projeção!F15 -> 0 | K15: =IF(D15="","",IFERROR(D15/J15-1,"")) | L15: =IF(OR(D15="",F15=""),"",IFERROR(F15/(D15-E15+F15),"")) | M15: =IF(OR(I15="",E15=""),"",IFERROR(I15/E15,"")) | N15: =IF(OR(G15="",H15=""),"",G15-H15)
B16: =Projeção!B16 -> 11 | C16: =Projeção!C16 -> 46600 | J16: =Projeção!F16 -> 0 | K16: =IF(D16="","",IFERROR(D16/J16-1,"")) | L16: =IF(OR(D16="",F16=""),"",IFERROR(F16/(D16-E16+F16),"")) | M16: =IF(OR(I16="",E16=""),"",IFERROR(I16/E16,"")) | N16: =IF(OR(G16="",H16=""),"",G16-H16)
B17: =Projeção!B17 -> 12 | C17: =Projeção!C17 -> 46631 | J17: =Projeção!F17 -> 0 | K17: =IF(D17="","",IFERROR(D17/J17-1,"")) | L17: =IF(OR(D17="",F17=""),"",IFERROR(F17/(D17-E17+F17),"")) | M17: =IF(OR(I17="",E17=""),"",IFERROR(I17/E17,"")) | N17: =IF(OR(G17="",H17=""),"",G17-H17)
... B29: =Projeção!B29 -> 24 | C29: =Projeção!C29 -> 46997 | J29: =Projeção!F29 -> 0 | K29: =IF(D29="","",IFERROR(D29/J29-1,"")) | L29: =IF(OR(D29="",F29=""),"",IFERROR(F29/(D29-E29+F29),"")) | M29: =IF(OR(I29="",E29=""),"",IFERROR(I29/E29,"")) | N29: =IF(OR(G29="",H29=""),"",G29-H29)
B31: Lance uma linha por mês, sempre no fim do mês.
B32: Churn real = cancelados ÷ clientes no início do mês. CAC real = anúncios ÷ novos clientes. Real × projetado em vermelho = mais de 10% abaixo do planejado.

Sheet Projeção
B1: ⌂ Painel
B2: ="PROJEÇÃO 24 MESES · CENÁRIO "&UPPER(Premissas!$C$8) -> PROJEÇÃO 24 MESES · CENÁRIO REALISTA
B3: Mês a mês no cenário em uso. O plano anual entra inteiro no caixa quando é vendido ou renovado. Tudo automático.
B5: Nº | C5: MÊS | D5: NOVOS | E5: CANCELADOS | F5: CLIENTES ATIVOS | G5: MRR | H5: CUSTOS | I5: LUCRO | J5: CAIXA DO MÊS | K5: CAIXA ACUMULADO | L5: MÊS COM LUCRO?
B6: =1 -> 1 | C6: =EDATE(Premissas!$C$6,B6-1) -> 46296 | D6: =Premissas!$F$17*(1+Premissas!$F$18)^(B6-1) -> 0 | E6: =N(F5)*Premissas!$F$19 -> 0 | F6: =N(F5)-E6+D6 -> 0 | G6: =F6*Premissas!$C$40 -> 0 | H6: =G6*Premissas!$C$24+Premissas!$C$43 -> 0 | I6: =G6-H6 -> 0 | J6: =I6+(D6+IF(B6>12,INDEX($D$6:$D$29,B6-12)*(1-Premissas!$F$19)^12,0))*Premissas!$F$21*Premissas!$C$42-F6*Premissas!$F$21*Premissas!$C$42/12 -> 0 | K6: =IF(B6=1,Premissas!$C$7,N(K5))+J6 -> 0 | L6: =IF(I6>0,B6,"")
B7: =B6+1 -> 2 | C7: =EDATE(Premissas!$C$6,B7-1) -> 46327 | D7: =Premissas!$F$17*(1+Premissas!$F$18)^(B7-1) -> 0 | E7: =N(F6)*Premissas!$F$19 -> 0 | F7: =N(F6)-E7+D7 -> 0 | G7: =F7*Premissas!$C$40 -> 0 | H7: =G7*Premissas!$C$24+Premissas!$C$43 -> 0 | I7: =G7-H7 -> 0 | J7: =I7+(D7+IF(B7>12,INDEX($D$6:$D$29,B7-12)*(1-Premissas!$F$19)^12,0))*Premissas!$F$21*Premissas!$C$42-F7*Premissas!$F$21*Premissas!$C$42/12 -> 0 | K7: =IF(B7=1,Premissas!$C$7,N(K6))+J7 -> 0 | L7: =IF(I7>0,B7,"")
B8: =B7+1 -> 3 | C8: =EDATE(Premissas!$C$6,B8-1) -> 46357 | D8: =Premissas!$F$17*(1+Premissas!$F$18)^(B8-1) -> 0 | E8: =N(F7)*Premissas!$F$19 -> 0 | F8: =N(F7)-E8+D8 -> 0 | G8: =F8*Premissas!$C$40 -> 0 | H8: =G8*Premissas!$C$24+Premissas!$C$43 -> 0 | I8: =G8-H8 -> 0 | J8: =I8+(D8+IF(B8>12,INDEX($D$6:$D$29,B8-12)*(1-Premissas!$F$19)^12,0))*Premissas!$F$21*Premissas!$C$42-F8*Premissas!$F$21*Premissas!$C$42/12 -> 0 | K8: =IF(B8=1,Premissas!$C$7,N(K7))+J8 -> 0 | L8: =IF(I8>0,B8,"")
B9: =B8+1 -> 4 | C9: =EDATE(Premissas!$C$6,B9-1) -> 46388 | D9: =Premissas!$F$17*(1+Premissas!$F$18)^(B9-1) -> 0 | E9: =N(F8)*Premissas!$F$19 -> 0 | F9: =N(F8)-E9+D9 -> 0 | G9: =F9*Premissas!$C$40 -> 0 | H9: =G9*Premissas!$C$24+Premissas!$C$43 -> 0 | I9: =G9-H9 -> 0 | J9: =I9+(D9+IF(B9>12,INDEX($D$6:$D$29,B9-12)*(1-Premissas!$F$19)^12,0))*Premissas!$F$21*Premissas!$C$42-F9*Premissas!$F$21*Premissas!$C$42/12 -> 0 | K9: =IF(B9=1,Premissas!$C$7,N(K8))+J9 -> 0 | L9: =IF(I9>0,B9,"")
B10: =B9+1 -> 5 | C10: =EDATE(Premissas!$C$6,B10-1) -> 46419 | D10: =Premissas!$F$17*(1+Premissas!$F$18)^(B10-1) -> 0 | E10: =N(F9)*Premissas!$F$19 -> 0 | F10: =N(F9)-E10+D10 -> 0 | G10: =F10*Premissas!$C$40 -> 0 | H10: =G10*Premissas!$C$24+Premissas!$C$43 -> 0 | I10: =G10-H10 -> 0 | J10: =I10+(D10+IF(B10>12,INDEX($D$6:$D$29,B10-12)*(1-Premissas!$F$19)^12,0))*Premissas!$F$21*Premissas!$C$42-F10*Premissas!$F$21*Premissas!$C$42/12 -> 0 | K10: =IF(B10=1,Premissas!$C$7,N(K9))+J10 -> 0 | L10: =IF(I10>0,B10,"")
B11: =B10+1 -> 6 | C11: =EDATE(Premissas!$C$6,B11-1) -> 46447 | D11: =Premissas!$F$17*(1+Premissas!$F$18)^(B11-1) -> 0 | E11: =N(F10)*Premissas!$F$19 -> 0 | F11: =N(F10)-E11+D11 -> 0 | G11: =F11*Premissas!$C$40 -> 0 | H11: =G11*Premissas!$C$24+Premissas!$C$43 -> 0 | I11: =G11-H11 -> 0 | J11: =I11+(D11+IF(B11>12,INDEX($D$6:$D$29,B11-12)*(1-Premissas!$F$19)^12,0))*Premissas!$F$21*Premissas!$C$42-F11*Premissas!$F$21*Premissas!$C$42/12 -> 0 | K11: =IF(B11=1,Premissas!$C$7,N(K10))+J11 -> 0 | L11: =IF(I11>0,B11,"")
B12: =B11+1 -> 7 | C12: =EDATE(Premissas!$C$6,B12-1) -> 46478 | D12: =Premissas!$F$17*(1+Premissas!$F$18)^(B12-1) -> 0 | E12: =N(F11)*Premissas!$F$19 -> 0 | F12: =N(F11)-E12+D12 -> 0 | G12: =F12*Premissas!$C$40 -> 0 | H12: =G12*Premissas!$C$24+Premissas!$C$43 -> 0 | I12: =G12-H12 -> 0 | J12: =I12+(D12+IF(B12>12,INDEX($D$6:$D$29,B12-12)*(1-Premissas!$F$19)^12,0))*Premissas!$F$21*Premissas!$C$42-F12*Premissas!$F$21*Premissas!$C$42/12 -> 0 | K12: =IF(B12=1,Premissas!$C$7,N(K11))+J12 -> 0 | L12: =IF(I12>0,B12,"")
B13: =B12+1 -> 8 | C13: =EDATE(Premissas!$C$6,B13-1) -> 46508 | D13: =Premissas!$F$17*(1+Premissas!$F$18)^(B13-1) -> 0 | E13: =N(F12)*Premissas!$F$19 -> 0 | F13: =N(F12)-E13+D13 -> 0 | G13: =F13*Premissas!$C$40 -> 0 | H13: =G13*Premissas!$C$24+Premissas!$C$43 -> 0 | I13: =G13-H13 -> 0 | J13: =I13+(D13+IF(B13>12,INDEX($D$6:$D$29,B13-12)*(1-Premissas!$F$19)^12,0))*Premissas!$F$21*Premissas!$C$42-F13*Premissas!$F$21*Premissas!$C$42/12 -> 0 | K13: =IF(B13=1,Premissas!$C$7,N(K12))+J13 -> 0 | L13: =IF(I13>0,B13,"")
B14: =B13+1 -> 9 | C14: =EDATE(Premissas!$C$6,B14-1) -> 46539 | D14: =Premissas!$F$17*(1+Premissas!$F$18)^(B14-1) -> 0 | E14: =N(F13)*Premissas!$F$19 -> 0 | F14: =N(F13)-E14+D14 -> 0 | G14: =F14*Premissas!$C$40 -> 0 | H14: =G14*Premissas!$C$24+Premissas!$C$43 -> 0 | I14: =G14-H14 -> 0 | J14: =I14+(D14+IF(B14>12,INDEX($D$6:$D$29,B14-12)*(1-Premissas!$F$19)^12,0))*Premissas!$F$21*Premissas!$C$42-F14*Premissas!$F$21*Premissas!$C$42/12 -> 0 | K14: =IF(B14=1,Premissas!$C$7,N(K13))+J14 -> 0 | L14: =IF(I14>0,B14,"")
B15: =B14+1 -> 10 | C15: =EDATE(Premissas!$C$6,B15-1) -> 46569 | D15: =Premissas!$F$17*(1+Premissas!$F$18)^(B15-1) -> 0 | E15: =N(F14)*Premissas!$F$19 -> 0 | F15: =N(F14)-E15+D15 -> 0 | G15: =F15*Premissas!$C$40 -> 0 | H15: =G15*Premissas!$C$24+Premissas!$C$43 -> 0 | I15: =G15-H15 -> 0 | J15: =I15+(D15+IF(B15>12,INDEX($D$6:$D$29,B15-12)*(1-Premissas!$F$19)^12,0))*Premissas!$F$21*Premissas!$C$42-F15*Premissas!$F$21*Premissas!$C$42/12 -> 0 | K15: =IF(B15=1,Premissas!$C$7,N(K14))+J15 -> 0 | L15: =IF(I15>0,B15,"")
B16: =B15+1 -> 11 | C16: =EDATE(Premissas!$C$6,B16-1) -> 46600 | D16: =Premissas!$F$17*(1+Premissas!$F$18)^(B16-1) -> 0 | E16: =N(F15)*Premissas!$F$19 -> 0 | F16: =N(F15)-E16+D16 -> 0 | G16: =F16*Premissas!$C$40 -> 0 | H16: =G16*Premissas!$C$24+Premissas!$C$43 -> 0 | I16: =G16-H16 -> 0 | J16: =I16+(D16+IF(B16>12,INDEX($D$6:$D$29,B16-12)*(1-Premissas!$F$19)^12,0))*Premissas!$F$21*Premissas!$C$42-F16*Premissas!$F$21*Premissas!$C$42/12 -> 0 | K16: =IF(B16=1,Premissas!$C$7,N(K15))+J16 -> 0 | L16: =IF(I16>0,B16,"")
B17: =B16+1 -> 12 | C17: =EDATE(Premissas!$C$6,B17-1) -> 46631 | D17: =Premissas!$F$17*(1+Premissas!$F$18)^(B17-1) -> 0 | E17: =N(F16)*Premissas!$F$19 -> 0 | F17: =N(F16)-E17+D17 -> 0 | G17: =F17*Premissas!$C$40 -> 0 | H17: =G17*Premissas!$C$24+Premissas!$C$43 -> 0 | I17: =G17-H17 -> 0 | J17: =I17+(D17+IF(B17>12,INDEX($D$6:$D$29,B17-12)*(1-Premissas!$F$19)^12,0))*Premissas!$F$21*Premissas!$C$42-F17*Premissas!$F$21*Premissas!$C$42/12 -> 0 | K17: =IF(B17=1,Premissas!$C$7,N(K16))+J17 -> 0 | L17: =IF(I17>0,B17,"")
B18: =B17+1 -> 13 | C18: =EDATE(Premissas!$C$6,B18-1) -> 46661 | D18: =Premissas!$F$17*(1+Premissas!$F$18)^(B18-1) -> 0 | E18: =N(F17)*Premissas!$F$19 -> 0 | F18: =N(F17)-E18+D18 -> 0 | G18: =F18*Premissas!$C$40 -> 0 | H18: =G18*Premissas!$C$24+Premissas!$C$43 -> 0 | I18: =G18-H18 -> 0 | J18: =I18+(D18+IF(B18>12,INDEX($D$6:$D$29,B18-12)*(1-Premissas!$F$19)^12,0))*Premissas!$F$21*Premissas!$C$42-F18*Premissas!$F$21*Premissas!$C$42/12 -> 0 | K18: =IF(B18=1,Premissas!$C$7,N(K17))+J18 -> 0 | L18: =IF(I18>0,B18,"")
... B29: =B28+1 -> 24 | C29: =EDATE(Premissas!$C$6,B29-1) -> 46997 | D29: =Premissas!$F$17*(1+Premissas!$F$18)^(B29-1) -> 0 | E29: =N(F28)*Premissas!$F$19 -> 0 | F29: =N(F28)-E29+D29 -> 0 | G29: =F29*Premissas!$C$40 -> 0 | H29: =G29*Premissas!$C$24+Premissas!$C$43 -> 0 | I29: =G29-H29 -> 0 | J29: =I29+(D29+IF(B29>12,INDEX($D$6:$D$29,B29-12)*(1-Premissas!$F$19)^12,0))*Premissas!$F$21*Premissas!$C$42-F29*Premissas!$F$21*Premissas!$C$42/12 -> 0 | K29: =IF(B29=1,Premissas!$C$7,N(K28))+J29 -> 0 | L29: =IF(I29>0,B29,"")
B30: TOTAL | D30: =SUM(D6:D29) -> 0 | E30: =SUM(E6:E29) -> 0 | G30: =SUM(G6:G29) -> 0 | H30: =SUM(H6:H29) -> 0 | I30: =SUM(I6:I29) -> 0 | J30: =SUM(J6:J29) -> 0
